Workbook

Sheet UIO 2025
J2: INVENTARIO DE SERVIDORES VIRTUALIZADOS Y FISICOS UIO 2024
A5: Fecha de actualización:19/09/2025 | H5: Actualizado por: Evelyn Puetate
A7: CIUDAD | B7: ENCLOSURE | C7: SRV FISICOS | D7: SERIE | E7: IP DEL BLADE | F7: TOTAL SRV FISICOS | G7: CARACTERISTICAS | H7: SOPORTE | I7: # SRV VIRTUALES | J7: TIPO DE SERVIDOR | K7: SRV VIRTUALES | L7: APLICACIÓN | M7: IP INTERNA | N7: IP PUBLICA | O7: PROTECCIÓN DE TREND MCRO XDR - SRV | P7: CORTEX | Q7: Persona responsable del uso del SRV | R7: PANDORA | S7: SISTEMA OPERATIVO | T7: MEMORIA | U7: Espacio Disco | V7: Procesador | W7: SISTEMAS CRITICOS | X7: SERVIDOR PRODUCCIÓN / PREPRODUCCIÓN | Y7: BASE DE DATOS | Z7: VERSIÓN DB | AA7: COSTO SOPORTE | AB7: EMPRESA QUE DA SOPORTE | AC7: BACKUP SE REALIZA | AD7: PLATAFORMA DE BACKUP | AE7: POLITICA DE BACKUP
A8: UIO - SIMPLIVITY | B8: tvc-srv-esx1 | C8: ProLiant DL380 2 x Intel(R) Xeon(R) Gold 6230 CPU @ 2.10GHz x 20 Cores | D8: 2M211600MH | E8: 192.168.34.160 | F8: 4 | G8: Gen 10 1.5 TB RAM | H8: SI | I8: =COUNTIF(J9:J97,"=VIRTUAL") -> 89 | J8: VIRTUAL | K8: Fortiweb | L8: Firewall Waf | M8: 192.168.33.50 | N8: 200.63.213.18 | O8: - | P8: - | Q8: Luis Conteron / Guillermo Jurado | R8: NO | S8: Other 2.6.x Linux (64-bit) | T8: 8 | U8: 150 | V8: 8 | W8: ALTO | X8: PRODUCCIÓN | Y8: NA | Z8: NA | AC8: SI | AD8: Veritas | AE8: Veritas-FUllTue-Ret15_UIO_04
B9: tvc-srv-esx2 | C9: ProLiant DL381 2 x Intel(R) Xeon(R) Gold 6230 CPU @ 2.10GHz x 20 Cores | D9: 2M211600MG | E9: 192.168.34.162 | G9: Gen 10 1.5 TB RAM | H9: SI | J9: VIRTUAL | K9: OmniStackVC-192-168-34-161 | L9: Servidor propio de trabajo SimpliVity | M9: 192.168.34.161 | O9: NO | P9: NO | Q9: Evelyn Puetate | R9: SI | S9: Ubuntu Linux (64-bit) | T9: 92 | U9: 209.96 | V9: 8 | W9: BAJO | X9: PRODUCCIÓN | Y9: NA | Z9: NA | AC9: NO es parte sistema operativo de Simplivity | AD9: - | AE9: NO es parte sistema operativo de Simplivity
B10: tvc-srv-esx3 | C10: ProLiant DL380 2 x Intel(R) Xeon(R) Gold 6238 CPU @ 2.10GHz x 22 Cores | D10: 2M232601ZG | E10: 192.168.34.164 | G10: Gen 10 1 TB RAM | H10: SI | J10: VIRTUAL | K10: OmniStackVC-192-168-34-163 | L10: Servidor propio de trabajo SimpliVity | M10: 192.168.34.163 | O10: NO | P10: NO | Q10: Evelyn Puetate | R10: SI | S10: Ubuntu Linux (64-bit) | T10: 92 | U10: 209.96 | V10: 8 | W10: BAJO | X10: PRODUCCIÓN | Y10: NA | Z10: NA | AC10: NO es parte sistema operativo de Simplivity | AD10: - | AE10: NO es parte sistema operativo de Simplivity
B11: tvc-srv-esx4 | C11: ProLiant DL380 2 x Intel(R) Xeon(R) Gold 6238 CPU @ 2.10GHz x 22 Cores | D11: 2M232601ZH | E11: 192.168.34.166 | G11: Gen 10 1 TB RAM | H11: SI | J11: VIRTUAL | K11: OmniStackVC-192-168-34-165 | L11: Servidor propio de trabajo SimpliVity | M11: 192.168.34.165 | O11: NO | P11: NO | Q11: Evelyn Puetate | R11: SI | S11: Ubuntu Linux (64-bit) | T11: 92 | U11: 209.96 | V11: 8 | W11: BAJO | X11: PRODUCCIÓN | Y11: NA | Z11: NA | AC11: NO es parte sistema operativo de Simplivity | AD11: - | AE11: NO es parte sistema operativo de Simplivity
J12: VIRTUAL | K12: OmniStackVC-192-168-34-167 | L12: Servidor propio de trabajo SimpliVity | M12: 192.168.34.167 | O12: NO | P12: NO | Q12: Evelyn Puetate | R12: SI | S12: Ubuntu Linux (64-bit) | T12: 92 | U12: 209.96 | V12: 8 | W12: BAJO | X12: PRODUCCIÓN | Y12: NA | Z12: NA | AC12: NO es parte sistema operativo de Simplivity | AD12: - | AE12: NO es parte sistema operativo de Simplivity
J13: VIRTUAL | K13: tvc-srv-adprint | L13: Administrador de impresoras UIO | M13: 192.168.21.17 | O13: SI | P13: - | Q13: Hector Miranda/Graciela Ortiz | R13: SI | S13: Microsoft Windows Server 2016 (64-bit) | T13: 16 | U13: 350 | V13: 4 | W13: MEDIO | X13: PRODUCCIÓN | Y13: NA | Z13: NA | AC13: SI | AD13: Veritas | AE13: Veritas-FUllWed-Ret15_UIO_08
J14: VIRTUAL | K14: tvc-srv-aduio2 | L14: Conector del AD | M14: 192.168.21.26 | N14: 200.63.213.27 | O14: SI | P14: - | Q14: Evelyn Puetate | R14: SI | S14: Microsoft Windows Server 2016 (64-bit) | T14: 20 | U14: 150 | V14: 4 | W14: ALTO | X14: PRODUCCIÓN | Y14: NA | Z14: NA | AC14: SI | AD14: Veritas | AE14: Veritas-FUllWed-Ret15_UIO_08
J15: VIRTUAL | K15: tvc-srv-aduio3 | L15: Active Directory secundario | M15: 192.168.21.27 | O15: SI | P15: - | Q15: Evelyn Puetate | R15: SI | S15: Microsoft Windows Server 2016 (64-bit) | T15: 20 | U15: 150 | V15: 4 | W15: ALTO | X15: PRODUCCIÓN | AC15: SI | AD15: Veritas | AE15: Veritas-FUllWed-Ret15_UIO_08
J16: VIRTUAL | K16: tvc-srv-agdi | L16: Pagina Web Agencia Digital, tmbn tiene xtrim.tv, xtrim.com.ec, Pagina de Ingreso de contrato para vendedores, proveedores y distribuidores - mixtrim.com.ec/IngresoContratos | M16: 192.168.21.243 | N16: 200.63.213.43 | O16: SI | P16: - | Q16: Hector Miranda /Administrador de aplicaciones | R16: SI | S16: Red Hat Enterprise Linux 7 (64-bit) | T16: 48 | U16: 180 | V16: 8 | W16: ALTO | X16: PRODUCCIÓN | Y16: MySQL | Z16: 5.6.28 Community Edition 64 bits | AC16: SI | AD16: Veritas | AE16: Veritas-FUllMon-Ret15_UIO_02
J17: VIRTUAL | K17: tvc-srv-amas | L17: Servidor de amas - Relacionado con las llamadas telefonicas. | M17: 192.168.21.31 | O17: SI | P17: - | Q17: Hector Miranda /Administrador de aplicaciones | R17: SI | S17: Windows 10 | T17: 8 | U17: 931.65 | V17: 4 | W17: BAJO | X17: PRODUCCIÓN | AC17: SI | AD17: Veritas | AE17: Veritas-FUllMon-Ret15_UIO_02
J18: VIRTUAL | K18: tvc-srv-apjaira | L18: Mesa de Servicios - Flujos internos. (con el tiempo se dará de baja) | M18: 192.168.21.35 | O18: SI | P18: - | Q18: Hector Miranda /Administrador de aplicaciones | R18: SI | S18: Microsoft Windows Server 2016 (64-bit) | T18: 20 | U18: 400 | V18: 4 | W18: BAJO | X18: PRODUCCIÓN | Y18: NA | Z18: NA | AC18: SI | AD18: Veritas | AE18: Veritas-FUllThu-Ret15_UIO_09
J19: VIRTUAL | K19: tvc-srv-appadm | L19: Aplicaciones del sistema de nomina - Datalife | M19: 192.168.21.101 | O19: - | P19: SI | Q19: Jaqueline Andrade/Carlos Ayala/Christian Castillo | R19: SI | S19: Microsoft Windows Server 2022 (64-bit) | T19: 16 | U19: 160 | V19: 2 | W19: ALTO | X19: PRODUCCIÓN | AC19: SI | AD19: Veritas | AE19: Veritas-FUllWed-Ret15_UIO_06
J20: VIRTUAL | K20: tvc-srv-as2back - ELIMINADO | L20: SERVIDOR DE RESPALDO DEL AS2, DE LA INFOPRMACIÓN QUE ESTA EN EL ONEDRIVE. (3ER RESPALDO) | M20: 192.168.21.15 | O20: - | P20: SI | Q20: Jose Fernandez/Ivone Intriago | R20: SI | S20: Microsoft Windows Server 2022 (64-bit) | T20: 4 | U20: 300 | V20: 4 | W20: ALTO | X20: PRODUCCIÓN | AC20: SI | AD20: Veritas | AE20: Veritas-FUllMon-Ret15_UIO_00 Veritas-FullFri-Ret15_UIO_14
J21: VIRTUAL | K21: tvc-srv-autosrv | L21: Servidor autoservicios | M21: 192.168.21.16 | O21: - | P21: SI | Q21: Hector Miranda /Administrador de aplicaciones | R21: SI | S21: Ubuntu 22,04 LTS Linux (64-bit) | T21: 8 | U21: 100 | V21: 4 | W21: ALTO | X21: PRODUCCIÓN | Y21: NA | Z21: NA | AC21: SI | AD21: Veritas | AE21: Veritas-FUllTue-Ret15_UIO_05
J22: VIRTUAL | K22: tvc-srv-autosrvclon | M22: 192.168.21.20 | O22: - | P22: SI | Q22: Hector Miranda /Administrador de aplicaciones | R22: SI | S22: Ubuntu 22,04 LTS Linux (64-bit) | T22: 8 | U22: 100 | V22: 4 | W22: ALTO | X22: PRODUCCIÓN | Y22: NA | Z22: NA
J23: VIRTUAL | K23: tvc-srv-bdadm | L23: Base de datos de sistema de nomina | M23: 192.168.21.102 | O23: - | P23: SI | Q23: Jaqueline Andrade/Carlos Ayala/James Pesantes | R23: SI | S23: Microsoft Windows Server 2022 (64-bit) | T23: 16 | U23: 500 | V23: 4 | W23: ALTO | X23: PRODUCCIÓN | AC23: SI | AD23: veritas | AE23: Veritas-FUllWed-Ret15_UIO_06
J24: VIRTUAL | K24: xtr-srv-ansible-platform-gateway | L24: Ansible Plataform Gateway | M24: 192.168.21.6 | O24: - | P24: SI | Q24: Evelyn Puetate | R24: SI | S24: Red Hat Enterprise Linux 9 (64-bit) | T24: 16 | U24: 60 | V24: 4 | W24: MEDIO | X24: PRODUCCIÓN | AC24: SI | AD24: veritas | AE24: Veritas-FUllTue-Ret15_UIO_06
J25: VIRTUAL | K25: xtr-srv-ansible-automation-hub | L25: Ansible Private Automation Hub | M25: 192.168.21.7 | O25: - | P25: SI | Q25: Evelyn Puetate | R25: SI | S25: Red Hat Enterprise Linux 9 (64-bit) | T25: 16 | U25: 60 | V25: 4 | W25: MEDIO | X25: PRODUCCIÓN | AC25: SI | AD25: veritas | AE25: Veritas-FUllTue-Ret15_UIO_05
J26: VIRTUAL | K26: xtr-srv-ansible-controller-control | L26: Ansible Automation Controller | M26: 192.168.21.12 | O26: - | P26: SI | Q26: Evelyn Puetate | R26: SI | S26: Red Hat Enterprise Linux 9 (64-bit) | T26: 16 | U26: 180 | V26: 4 | W26: MEDIO | X26: PRODUCCIÓN | AC26: SI | AD26: veritas | AE26: Veritas-FUllTue-Ret15_UIO_04
J27: VIRTUAL | K27: xtr-srv-ansible-controller-execution | L27: Ansible Controller Excecution | M27: 192.168.21.28 | O27: - | P27: SI | Q27: Evelyn Puetate | R27: SI | S27: Red Hat Enterprise Linux 9 (64-bit) | T27: 16 | U27: 60 | V27: 4 | W27: MEDIO | X27: PRODUCCIÓN | AC27: SI | AD27: veritas | AE27: Veritas-FUllMon-Ret15_UIO_02
J28: VIRTUAL | K28: tvc-srv-ansible-pivot | L28: Ansible Pivot | M28: 192.168.21.4 | O28: - | P28: SI | Q28: Evelyn Puetate | R28: SI | S28: Microsoft Windows Server 2022 (64-bit) | T28: 8 | U28: 90 | V28: 4 | W28: MEDIO | X28: PRODUCCIÓN
J29: VIRTUAL | K29: tvc-srv-backupAS2 | L29: Backup AS2 | M29: 192.168.21.34 | P29: SI | Q29: Evelyn Puetate | R29: SI | S29: Microsoft Windows Server 2022 (64-bit) | T29: 16 | U29: 1240 | V29: 8 | W29: ALTO | X29: PRODUCCIÓN | AC29: SI | AD29: Veritas
J30: VIRTUAL | K30: tvc-srv-cluster3 | L30: Cluster base de datos | M30: 192.168.21.25 | O30: - | P30: SI | Q30: Carlos Ayala / James Pesantes | R30: SI | S30: Red Hat Enterprise Linux 9 (64-bit) | T30: 4 | U30: 400 | V30: 2 | W30: ALTO | X30: PRODUCCIÓN | Y30: NA | Z30: NA | AC30: SI | AD30: Veritas | AE30: Veritas-FUllTue-Ret15_UIO_05
J31: VIRTUAL | K31: tvc-srv-colecsoc | L31: Logs del SOC | M31: 192.168.21.236 | O31: - | P31: SI | Q31: Jose Fernandez/Alejandro Alvarez | R31: SI | S31: Red Hat Enterprise Linux 9.2 (64-bit) | T31: 8 | U31: 250 | V31: 4 | W31: ALTO | X31: PRODUCCIÓN | AC31: SI | AD31: Veritas | AE31: Veritas-FUllMon-Ret15_UIO_01
J32: VIRTUAL | K32: tvc-srv-condell | L32: Servidor Thincliente Dell | M32: 192.168.21.5 | O32: - | P32: SI | Q32: Evelyn Puetate | R32: SI | S32: Microsoft Windows Server 2019 (64-bit) | T32: 8 | U32: 100 | V32: 4 | W32: ALTO | X32: PRODUCCIÓN | Y32: NA | Z32: NA | AC32: SI | AD32: Veritas | AE32: Veritas-FullWed-Ret15_UIO_07
J33: VIRTUAL | K33: tvc-srv-dbas2bi | L33: Enviar informacion de base de datos AS2 | M33: 192.168.21.13 | N33: 200.63.213.82 | O33: - | P33: SI | Q33: Carlos Ayala/Christian Castillo | R33: SI | S33: Red Hat Enterprise Linux 9 (64-bit) | T33: 8 | U33: 300 | V33: 8 | W33: ALTO | X33: PRODUCCIÓN | AC33: SI | AD33: veaam | AE33: Veeam-FullWed-Ret15_UIO_23
J34: VIRTUAL | K34: tvc-srv-dbjaira | L34: Servidor base de datos Jira | M34: 192.168.21.36 | O34: SI | P34: - | Q34: Carlos Ayala/Christian Castillo | R34: SI | S34: Microsoft Windows Server 2012 (64-bit) | T34: 8 | U34: 550 | V34: 2 | W34: MEDIO | X34: PRODUCCIÓN | Y34: SQL SERVER | Z34: SQL Server 2012 | AC34: SI | AD34: Veritas | AE34: Veritas-FUllThu-Ret15_UIO_09
J35: VIRTUAL | K35: tvc-srv-desa-www | L35: Servidor www FSM | M35: 192.168.21.197 | O35: SI | P35: - | Q35: Hector Miranda/Administrador de aplicaciones | R35: SI | S35: Red Hat Enterprise Linux 6 (64-bit) | T35: 38 | U35: 100 | V35: 10 | W35: ALTO | X35: DESARROLLO | AC35: SI | AE35: Veritas-FUllTue-Ret15_UIO_04
J36: VIRTUAL | K36: tvc-srv-dhcpuio | L36: Servidor DHCP y consola de Unifi (Wifi) | M36: 192.168.21.2 | O36: SI | P36: - | Q36: Luis Conteron/Guillermo Jurado | R36: SI | S36: Microsoft Windows Server 2016 (64-bit) | T36: 8 | U36: 80 | V36: 4 | W36: ALTO | X36: PRODUCCIÓN | Y36: NA | Z36: NA | AC36: SI | AD36: Veritas | AE36: Veritas-FUllWed-Ret15_UIO_08
J37: VIRTUAL | K37: tvc-srv-exuio | L37: Servidor de Correo | M37: 192.168.21.50 192.168.21.196 | N37: 200.63.213.13 | O37: - | P37: SI | Q37: Evelyn Puetate | R37: SI | S37: Microsoft Windows Server 2022 (64-bit) | T37: 20 | U37: =250+150 -> 400 | V37: 4 | W37: ALTO | X37: PRODUCCIÓN | Y37: NA | Z37: NA | AC37: SI | AD37: Veritas | AE37: Veritas-FUllWed-Ret15_UIO_06
J38: VIRTUAL | K38: tvc-srv-finform | L38: Servidor de Formas Hiperk - Reemplazado por el AS2 | M38: 192.168.21.46 | O38: SI | P38: - | Q38: Hector Miranda/Administrador de aplicaciones | R38: SI | S38: Microsoft Windows Server 2016 (64-bit) | T38: 6 | U38: 250 | V38: 4 | W38: BAJO | X38: PREPRODUCCIÓN | Y38: NA | Z38: NA | AC38: SI | AD38: Veritas | AE38: Veritas-FUllWed-Ret15_UIO_06
J39: VIRTUAL | K39: tvc-srv-fsm | L39: Base Datos FSM | M39: 192.168.21.124 | O39: SI | P39: - | Q39: Carlos Ayala/James Pesantes | R39: SI | S39: Red Hat Enterprise Linux 6.4 (64-bit) | T39: 64 | U39: 3000 | V39: 8 | W39: ALTO | X39: PRODUCCIÓN | Y39: ORACLE | Z39: Oracle 11g R2 | AC39: Se respalda Base de Datos | AD39: Veritas | AE39: Veritas-FUllTue-Ret15_UIO_04
J40: VIRTUAL | K40: tvc-srv-ftp | L40: FTP Recargas efectos de consiliaciones | M40: 192.168.21.157 | N40: 200.63.213.64 | O40: SI | P40: - | Q40: Hector Miranda/Administrador de aplicaciones | R40: SI | S40: Red Hat Enterprise Linux 6 (64-bit) | T40: 2 | U40: 60 | V40: 1 | W40: ALTO | X40: PRODUCCIÓN | Y40: NA | Z40: NA | AC40: SI | AD40: Veritas | AE40: Veritas-FUllTue-Ret15_UIO_03
J41: VIRTUAL | K41: tvc-srv-ftpac | L41: Ftp actualizaciones BackOffice | M41: 192.168.21.203 | N41: 200.63.213.68 | O41: SI | P41: - | Q41: pendiente de confirmacion David Villamar | R41: SI | S41: Red Hat Enterprise Linux 6 (64-bit) | T41: 4 | U41: 50 | V41: 2 | W41: MEDIO | X41: PRODUCCIÓN | Y41: NA | Z41: NA | AC41: SI | AD41: veeam | AE41: Veritas-FullFri-Ret15_UIO_12
J42: VIRTUAL | K42: tvc-srv-gruptvc | L42: Pruebas pagina Grupo TVCable | M42: 192.168.21.123/192.168.122.1 | O42: SI | P42: - | Q42: Carlos Ayala / David Villamar | R42: SI | S42: Red Hat Enterprise Linux 7 (64-bit) | T42: 4 | U42: 120 | V42: 2 | W42: BAJO | X42: PREPRODUCCIÓN | Y42: MySQL | Z42: 5.6.28 Community Edition 64 bits | AC42: SI | AD42: Veritas | AE42: Veritas-FUllMon-Ret15_UIO_01
J43: VIRTUAL | K43: tvc-srv-guardium | L43: Servidor firewall base de datos | M43: 192.168.21.210 | N43: 200.63.213.56 | O43: SI | P43: - | Q43: Carlos Ayala/James Pesantes | R43: SI | S43: Red Hat Enterprise Linux 7 (64-bit) | T43: 32 | U43: 1000 | V43: 8 | W43: ALTO | X43: PRODUCCIÓN | Y43: MYSQL | Z43: MySQL modificado | AC43: SI | AD43: Veritas | AE43: Veritas-FUllTue-Ret15_UIO_04
J44: VIRTUAL | K44: tvc-srv-jenkins | L44: Servidor jenkins para bitbucket | M44: 192.168.21.14 | N44: 200.63.213.65 | O44: - | P44: SI | Q44: Mauricio Rodriguez | R44: SI | S44: Ubuntu Linux (64-bit) | T44: 6 | U44: 60 | V44: 2 | W44: MEDIO | X44: PRODUCCIÓN | Y44: NA | Z44: NA | AC44: SI | AD44: Veritas | AE44: Veritas-FUllTue-Ret15_UIO_03
J45: VIRTUAL | K45: tvc-srv-keycloak | L45: Keycloak | M45: 192.168.21.105 | O45: - | P45: NO | Q45: Graciela Ortiz | R45: SI | S45: Red Hat Enterprise Linux 9 (64-bit) | T45: 4 | U45: 80 | V45: 2 | W45: MEDIO | X45: PRODUCCIÓN | AC45: SI | AD45: Veritas | AE45: Veritas-FUllTue-Ret15_UIO_05
J46: VIRTUAL | K46: tvc-srv-malwareuio | L46: Srv Malware que analizará los backup de Veritas. | M46: 192.168.21.73 | O46: - | P46: SI | Q46: Evelyn Puetate | R46: SI | S46: Red Hat Enterprise Linux 9 (64-bit) | T46: 32 | U46: =100+20 -> 120 | V46: 8 | W46: MEDIO | X46: PRODUCCIÓN | AC46: SI | AD46: Veritas | AE46: Veritas-FUllWed-Ret15_UIO_06
J47: VIRTUAL | K47: tvc-srv-mediaveritas | L47: Intermiediario para convertir un equipo fisico a virtual con la plataforma de veritas | M47: 192.168.21.38 | O47: - | P47: SI | Q47: Evelyn Puetate | R47: SI | S47: Microsoft Windows Server 2022 (64-bit) | T47: 4 | U47: =160+279.366+1000 -> 1439.366 | V47: 2 | W47: BAJO | X47: PRODUCCIÓN | AC47: SI | AD47: Veritas | AE47: Veritas-FullFri-Ret15_UIO_13
J48: VIRTUAL | K48: tvc-srv-migracion | L48: Migracion y encriptacion de tablas y base de datos MYSQL | M48: 192.168.21.18 | O48: SI | P48: - | Q48: Carlos Ayala/James Pesantes | R48: SI | S48: Microsoft Windows Server 2016 (64-bit) | T48: 8 | U48: 250 | V48: 4 | W48: ALTO | X48: PREPRODUCCIÓN | Y48: NA | Z48: NA | AC48: SI | AD48: Veritas | AE48: Veritas-FUllThu-Ret15_UIO_09
J49: VIRTUAL | K49: tvc-srv-mobil | L49: Servidor MOBIL FSM | M49: 192.168.21.185 | N49: 200.63.213.61 | O49: SI | P49: - | Q49: Hector Miranda /Administrador de aplicaciones | R49: SI | S49: Red Hat Enterprise Linux 6 (64-bit) | T49: 30 | U49: 100 | V49: 8 | W49: ALTO | X49: PRODUCCIÓN | Y49: NA | Z49: NA | AC49: SI | AD49: Veritas | AE49: Veritas-FUllMon-Ret15_UIO_02
J50: VIRTUAL | K50: tvc-srv-myapp | L50: Aplicaciones Tecnico - Base de datos del isp de Tecnología | M50: 192.168.21.24 | O50: SI | P50: - | Q50: Tecnologia | R50: SI | S50: Microsoft Windows Server 2016 (64-bit) | T50: 12 | U50: 300 | V50: 6 | W50: MEDIO | X50: PRODUCCIÓN | Y50: NA | Z50: NA | AC50: SI | AD50: veeam | AE50: Veritas-FullFri-Ret15_UIO_13
J51: VIRTUAL | K51: tvc-srv-napi | L51: Servidor de api del FSM | M51: 192.168.21.186 | O51: SI | P51: - | Q51: Hector Miranda /Administrador de aplicaciones | R51: SI | S51: Red Hat Enterprise Linux 6 (64-bit) | T51: 12 | U51: 120 | V51: 4 | W51: ALTO | X51: PRODUCCIÓN | Y51: NA | Z51: NA | AC51: SI | AD51: Veritas | AE51: Veritas-FUllMon-Ret15_UIO_02
J52: VIRTUAL | K52: tvc-srv-nems | L52: Servidor webservice FSM/EMS | M52: 192.168.21.179 | O52: - | P52: SI | Q52: Hector Miranda /Administrador de aplicaciones | R52: SI | S52: Microsoft Windows Server 2022 (64-bit) | T52: 14 | U52: 150 | V52: 4 | W52: ALTO | X52: PRODUCCIÓN | Y52: NA | Z52: NA | AC52: SI | AD52: Veritas | AE52: Veritas-FUllWed-Ret15_UIO_07
J53: VIRTUAL | K53: tvc-srv-nfieb | L53: sistema Ebissnez intermix servicios de facturacion | M53: 192.168.21.209 | N53: 200.63.213.67 | O53: - | P53: SI | Q53: Hector Miranda /Administrador de aplicaciones | R53: SI | S53: Microsoft Windows Server 2022 (64-bit) | T53: 12 | U53: 300 | V53: 6 | W53: ALTO | X53: PRODUCCIÓN | Y53: NA | Z53: NA | AC53: SI | AD53: Veritas | AE53: Veritas-FUllWed-Ret15_UIO_06
J54: VIRTUAL | K54: tvc-srv-njbdps | L54: Pruebas página de Xtrim En el servidor 21.189 se encuentran las siguientes aplicaciones 1. JBoss y CM de Desarrollo 2. Dps de desarrollo 3. JBoss y CM de AQTEST 4. Dps de desarrollo (QAtest) Adicionalmente funciona como repositorio ftp para transacciones de pruebas, como por ejemplo 1. SoftSwitch 2. Débitos automáticos 3. Cdr 4. Facturación electronica de prueba. | M54: 192.168.21.189 | O54: SI | P54: - | Q54: Hector Miranda /Administrador de aplicaciones | R54: SI | S54: CentOS Linux release 7.9.2009 (Core) | T54: 8 | U54: =240+120 -> 360 | V54: 4 | W54: BAJO | X54: PREPRODUCCIÓN | Y54: NA | Z54: NA | AC54: SI | AD54: Veritas | AE54: Veritas-FUllMon-Ret15_UIO_02
J55: VIRTUAL | K55: tvc-srv-nmensajeria | L55: Enviar mensajes para Conax.SMS. Pagina de Vendedores. https://vendedores.xtrim.tv/LoginEfx.aspx Tambien maneja los bats de las bases de datos. Lo usa James y Carlos Ayala. | M55: a | O55: SI | P55: - | Q55: Hector Miranda /Administrador de aplicaciones | R55: SI | S55: Microsoft Windows Server 2016 (64-bit) | T55: 8 | U55: 250 | V55: 4 | W55: ALTO | X55: PRODUCCIÓN | Y55: NA | Z55: NA | AC55: SI | AD55: Veritas | AE55: Veritas-FUllWed-Ret15_UIO_08
J56: VIRTUAL | K56: tvc-srv-nsofbd | L56: Nuevo servidor base de datos soft | M56: 192.168.21.211 | O56: - | P56: SI | Q56: Carlos Ayala/James Pesantes | R56: SI | S56: Microsoft Windows Server 2019 (64-bit) | T56: 4 | U56: 300 | V56: 2 | W56: ALTO | X56: PRODUCCIÓN | Y56: SQL SERVER | Z56: SQL Server 2019 | AC56: SI | AD56: Veritas | AE56: Veritas-FUllWed-Ret15_UIO_07
J57: VIRTUAL | K57: tvc-srv-nuevapiis | L57: Servidores de aplicaciones, donde se encuentra el servicio de Biometria que hace la conexión con https://adocolumbia.ado-tech.com/TVCable/api/Integration/TVCable/Validation/StartCompareFaces, para ello debe tener permiso el acceso al puerto 443 y asi mismo tiene otras conexiones hacia otros servicios que se identificaran en el transcurso del día. | M57: 192.168.21.155 | O57: SI | P57: - | Q57: Hector Miranda /Administrador de aplicaciones | R57: SI | S57: Microsoft Windows Server 2016 (64-bit) | T57: 24 | U57: 200 | V57: 8 | W57: ALTO | X57: PRODUCCIÓN | Y57: NA | Z57: NA | AC57: SI | AD57: Veritas | AE57: Veritas-FUllWed-Ret15_UIO_07
J58: VIRTUAL | K58: tvc-srv-oracleasr | L58: Monitoreo de ODA | M58: 192.168.21.70 | O58: NO | P58: NO | Q58: Evelyn Puetate/Yurema Tobar | R58: SI | S58: Other (64-bit) | T58: 8 | U58: 70 | V58: 2 | W58: ALTO | X58: PRODUCCIÓN | Y58: NA | Z58: NA | AC58: SI | AD58: Veritas | AE58: Veritas-FUllTue-Ret15_UIO_03
J59: VIRTUAL | K59: tvc-srv-pbxprov | L59: Central Telefónica Provincias | M59: 192.168.21.21/192.168.21.69 interface | O59: NO | P59: SI | Q59: Luis Conteron/Guillermo Jurado | R59: SI | S59: Centos 7 | T59: 16 | U59: 100 | V59: 4 | W59: ALTO | X59: PRODUCCIÓN | Y59: NA | Z59: NA | AC59: SI | AE59: Veritas-FUllTue-Ret15_UIO_03
J60: VIRTUAL | K60: tvc-srv-pbxuio | L60: Central Telefónica UIO | M60: 192.168.21.75 | O60: SI | P60: - | Q60: Luis Conteron /Guillermo Jurado | R60: SI | S60: CentOS 7 (64-bit) | T60: 16 | U60: 500 | V60: 4 | W60: ALTO | X60: PRODUCCIÓN | AC60: SI | AD60: Veritas | AE60: Veritas-FUllTue-Ret15_UIO_03
J61: VIRTUAL | K61: tvc-srv-preapi | L61: Servidor API FSM | M61: 192.168.21.188 | O61: SI | P61: - | Q61: Hector Miranda /Administrador de aplicaciones | R61: SI | S61: Red Hat Enterprise Linux 6 (64-bit) | T61: 48 | U61: =100+100 -> 200 | V61: 2 | W61: ALTO | X61: PREPRODUCCIÓN | Y61: NA | Z61: NA | AC61: SI | AD61: Veritas | AE61: Veritas-FUllMon-Ret15_UIO_01
J62: VIRTUAL | K62: tvc-srv-predb | L62: Servidor pruebas base de datos FSM | M62: 192.168.21.182 | N62: 200.63.213.34 | O62: SI | P62: - | Q62: Carlos Ayala/james Pesantes | R62: SI | S62: Red Hat Enterprise Linux 6 (64-bit) | T62: 16 | U62: 300 | V62: 2 | W62: BAJO | X62: PREPRODUCCIÓN | Y62: ORACLE | Z62: Oracle 11g R2 | AC62: SI | AD62: Veritas | AE62: Veritas-FUllMon-Ret15_UIO_02
J63: VIRTUAL | K63: tvc-srv-proxyvrtuio | L63: Agente de Veritas, levanta la consola del NETbackup que permite generar y restaturar los respaldos | M63: 192.168.19.13 | O63: - | P63: SI | Q63: Evelyn Puetate | R63: SI | S63: Red Hat Enterprise Linux 9.2 (64-bit) | T63: 8 | U63: 80 | V63: 8 | W63: ALTO | X63: PRODUCCIÓN | Y63: NA | Z63: NA | AC63: SI | AD63: Veritas | AE63: Veritas-FUllTue-Ret15_UIO_05
J64: VIRTUAL | K64: tvc-srv-qaapi | L64: Servidor pruebas API FSM | M64: 192.168.21.187 | O64: SI | P64: - | Q64: Hector Miranda /Administrador de aplicaciones | R64: SI | S64: Red Hat Enterprise Linux 6 (64-bit) | T64: 48 | U64: 120 | V64: 2 | W64: BAJO | X64: PREPRODUCCIÓN | Y64: NA | Z64: NA | AC64: SI | AD64: Veritas | AE64: Veritas-FUllMon-Ret15_UIO_01
J65: VIRTUAL | K65: tvc-srv-qtev-vir | L65: Qlik Sense - Analitica de datos que le permite hacer frente a los problemas analiticos más complejos. Servidor critico para la toma de decisiones de la compañia, porque es el resumen de las ventas que tiene la empresa. | M65: 192.168.21.100 | N65: 200.63.213.31 | O65: SI | P65: - | Q65: Veronica Molina | R65: SI | S65: Windows Server 2016 | T65: 196 | U65: =279.37+1000 -> 1279.37 | V65: 24 | W65: ALTO | X65: PRODUCCIÓN | Y65: NA | Z65: NA | AC65: SI | AD65: Veritas | AE65: Veritas-FUllThu-Ret15_UIO_10
J66: VIRTUAL | K66: tvc-srv-repfin | L66: Repositorio de documentos para F.Eléctronica | M66: 192.168.21.176 | O66: SI | P66: - | Q66: Hector Miranda /Administrador de aplicaciones | R66: SI | S66: Red Hat Enterprise Linux 7 (64-bit) | T66: 12 | U66: =250+50 -> 300 | V66: 6 | W66: ALTO | X66: PRODUCCIÓN | Y66: NA | Z66: NA | AC66: SI | AD66: Veritas | AE66: Veritas-FUllMon-Ret15_UIO_01
J67: VIRTUAL | K67: tvc-srv-robot | L67: Backup Robot | M67: 192.168.21.163 | O67: SI | P67: - | Q67: Hector Miranda /Administrador de aplicaciones | R67: SI | S67: Microsoft Windows Server 2016 (64-bit) | T67: 20 | U67: 250 | V67: 8 | W67: MEDIO | X67: PREPRODUCCIÓN | Y67: NA | Z67: NA | AC67: SI | AD67: Veritas | AE67: Veritas-FUllThu-Ret15_UIO_09
J68: VIRTUAL | K68: tvc-srv-rpdr | L68: Servidor de RapidDR, para el manejo de tareas de failover del simplivity | M68: 192.168.21.110 | O68: SI | P68: - | Q68: Evelyn Puetate | R68: SI | S68: Microsoft Windows Server 2016 (64-bit) | T68: 8 | U68: 120 | V68: 4 | W68: ALTO | X68: PRODUCCIÓN | Y68: NA | Z68: NA | AC68: si | AD68: Veritas | AE68: Veritas-FUllMon-Ret15_UIO_01
J69: VIRTUAL | K69: tvc-srv-satelitepan | L69: Servidor de Pandora FMS Enterprise | M69: 192.168.21.240 | O69: - | P69: SI | Q69: Evelyn Puetate | R69: SI | S69: Red Hat Enterprise Linux 8 (64-bit) | T69: 4 | U69: 80 | V69: 4 | W69: MEDIO | X69: PRODUCCIÓN | AC69: SI | AD69: Veritas | AE69: Veritas-FUllTue-Ret15_UIO_03
J70: VIRTUAL | K70: tvc-srv-sofpro | L70: Servidor softswitch bancos | M70: 192.168.21.158 | O70: - | P70: SI | Q70: Hector Miranda /Administrador de aplicaciones | R70: SI | S70: Microsoft Windows Server 2016 (64-bit) | T70: 24 | U70: 200 | V70: 6 | W70: ALTO | X70: PRODUCCIÓN | Y70: NA | Z70: NA | AC70: SI | AD70: Veritas
J71: VIRTUAL | K71: tvc-srv-softdb | L71: Base datos softswich de pagos - bancos | M71: 192.168.21.159 | N71: 200.63.213.30 | O71: - | P71: SI | Q71: Carlos Ayala/james Pesantes | R71: SI | S71: Microsoft Windows Server 2012 (64-bit) | T71: 16 | U71: 200 | V71: 4 | W71: ALTO | X71: PRODUCCIÓN | Y71: SQL SERVER | Z71: SQL Server 2012 Standard Edition | AC71: SI | AD71: Veritas | AE71: Veritas-FUllWed-Ret15_UIO_08
J72: VIRTUAL | K72: tvc-srv-softbd2 | L72: Base datos softswich de pagos - bancos-pruebas de bancos | M72: 192.168.21.212 | O72: - | P72: SI/REV | Q72: Carlos Ayala/James Pesantes | R72: SI | S72: Microsoft Windows Server 2012 (64-bit) | T72: 16 | U72: 200 | V72: 4 | W72: ALTO | X72: PRUEBAS | Y72: SQL SERVER | Z72: SQL Server 2012 Standard Edition | AC72: SI | AD72: Veritas | AE72: Veritas-FullFri-Ret15_UIO_13
J73: VIRTUAL | K73: xtr-srv-systemcm | L73: Nuevo System Center Mnager | M73: 192.168.21.33 | O73: - | P73: SI/REV | Q73: Dalton Benitez/Julio Enriquez | R73: SI | S73: Microsoft Windows Server 2025(64-bit) | T73: 8 | U73: 150 | V73: 4 | W73: ALTO | X73: PRODUCCIÓN | AC73: SI | AD73: Veritas | AE73: Veritas-FullSun-Ret60_UIO_18
J74: VIRTUAL | K74: tvc-srv-ssprodu | L74: Base datos de sofswitch y debitos automaticos producción | M74: 192.168.21.103 | O74: - | P74: SI | Q74: Carlos Ayala / Hector Miranda | R74: SI | S74: Microsoft Windows Server 2022 (64-bit) | T74: 32 | U74: 350 | V74: 4 | W74: ALTO | X74: PRODUCCIÓN | Y74: SQL SERVER | Z74: SQL Server 2019 Standard Edition | AC74: SI | AD74: Veritas | AE74: Veritas-FUllThu-Ret15_UIO_09
J75: VIRTUAL | K75: tvc-srv-sonarqube | L75: Aplicativo SONARQUBE para analisis de codigo | M75: 192.168.21.39 | O75: - | P75: SI | Q75: Mauricio Rodriguez | R75: SI | S75: Red Hat Enterprise Linux 9.2 (64-bit) | T75: 12 | U75: 150 | V75: 2 | W75: MEDIO | X75: PRODUCCIÓN | AC75: SI | AD75: veritas | AE75: Veritas-FullThu-Ret15_UIO_09
J76: VIRTUAL | K76: tvc-srv-sopcomarch | L76: Soporte de comarch | M76: 192.168.21.30 | O76: - | P76: SI | Q76: Hector Miranda / Graciela Ortiz | R76: SI | S76: Microsoft Windows Server 2022 (64-bit) | T76: 8 | U76: 150 | V76: 4 | W76: MEDIO | X76: PRUEBAS | AC76: SI | AD76: veritas | AE76: Veritas-FullThu-Ret15_UIO_09
J77: VIRTUAL | K77: tvc-srv-techin | L77: Sistema de control de ingreso | M77: 192.168.21.3 | O77: SI | P77: - | Q77: Carlos Ayala / Administrador de aplicaciones / Angel Zambrano | R77: SI | S77: Microsoft Windows Server 2016 (64-bit) | T77: 20 | U77: 1300 | V77: 8 | W77: MEDIO | X77: PRODUCCIÓN | Y77: SQL SERVER | Z77: SQL Server 2012 Standard Edition | AC77: SI | AD77: veritas | AE77: Veritas-FUllWed-Ret15_UIO_08
J78: VIRTUAL | K78: tvc-srv-wso2nod3 | L78: Servidor Dockers Net Core Apis. Tiene los contenedores que estan desarrollados en .NET , son 3 micros para el uso de los servicios de SeedBIlling. | M78: 192.168.21.178 | N78: 200.63.213.33 | O78: - | P78: SI | Q78: Hector Miranda / Graciela Ortiz | R78: SI | S78: Red Hat Enterprise Linux 7 (64-bit) | T78: 8 | U78: 250 | V78: 2 | W78: BAJO | X78: PRODUCCIÓN | Y78: NA | Z78: NA | AC78: SI | AD78: veeam | AE78: Veritas-FullFri-Ret15_UIO_13
J79: VIRTUAL | K79: tvc-srv-testeb | L79: Desarrollo de Ebizness | M79: 192.168.21.223 | O79: - | P79: SI | Q79: Hector Miranda / Graciela Ortiz | R79: SI | S79: Microsoft Windows Server 2022 (64-bit) | T79: 12 | U79: 350 | V79: 6 | W79: BAJO | X79: PREPRODUCCIÓN | Y79: NA | Z79: NA | AC79: SI | AD79: veritas | AE79: Veritas-FUllThu-Ret15_UIO_10
J80: VIRTUAL | K80: tvc-srv-tiflow | L80: Servidor flujos TI | M80: 192.168.21.221 | O80: SI | P80: - | Q80: Graciela Ortiz | R80: SI | S80: Microsoft Windows Server 2012 (64-bit) | T80: 10 | U80: 600 | V80: 4 | W80: MEDIO | X80: PRODUCCIÓN | Y80: NA | Z80: NA | AC80: SI | AD80: Veritas | AE80: Veritas-FUllThu-Ret15_UIO_10
J81: VIRTUAL | K81: tvcsrvvcu | L81: Vcenter Quito | M81: 192.168.21.9 | O81: NO | P81: NO | Q81: Evelyn Puetate | R81: SI | S81: Other 3.x or later Linux (64-bit) | T81: 19 | U81: 700.35 | V81: 4 | W81: ALTO | X81: PRODUCCIÓN | Y81: NA | Z81: NA | AC81: SI | AD81: veritas | AE81: Veritas-FUllTue-Ret15_UIO_05
J82: VIRTUAL | K82: XTR-SRV-HUAWEI | L82: Función: Para ambiente de pruebas donde se instalara la aplicación de integración hacia el NME de Huawei , esta será una nueva OLT que estará implementándose en un piloto en la ciudad del Carmen para 10000 HP de FO. | M82: 192.168.21.40 | P82: SI | Q82: Harry Salvatierra / Cesar Calderon | R82: SI | S82: Microsoft Windows Server 2025 | T82: 16 | U82: 300 | V82: 4 | W82: MEDIO | X82: PRODUCCIÓN | Y82: NA | Z82: N/A | AC82: si | AD82: Veritas | AE82: Veritas-FUllWed-Ret15_UIO_07
J83: VIRTUAL | K83: XTR-SRV-PASMUIO | L83: implementacion de un nuevo PAM | M83: 192.168.212.44 | O83: SI
J84: VIRTUAL | K84: tvc-srv-medi2 | L84: Mediador windows prueba. Servidor donde esta el front operativo de servicios, para reiniciar los dps y los daemon. | M84: 192.168.21.205 | O84: - | P84: SI | Q84: Hector Miranda | R84: SI | S84: Microsoft Windows Server 2022 (64-bit) | T84: 14 | U84: 300 | V84: 6 | W84: BAJO | X84: PRODUCCIÓN | Y84: NA | Z84: NA | AC84: SI | AD84: Veritas | AE84: Veritas-FUllWed-Ret15_UIO_08
J85: VIRTUAL | K85: tvc-srv-wmedia2 | L85: Servidor mediación 02. Servidor donde esta el front operativo de servicios, para reiniciar los dps y los daemon. | M85: 192.168.21.104 | N85: 200.63.213.14 | O85: SI | P85: - | Q85: Hector Miranda | R85: SI | S85: Microsoft Windows Server 2016 (64-bit) | T85: 10 | U85: 300 | V85: 6 | W85: ALTO | X85: PRODUCCIÓN | Y85: NA | Z85: NA | AC85: SI | AD85: Veritas | AE85: Veritas-FUllWed-Ret15_UIO_08
J86: VIRTUAL | K86: tvc-srv-www | L86: Servidor www FSM | M86: 192.168.21.184 | N86: 200.63.213.62 | O86: SI | P86: - | Q86: Hector Miranda | R86: SI | S86: Red Hat Enterprise Linux 6 (64-bit) | T86: 38 | U86: 100 | V86: 10 | W86: ALTO | X86: PRODUCCIÓN | Y86: NA | Z86: NA | AC86: SI | AD86: Veritas | AE86: Veritas-FUllMon-Ret15_UIO_01
J87: VIRTUAL | K87: tvc-srv-XtrimTest | L87: pagina de Xtrim - PRODUCCION | M87: 192.168.21.190 | N87: 200.63.213.90 | O87: SI | P87: - | Q87: Hector Miranda | R87: SI | S87: CentOS 7 (64-bit) | T87: 16 | U87: 250 | V87: 2 | W87: ALTO | X87: PRODUCCIÓN | Y87: NA | Z87: NA | AC87: SI | AD87: Veritas | AE87: Veritas-FUllTue-Ret15_UIO_03
J88: VIRTUAL | K88: xtr-srv-grafana | L88: Monitoreo de servicios | M88: 192.168.21.128 | O88: SI | P88: - | Q88: Evelyn Puetate | S88: Red Hat Enterprise Linux 9.2 (64-bit) | T88: 6 | U88: 100 | V88: 4 | W88: ALTO | X88: PRODUCCIÓN
J89: VIRTUAL | K89: tvc-srv-xtvcable | L89: 59.57 | M89: 192.168.21.129 | N89: 200.63.213.26 | O89: SI | P89: - | Q89: Hector Miranda | R89: SI | S89: Red Hat Enterprise Linux 7 (64-bit) | T89: 18 | U89: 200 | V89: 10 | W89: ALTO | X89: PRODUCCIÓN | Y89: MYSQL | Z89: MySQL 5.1.57-community edition | AC89: SI | AD89: veritas | AE89: Veritas-FUllMon-Ret15_UIO_01
J90: VIRTUAL | K90: tvc-srv-aduio1 | L90: Active Directory Principal | M90: 192.168.21.42 | O90: SI | P90: - | Q90: Evelyn Puetate | R90: SI | S90: Microsoft Windows Server 2016 (64-bit) | T90: 20 | U90: 250 | V90: 8 | W90: ALTO | X90: PRODUCCIÓN | Y90: NA | Z90: NA | AC90: SI | AD90: Veritas | AE90: Veritas-FUllWed-Ret15_UIO_06
J91: VIRTUAL | K91: tvc-srvmysql | L91: Servidor base de datos mediacion | M91: 192.168.21.206 | O91: SI | P91: - | Q91: Carlos Ayala/James Pesantes | R91: SI | S91: Red Hat Enterprise Linux 5 (64-bit) | T91: 6 | U91: 200 | V91: 4 | W91: ALTO | X91: PRODUCCIÓN | Y91: MYSQL | Z91: MySQL 5.1.57-community edition | AC91: SI | AD91: Veritas | AE91: Veritas-FUllMon-Ret15_UIO_02
J92: VIRTUAL | K92: tvc-srvmysql-test | L92: Base de datos mediador de test, de aprovisionamiento para enviar comando en los equipos de los clientes. | M92: 192.168.21.193 | O92: SI | P92: - | Q92: Carlos Ayala/James Pesantes | R92: SI | S92: Red Hat Enterprise Linux 5 (64-bit) | T92: 6 | U92: 200 | V92: 4 | W92: BAJO | X92: PREPRODUCCIÓN | Y92: MYSQL | Z92: MySQL 5.1.57-community edition | AC92: SI | AD92: veeam | AE92: Veritas-FullFri-Ret15_UIO_12
J93: VIRTUAL | K93: tvc-srvpamuio | L93: Servidor de Boveda de Claves (PAM) | M93: 192.168.21.107 | N93: 200.63.213.35 | O93: SI | P93: - | Q93: Evelyn Puetate | R93: SI | S93: Microsoft Windows Server 2016 (64-bit) | T93: 16 | U93: 110 | V93: 4 | W93: ALTO | X93: PRODUCCIÓN | Y93: NA | Z93: NA | AC93: SI | AD93: Veritas | AE93: Veritas-FUllThu-Ret15_UIO_09
J94: VIRTUAL | K94: XTR-SRV-ODA-CM2 | L94: SERVIDOR DE REEMPLAZO TEMPORAL DEL 192.168.21.175 | M94: 192.168.21.232 | Q94: Hector Miranda | S94: oracle linux 7.9 | W94: ALTO | X94: PRODUCCIÓN | Y94: NA | Z94: NA | AC94: SI | AD94: Veritas | AE94: Veritas-FUllThu-Ret15_UIO_10
J95: VIRTUAL | K95: XTR-SRV-ODA-DPS | L95: SERVIDOR DE REEMPLAZO TEMPORAL DEL 192.168.21.147 | M95: 192.168.21.231 | Q95: Hector Miranda | S95: oracle linux 7.9 | W95: ALTO | X95: PRODUCCIÓN | Y95: NA | Z95: NA | AC95: SI | AD95: Veritas | AE95: Veritas-FUllThu-Ret15_UIO_10
J96: VIRTUAL | K96: XTR-SRV-ODA-CM | L96: SERVIDOR DE REEMPLAZO TEMPORAL DEL 192.168.21.175 | M96: 192.168.21.233 | O96: SI | Q96: Hector Miranda | S96: oracle linux 7.9 | W96: ALTO | X96: PRODUCCIÓN | Y96: NA | Z96: NA | AC96: SI | AD96: Veritas | AE96: Veritas-FUllThu-Ret15_UIO_10
J97: VIRTUAL | K97: xtr-srv-elern | L97: Servidor capacitación tecnología | M97: 192.168.21.74 | O97: - | P97: SI | Q97: Julio Enriquez / Miriam Tupiza | R97: NO | S97: Windows Server 2022 | T97: 16 | U97: 600 | V97: 1 | W97: BAJO | X97: PRODUCCIÓN | Y97: NA | Z97: NA | AA97: 0 | AC97: SI | AD97: Veritas | AE97: Veritas-FullSun-Ret60_UIO_19
A98: UIO - ODA X8 | B98: ODA X8-2L | C98: ODA X8-2L NODODB1-ILOM 192.168.33.160 NODODB2-ILOM 192.168.33.162 | D98: 2114XC000M | E98: Blade 192.168.21.120 Baremetal 192.168.21.115 | F98: 2 | G98: 2X Intel(R) Xeon(R) Gold 5218 CPU @ 2.30GHz, 384 GB RAM, se puede aumentar 12 mas de 32GB. 2 discos de 7,68TB. | H98: SI | I98: =COUNTIF(J98:J100,"=VIRTUAL") -> 3 | J98: VIRTUAL | K98: tvc-oda1 | L98: Titan | M98: 192.168.21.117 | O98: SI | P98: - | Q98: Hector Miranda | R98: SI | S98: Oracle 19.9.0.0.0 | T98: 164 | V98: 16 | W98: ALTO | X98: PRODUCCIÓN | Y98: ORACLE | Z98: Oracle 11g R2 | AA98: 11610 | AC98: No, es la base de datos | AE98: Veritas-FullSat-Ret60_UIO_15
J99: VIRTUAL | K99: tvc-oda-dps | L99: DPS | M99: 192168.21.147 | O99: SI | P99: - | Q99: Hector Miranda | R99: SI | S99: Red Hat Enterprise Linux Server release 7.9 | T99: 65 | V99: 12 | W99: ALTO | X99: PRODUCCIÓN | Y99: ORACLE | Z99: Oracle 11g R2 | AC99: VERITAS | AD99: Veritas | AE99: Veritas-FullSat-Ret60_UIO_15
J100: VIRTUAL | K100: tvc-oda-insight-bm | L100: Mediacción | M100: 192.168.31.200 | O100: SI | P100: - | Q100: Hector Miranda | R100: SI | S100: Red Hat Enterprise Linux Server release 7.9 | T100: 32 | V100: 10 | W100: ALTO | X100: PRODUCCIÓN | Y100: ORACLE | Z100: Oracle 11g R2 | AC100: VERITAS | AD100: Veritas | AE100: Veritas-FullSat-Ret60_UIO_15
E101: Blade 192.168.21.122 Baremetal 192.168.21.116 | I101: =COUNTIF(J101:J103,"=VIRTUAL") -> 3 | J101: VIRTUAL | K101: tvc-oda2 | L101: Servidor base de datos sistema Comarch | M101: 192.168.21.118 | O101: SI | P101: - | Q101: Hector Miranda | R101: SI | S101: Oracle 19.9.0.0.0 | T101: 164 | V101: 16 | W101: ALTO | X101: PRODUCCIÓN | Y101: ORACLE | Z101: Oracle 11g R2 | AC101: No, es la base de datos | AE101: Veritas-FullSat-Ret60_UIO_15
J102: VIRTUAL | K102: tvc-oda-cm | L102: JBOSS | M102: 192.168.21.175 | O102: SI | P102: - | Q102: Hector Miranda | R102: SI | S102: Red Hat Enterprise Linux Server release 7.9 | T102: 98 | V102: 12 | W102: ALTO | X102: PRODUCCIÓN | Y102: NA | Z102: NA | AC102: VERITAS | AD102: Veritas | AE102: Veritas-FullSat-Ret60_UIO_15
J103: VIRTUAL | K103: tvc-oda-insight-sa | L103: Mediacción | M103: 192.168.31.190 | O103: SI | P103: - | Q103: Hector Miranda | R103: SI | S103: Red Hat Enterprise Linux Server release 7.9 | T103: 32 | V103: 10 | W103: ALTO | X103: PRODUCCIÓN | Y103: NA | Z103: NA | AC103: VERITAS | AD103: Veritas | AE103: Veritas-FullSat-Ret60_UIO_15
A104: UIO - C7000 | B104: C7000 - TEC | C104: BL460 | D104: USE309X0JP | E104: 192.168.34.11 | F104: 1 | G104: 2X GEN8. Procesador Intel(R) Xeon(R) CPU E5-2670 0 @ 2.60GHz, 2 slot de memoria c/u de 256GB en total 512 GB RAM. | H104: NO | J104: FISICO
...

Sheet UIO
J2: INVENTARIO DE SERVIDORES VIRTUALIZADOS Y FISICOS UIO 2024
A5: Fecha de actualización: 4Julio2024 | H5: Actualizado por: Evelyn Puetate
A7: CIUDAD | B7: ENCLOSURE | C7: SRV FISICOS | D7: SERIE | E7: IP DEL BLADE | F7: TOTAL SRV FISICOS | G7: CARACTERISTICAS | H7: SOPORTE | I7: # SRV VIRTUALES | J7: TIPO DE SERVIDOR | K7: SRV VIRTUALES | L7: APLICACIÓN | M7: IP INTERNA | N7: IP PUBLICA | O7: PROTECCIÓN DE TREND MCRO XDR - SRV | P7: CORTEX | Q7: Persona responsable del uso del SRV | R7: SISTEMA OPERATIVO | S7: MEMORIA | T7: Espacio Disco | U7: Procesador | V7: SISTEMAS CRITICOS | W7: SERVIDOR PRODUCCIÓN / PREPRODUCCIÓN | X7: BASE DE DATOS | Y7: VERSIÓN DB | Z7: COSTO SOPORTE | AA7: EMPRESA QUE DA SOPORTE | AB7: BACKUP SE REALIZA | AC7: PLATAFORMA DE BACKUP | AD7: POLITICA DE BACKUP
A8: UIO | B8: tvc-srv-esx1 | C8: ProLiant DL380 2 x Intel(R) Xeon(R) Gold 6230 CPU @ 2.10GHz x 20 Cores | D8: 2M211600MH | E8: shp | F8: 4 | G8: Gen 10 1.5 TB RAM | H8: SI | I8: =COUNTIF(J8:J106,"=VIRTUAL") -> 99 | J8: VIRTUAL | K8: Fortiweb | L8: Firewall Waf | M8: 192.168.21.32 | N8: 200.63.213.18 | O8: - | P8: - | Q8: Luis Conteron / Guillermo Jurado | R8: Other 2.6.x Linux (64-bit) | S8: 8 | T8: 150 | U8: 8 | V8: ALTO | W8: PRODUCCIÓN | X8: NA | Y8: NA | AB8: SI | AC8: Veritas | AD8: Veritas-FUllTue-Ret15_UIO_04
A9: UIO | B9: tvc-srv-esx2 | C9: ProLiant DL381 2 x Intel(R) Xeon(R) Gold 6230 CPU @ 2.10GHz x 20 Cores | D9: 2M211600MG | E9: 192.168.34.162 | G9: Gen 10 1.5 TB RAM | H9: SI | J9: VIRTUAL | K9: OmniStackVC-192-168-34-161 | L9: Servidor propio de trabajo SimpliVity | M9: 192.168.34.161 | O9: - | P9: - | Q9: Evelyn Puetate | R9: Ubuntu Linux (64-bit) | S9: 92 | T9: 209.96 | U9: 8 | V9: BAJO | W9: PRODUCCIÓN | X9: NA | Y9: NA | AB9: NO es parte sistema operativo de Simplivity | AC9: -
A10: UIO | B10: tvc-srv-esx3 | C10: ProLiant DL380 2 x Intel(R) Xeon(R) Gold 6238 CPU @ 2.10GHz x 22 Cores | D10: 2M232601ZG | E10: 192.168.34.164 | G10: Gen 10 1 TB RAM | H10: SI | J10: VIRTUAL | K10: OmniStackVC-192-168-34-163 | L10: Servidor propio de trabajo SimpliVity | M10: 192.168.34.163 | O10: - | P10: - | Q10: Evelyn Puetate | R10: Ubuntu Linux (64-bit) | S10: 92 | T10: 209.96 | U10: 8 | V10: BAJO | W10: PRODUCCIÓN | X10: NA | Y10: NA | AB10: NO es parte sistema operativo de Simplivity | AC10: -
A11: UIO | B11: tvc-srv-esx4 | C11: ProLiant DL380 2 x Intel(R) Xeon(R) Gold 6238 CPU @ 2.10GHz x 22 Cores | D11: 2M232601ZH | E11: 192.168.34.166 | G11: Gen 10 1 TB RAM | H11: SI | J11: VIRTUAL | K11: OmniStackVC-192-168-34-165 | L11: Servidor propio de trabajo SimpliVity | M11: 192.168.34.165 | O11: - | P11: - | Q11: Evelyn Puetate | R11: Ubuntu Linux (64-bit) | S11: 92 | T11: 209.96 | U11: 8 | V11: BAJO | W11: PRODUCCIÓN | X11: NA | Y11: NA | AB11: NO es parte sistema operativo de Simplivity | AC11: -
J12: VIRTUAL | K12: OmniStackVC-192-168-34-167 | L12: Servidor propio de trabajo SimpliVity | M12: 192.168.34.167 | O12: - | P12: - | Q12: Evelyn Puetate | R12: Ubuntu Linux (64-bit) | S12: 92 | T12: 209.96 | U12: 8 | V12: BAJO | W12: PRODUCCIÓN | X12: NA | Y12: NA | AB12: NO es parte sistema operativo de Simplivity | AC12: -
J13: VIRTUAL | K13: tvc-bss-crm-02 | L13: Alepo- CRM + Billing + Product catalogue + Inventory + Trouble Ticketing + Affiliate Management + Off line rating | M13: 192.168.21.60 | O13: - | P13: SI | Q13: Pendiente de confirmacion Xavier Leon | R13: Oracle Linux 8 (64-bit) | S13: 48 | T13: 800 | U13: 32 | V13: ALTO | W13: PRODUCCIÓN | X13: NA | Y13: NA | AB13: SI | AC13: Veritas | AD13: Veritas-FUllMon-Ret15_UIO_00
J14: VIRTUAL | K14: tvc-bss-ffm-02 | L14: Alepo - FFM | M14: 192.168.21.61 | O14: - | P14: SI | Q14: Pendiente de confirmacion Xavier Leon | R14: Oracle Linux 8 (64-bit) | S14: 32 | T14: 500 | U14: 8 | V14: ALTO | W14: PRODUCCIÓN | X14: NA | Y14: NA | AB14: SI | AC14: Veritas | AD14: Veritas-FUllMon-Ret15_UIO_00
J15: VIRTUAL | K15: tvc-bss-inter-02 | L15: Alepo - Interconnect | M15: 192.168.21.65 | O15: - | P15: SI | Q15: Pendiente de confirmacion Xavier Leon | R15: Oracle Linux 8 (64-bit) | S15: 48 | T15: 3430 | U15: 32 | V15: ALTO | W15: PRODUCCIÓN | X15: NA | Y15: NA | AB15: SI | AC15: Veritas | AD15: Veritas-FUllMon-Ret15_UIO_00
J16: VIRTUAL | K16: tvc-bss-mediation-02 | L16: Alepo - Mediation | M16: 192.168.21.64 | O16: - | P16: SI | Q16: Pendiente de confirmacion Xavier Leon | R16: Oracle Linux 8 (64-bit) | S16: 32 | T16: 600 | U16: 16 | V16: ALTO | W16: PRODUCCIÓN | X16: NA | Y16: NA | AB16: SI | AC16: Veritas | AD16: Veritas-FUllMon-Ret15_UIO_00
J17: VIRTUAL | K17: tvc-bss-oms-02 | L17: Alepo - Order Management | M17: 192.168.21.66 | O17: - | P17: SI | Q17: Pendiente de confirmacion Xavier Leon | R17: Oracle Linux 8 (64-bit) | S17: 32 | T17: 300 | U17: 16 | V17: ALTO | W17: PRODUCCIÓN | X17: NA | Y17: NA | AB17: SI | AC17: Veritas | AD17: Veritas-FUllMon-Ret15_UIO_00
J18: VIRTUAL | K18: tvc-bss-wsrc-02 | L18: Alepo - Web Self Care + Chatbot + Whatsapp | M18: 192.168.21.62 | O18: - | P18: SI | Q18: Pendiente de confirmacion Xavier Leon | R18: Oracle Linux 8 (64-bit) | S18: 28 | T18: 500 | U18: 16 | V18: ALTO | W18: PRODUCCIÓN | X18: NA | Y18: NA | AB18: SI | AC18: Veritas | AD18: Veritas-FUllMon-Ret15_UIO_00
J19: VIRTUAL | K19: tvc-srv-admapp - ELIMINADO | L19: Recursos Humanos Apicación | M19: 192.168.21.119 | Q19: Mauricio Rodriguez | R19: Microsoft Windows Server 2012 (64-bit) | S19: 8 | T19: 500 | U19: 4 | V19: MEDIO | W19: ELIMINADO | X19: SQL SERVER | Y19: SQL Server 2014 | AB19: NO equipo apagado
J20: VIRTUAL | K20: tvc-srv-admbd - ELIMINADO | L20: Recursos Humanos Base de Datos | M20: 192.168.21.121 | Q20: Mauricio Rodriguez | R20: Microsoft Windows Server 2012 (64-bit) | S20: 8 | T20: 500 | U20: 4 | V20: MEDIO | W20: ELIMINADO | X20: SQL SERVER | Y20: SQL Server 2014 | AB20: NO equipo apagado
J21: VIRTUAL | K21: tvc-srv-adprint | L21: Administrador de impresoras UIO | M21: 192.168.21.17 | O21: SI | P21: - | Q21: Hector Miranda/Graciela Ortiz | R21: Microsoft Windows Server 2016 (64-bit) | S21: 16 | T21: 350 | U21: 4 | V21: MEDIO | W21: PRODUCCIÓN | X21: NA | Y21: NA | AB21: SI | AC21: Veritas | AD21: Veritas-FUllWed-Ret15_UIO_08
J22: VIRTUAL | K22: tvc-srv-aduio2 | L22: Conector del AD | M22: 192.168.21.26 | N22: 200.63.213.27 | O22: SI | P22: - | Q22: Evelyn Puetate /Yurema Tobar | R22: Microsoft Windows Server 2016 (64-bit) | S22: 20 | T22: 150 | U22: 4 | V22: ALTO | W22: PRODUCCIÓN | X22: NA | Y22: NA | AB22: SI | AC22: Veritas | AD22: Veritas-FUllWed-Ret15_UIO_08
J23: VIRTUAL | K23: tvc-srv-aduio3 | L23: Active Directory secundario | M23: 192.168.21.27 | O23: SI | P23: - | Q23: Evelyn Puetate /Yurema Tobar | R23: Microsoft Windows Server 2016 (64-bit) | S23: 20 | T23: 150 | U23: 4 | V23: ALTO | W23: PRODUCCIÓN | AB23: SI | AC23: Veritas | AD23: Veritas-FUllWed-Ret15_UIO_08
J24: VIRTUAL | K24: tvc-srv-agdi | L24: Pagina Web Agencia Digital, tmbn tiene xtrim.tv, xtrim.com.ec, Pagina de Ingreso de contrato para vendedores, proveedores y distribuidores - mixtrim.com.ec/IngresoContratos | M24: 192.168.21.243 | N24: 200.63.213.43 | O24: SI | P24: - | Q24: Hector Miranda /Administrador de aplicaciones | R24: Red Hat Enterprise Linux 7 (64-bit) | S24: 48 | T24: 180 | U24: 8 | V24: ALTO | W24: PRODUCCIÓN | X24: MySQL | Y24: 5.6.28 Community Edition 64 bits | AB24: SI | AC24: Veritas | AD24: Veritas-FUllMon-Ret15_UIO_02
J25: VIRTUAL | K25: tvc-srv-amas | L25: Servidor de amas - Relacionado con las llamadas telefonicas. | M25: 192.168.21.31 | O25: SI | P25: - | Q25: Hector Miranda /Administrador de aplicaciones | R25: Windows 10 | S25: 8 | T25: 931.65 | U25: 4 | V25: BAJO | W25: PRODUCCIÓN | AB25: SI | AC25: Veritas | AD25: Veritas-FUllMon-Ret15_UIO_02
J26: VIRTUAL | K26: tvc-srv-apjaira | L26: Mesa de Servicios - Flujos internos. (con el tiempo se dará de baja) | M26: 192.168.21.35 | O26: SI | P26: - | Q26: Hector Miranda /Administrador de aplicaciones | R26: Microsoft Windows Server 2016 (64-bit) | S26: 20 | T26: 400 | U26: 4 | V26: BAJO | W26: PRODUCCIÓN | X26: NA | Y26: NA | AB26: SI | AC26: Veritas | AD26: Veritas-FUllThu-Ret15_UIO_09
J27: VIRTUAL | K27: tvc-srv-appadm | L27: Aplicaciones del sistema de nomina - Datalife | M27: 192.168.21.101 | O27: - | P27: SI | Q27: Jaqueline Andrade/Carlos Ayala/Christian Castillo | R27: Microsoft Windows Server 2022 (64-bit) | S27: 16 | T27: 160 | U27: 2 | V27: ALTO | W27: PRODUCCIÓN | AB27: SI | AC27: Veritas | AD27: Veritas-FUllWed-Ret15_UIO_06
J28: VIRTUAL | K28: tvc-srv-as2back | L28: SERVIDOR DE RESPALDO DEL AS2, DE LA INFOPRMACIÓN QUE ESTA EN EL ONEDRIVE. (3ER RESPALDO) | M28: 192.168.21.15 | O28: - | P28: SI | Q28: Jose Fernandez/Ivone Intriago | R28: Microsoft Windows Server 2022 (64-bit) | S28: 4 | T28: 300 | U28: 4 | V28: ALTO | W28: PRODUCCIÓN | AB28: SI | AC28: Veritas | AD28: Veritas-FUllMon-Ret15_UIO_00 Veritas-FullFri-Ret15_UIO_14
J29: VIRTUAL | K29: tvc-srv-autosrv | L29: Servidor autoservicios | M29: 192.168.21.16 | O29: - | P29: SI | Q29: Hector Miranda /Administrador de aplicaciones | R29: Ubuntu 22,04 LTS Linux (64-bit) | S29: 8 | T29: 100 | U29: 4 | V29: ALTO | W29: PRODUCCIÓN | X29: NA | Y29: NA | AB29: SI | AC29: Veritas | AD29: Veritas-FUllTue-Ret15_UIO_05
J30: VIRTUAL | K30: tvc-srv-bdadm | L30: Base de datos de sistema de nomina | M30: 192.168.21.102 | O30: - | P30: SI | Q30: Jaqueline Andrade/Carlos Ayala/Christian Castillo | R30: Microsoft Windows Server 2022 (64-bit) | S30: 16 | T30: 500 | U30: 4 | V30: ALTO | W30: PRODUCCIÓN | AB30: SI | AC30: veritas | AD30: Veritas-FUllWed-Ret15_UIO_06
J31: VIRTUAL | K31: tvc-srv-cluster3 | L31: Cluster base de datos | M31: 192.168.21.25 | O31: - | P31: SI | Q31: Carlos Ayala / Christian Castillo | R31: Red Hat Enterprise Linux 9 (64-bit) | S31: 4 | T31: 400 | U31: 2 | V31: ALTO | W31: PRODUCCIÓN | X31: NA | Y31: NA | AB31: SI | AC31: Veritas | AD31: Veritas-FUllTue-Ret15_UIO_05
J32: VIRTUAL | K32: tvc-srv-colecsoc | L32: Logs del SOC | M32: 192.168.21.236 | O32: - | P32: SI | Q32: Jose Fernandez/Alejandro Alvarez | R32: Red Hat Enterprise Linux 9.2 (64-bit) | S32: 8 | T32: 250 | U32: 4 | V32: ALTO | W32: PRODUCCIÓN | AB32: SI | AC32: Veritas | AD32: Veritas-FUllMon-Ret15_UIO_01
J33: VIRTUAL | K33: tvc-srv-condell | L33: Servidor Thincliente Dell | M33: 192.168.21.5 | O33: - | P33: SI | Q33: Evelyn Puetate/Yurema Tobar | R33: Microsoft Windows Server 2019 (64-bit) | S33: 8 | T33: 100 | U33: 4 | V33: ALTO | W33: PRODUCCIÓN | X33: NA | Y33: NA | AB33: SI | AC33: Veritas
J34: VIRTUAL | K34: tvc-srv-dbas2bi | L34: Enviar informacion de base de datos AS2 | M34: 192.168.21.13 | N34: 200.63.213.82 | O34: - | P34: SI | Q34: Carlos Ayala/Christian Castillo | R34: Red Hat Enterprise Linux 9 (64-bit) | S34: 8 | T34: 300 | U34: 8 | V34: ALTO | W34: PRODUCCIÓN
J35: VIRTUAL | K35: tvc-srv-dbjaira | L35: Servidor base de datos Jira | M35: 192.168.21.36 | O35: SI | P35: - | Q35: Carlos Ayala/Christian Castillo | R35: Microsoft Windows Server 2012 (64-bit) | S35: 8 | T35: 550 | U35: 2 | V35: MEDIO | W35: PRODUCCIÓN | X35: SQL SERVER | Y35: SQL Server 2012 | AB35: SI | AC35: Veritas | AD35: Veritas-FUllThu-Ret15_UIO_09
J36: VIRTUAL | K36: tvc-srv-desa-www | L36: Servidor www FSM | M36: 192.168.21.197 | O36: SI | P36: - | Q36: Hector Miranda/Administrador de aplicaciones | R36: Red Hat Enterprise Linux 6 (64-bit) | S36: 38 | T36: 100 | U36: 10 | V36: ALTO | W36: DESARROLLO
J37: VIRTUAL | K37: tvc-srv-dhcpuio | L37: Servidor DHCP y consola de Unifi (Wifi) | M37: 192.168.21.2 | O37: SI | P37: - | Q37: Luis Conteron/Guillermo Jurado | R37: Microsoft Windows Server 2016 (64-bit) | S37: 8 | T37: 80 | U37: 4 | V37: ALTO | W37: PRODUCCIÓN | X37: NA | Y37: NA | AB37: SI | AC37: Veritas | AD37: Veritas-FUllWed-Ret15_UIO_08
J38: VIRTUAL | K38: tvc-srv-eleuio - ELIMINADO | L38: Servidor elearning TEC. overtime | M38: 192.168.21.242 | N38: 200.63.213.25 | Q38: Julio Enriquez | R38: Microsoft Windows Server 2016 (64-bit) | S38: 3 | T38: 250 | U38: 3 | V38: BAJO | W38: ELIMINADO | X38: NA | Y38: NA | AB38: NO equipo apagado
J39: VIRTUAL | K39: tvc-srv-exuio | L39: Servidor de Correo | M39: 192.168.21.50 192.168.21.196 | N39: 200.63.213.13 | O39: - | P39: SI | Q39: Evelyn Puetate/Yurema Tobar | R39: Microsoft Windows Server 2022 (64-bit) | S39: 20 | T39: =250+150 -> 400 | U39: 4 | V39: ALTO | W39: PRODUCCIÓN | X39: NA | Y39: NA | AB39: SI | AC39: Veritas | AD39: Veritas-FUllWed-Ret15_UIO_06
J40: VIRTUAL | K40: tvc-srv-finform | L40: Servidor de Formas Hiperk - Reemplazado por el AS2 | M40: 192.168.21.46 | O40: SI | P40: - | Q40: Hector Miranda/Administrador de aplicaciones | R40: Microsoft Windows Server 2016 (64-bit) | S40: 6 | T40: 250 | U40: 4 | V40: BAJO | W40: PREPRODUCCIÓN | X40: NA | Y40: NA | AB40: SI | AC40: Veritas | AD40: Veritas-FUllWed-Ret15_UIO_06
J41: VIRTUAL | K41: tvc-srv-fsm | L41: Base Datos FSM | M41: 192.168.21.124 | O41: SI | P41: - | Q41: Carlos Ayala/Christian Castillo | R41: Red Hat Enterprise Linux 6.4 (64-bit) | S41: 64 | T41: 3000 | U41: 8 | V41: ALTO | W41: PRODUCCIÓN | X41: ORACLE | Y41: Oracle 11g R2 | AB41: Se respalda Base de Datos | AC41: Veritas | AD41: Veritas-FUllTue-Ret15_UIO_04
J42: VIRTUAL | K42: tvc-srv-ftp | L42: FTP Recargas efectos de consiliaciones | M42: 192.168.21.157 | N42: 200.63.213.64 | O42: SI | P42: - | Q42: Hector Miranda/Administrador de aplicaciones | R42: Red Hat Enterprise Linux 6 (64-bit) | S42: 2 | T42: 60 | U42: 1 | V42: ALTO | W42: PRODUCCIÓN | X42: NA | Y42: NA | AB42: SI | AC42: Veritas | AD42: Veritas-FUllTue-Ret15_UIO_03
J43: VIRTUAL | K43: tvc-srv-ftpac | L43: Ftp actualizaciones BackOffice | M43: 192.168.21.203 | N43: 200.63.213.68 | O43: SI | P43: - | Q43: pendiente de confirmacion David Villamar | R43: Red Hat Enterprise Linux 6 (64-bit) | S43: 4 | T43: 50 | U43: 2 | V43: MEDIO | W43: PRODUCCIÓN | X43: NA | Y43: NA | AB43: SI | AC43: veeam | AD43: Veritas-FullFri-Ret15_UIO_12
J44: VIRTUAL | K44: tvc-srv-gruptvc | L44: Pruebas pagina Grupo TVCable | M44: 192.168.21.123 | O44: SI | P44: - | Q44: Carlos Ayala / David Villamar | R44: Red Hat Enterprise Linux 7 (64-bit) | S44: 4 | T44: 120 | U44: 2 | V44: BAJO | W44: PREPRODUCCIÓN | X44: MySQL | Y44: 5.6.28 Community Edition 64 bits | AB44: SI | AC44: Veritas | AD44: Veritas-FUllMon-Ret15_UIO_01
J45: VIRTUAL | K45: tvc-srv-guardium | L45: Servidor firewall base de datos | M45: 192.168.21.210 | N45: 200.63.213.56 | O45: SI | P45: - | Q45: Carlos Ayala/Christian Castillo | R45: Red Hat Enterprise Linux 7 (64-bit) | S45: 32 | T45: 1000 | U45: 8 | V45: ALTO | W45: PRODUCCIÓN | X45: MYSQL | Y45: MySQL modificado | AB45: SI | AC45: Veritas | AD45: Veritas-FUllTue-Ret15_UIO_04
J46: VIRTUAL | K46: tvc-srv-jenkins | L46: Servidor jenkins para bitbucket | M46: 192.168.21.14 | N46: 200.63.213.65 | O46: - | P46: SI | Q46: Mauricio Rodriguez | R46: Ubuntu Linux (64-bit) | S46: 6 | T46: 60 | U46: 2 | V46: MEDIO | W46: CONFIGURACIÓN | X46: NA | Y46: NA | AB46: SI | AC46: Veritas | AD46: Veritas-FUllTue-Ret15_UIO_03
J47: VIRTUAL | K47: tvc-srv-keycloak | L47: Keycloak | M47: 192.168.21.105 | O47: - | P47: SI | Q47: Graciela Ortiz | R47: Red Hat Enterprise Linux 9 (64-bit) | S47: 4 | T47: 80 | U47: 2 | V47: MEDIO | W47: PRODUCCIÓN | AB47: SI | AC47: Veritas | AD47: Veritas-FUllTue-Ret15_UIO_05
J48: VIRTUAL | K48: tvc-srv-malepo | L48: Mediador Alepo Comarch. | M48: 192.168.21.233 | O48: SI | P48: - | Q48: Pendiente de confirmacion Xavier Leon | R48: Microsoft Windows Server 2016 or later (64-bit) | S48: 20 | T48: 300 | U48: 4 | V48: ALTO | W48: PRODUCCIÓN | AB48: SI | AC48: Veritas | AD48: Veritas-FUllWed-Ret15_UIO_07
J49: VIRTUAL | K49: tvc-srv-malwareuio | L49: Srv Malware que analizará los backup de Veritas. | M49: 192.168.21.73 | O49: - | P49: SI | Q49: Evelyn Puetate/Yurema Tobar | R49: Red Hat Enterprise Linux 9 (64-bit) | S49: 32 | T49: =100+20 -> 120 | U49: 8 | V49: MEDIO | W49: PRODUCCIÓN | AB49: SI | AC49: Veritas | AD49: Veritas-FUllWed-Ret15_UIO_06
J50: VIRTUAL | K50: tvc-srv-mediaveritas | L50: Intermiediario para convertir un equipo fisico a virtual con la plataforma de veritas | M50: 192.168.21.38 | O50: - | P50: SI | Q50: Evelyn Puetate/Yurema Tobar | R50: Microsoft Windows Server 2022 (64-bit) | S50: 4 | T50: =160+279.366+1000 -> 1439.366 | U50: 2 | V50: BAJO | W50: PRODUCCIÓN | AB50: SI | AC50: Veritas | AD50: Veritas-FullFri-Ret15_UIO_13
J51: VIRTUAL | K51: tvc-srv-migracion | L51: Migracion y encriptacion de tablas y base de datos MYSQL | M51: 192.168.21.18 | O51: SI | P51: - | Q51: Carlos Ayala/Christian Castillo | R51: Microsoft Windows Server 2016 (64-bit) | S51: 8 | T51: 250 | U51: 4 | V51: ALTO | W51: PREPRODUCCIÓN | X51: NA | Y51: NA | AB51: SI | AC51: Veritas | AD51: Veritas-FUllThu-Ret15_UIO_09
J52: VIRTUAL | K52: tvc-srv-mobil | L52: Servidor MOBIL FSM | M52: 192.168.21.185 | N52: 200.63.213.61 | O52: SI | P52: - | Q52: Hector Miranda /Administrador de aplicaciones | R52: Red Hat Enterprise Linux 6 (64-bit) | S52: 30 | T52: 100 | U52: 8 | V52: ALTO | W52: PRODUCCIÓN | X52: NA | Y52: NA | AB52: SI | AC52: Veritas | AD52: Veritas-FUllMon-Ret15_UIO_02
J53: VIRTUAL | K53: tvc-srv-monitoreoapp - APAGADO | L53: Monitoreo aplicaciones - NAGIOS | M53: 192.168.21.194 | O53: - | P53: - | Q53: Hector Miranda | R53: Red Hat Enterprise Linux 6 (64-bit) | S53: 10 | T53: 150 | U53: 4 | V53: BAJO | W53: ELIMINADO | X53: NA | Y53: NA | AB53: SI | AC53: veeam
J54: VIRTUAL | K54: tvc-srv-myapp | L54: Aplicaciones Tecnico - Base de datos del isp de Tecnología | M54: 192.168.21.24 | O54: SI | P54: - | Q54: Tecnologia | R54: Microsoft Windows Server 2016 (64-bit) | S54: 12 | T54: 300 | U54: 6 | V54: MEDIO | W54: PRODUCCIÓN | X54: NA | Y54: NA | AB54: SI | AC54: veeam | AD54: Veritas-FullFri-Ret15_UIO_13
J55: VIRTUAL | K55: tvc-srv-napi | L55: Servidor de api del FSM | M55: 192.168.21.186 | O55: SI | P55: - | Q55: Hector Miranda /Administrador de aplicaciones | R55: Red Hat Enterprise Linux 6 (64-bit) | S55: 12 | T55: 120 | U55: 4 | V55: ALTO | W55: PRODUCCIÓN | X55: NA | Y55: NA | AB55: SI | AC55: Veritas | AD55: Veritas-FUllMon-Ret15_UIO_02
J56: VIRTUAL | K56: tvc-srv-nems | L56: Servidor webservice FSM/EMS | M56: 192.168.21.179 | O56: - | P56: SI | Q56: Hector Miranda /Administrador de aplicaciones | R56: Microsoft Windows Server 2022 (64-bit) | S56: 14 | T56: 150 | U56: 4 | V56: ALTO | W56: PRODUCCIÓN | X56: NA | Y56: NA | AB56: SI | AC56: Veritas | AD56: Veritas-FUllWed-Ret15_UIO_07
J57: VIRTUAL | K57: tvc-srv-nfieb | L57: sistema Ebissnez intermix servicios de facturacion | M57: 192.168.21.209 | N57: 200.63.213.67 | O57: - | P57: SI | Q57: Hector Miranda /Administrador de aplicaciones | R57: Microsoft Windows Server 2022 (64-bit) | S57: 12 | T57: 300 | U57: 6 | V57: ALTO | W57: PRODUCCIÓN | X57: NA | Y57: NA | AB57: SI | AC57: Veritas | AD57: Veritas-FUllWed-Ret15_UIO_06
J58: VIRTUAL | K58: tvc-srv-njbdps | L58: Pruebas página de Xtrim En el servidor 21.189 se encuentran las siguientes aplicaciones 1. JBoss y CM de Desarrollo 2. Dps de desarrollo 3. JBoss y CM de AQTEST 4. Dps de desarrollo (QAtest) Adicionalmente funciona como repositorio ftp para transacciones de pruebas, como por ejemplo 1. SoftSwitch 2. Débitos automáticos 3. Cdr 4. Facturación electronica de prueba. | M58: 192.168.21.189 | O58: SI | P58: - | Q58: Hector Miranda /Administrador de aplicaciones | R58: CentOS Linux release 7.9.2009 (Core) | S58: 8 | T58: =240+120 -> 360 | U58: 4 | V58: BAJO | W58: PREPRODUCCIÓN | X58: NA | Y58: NA | AB58: SI | AC58: Veritas | AD58: Veritas-FUllMon-Ret15_UIO_02
J59: VIRTUAL | K59: tvc-srv-nmensajeria | L59: Enviar mensajes para Conax.SMS. Pagina de Vendedores. https://vendedores.xtrim.tv/LoginEfx.aspx | M59: 192.168.21.251 | O59: SI | P59: - | Q59: Hector Miranda /Administrador de aplicaciones | R59: Microsoft Windows Server 2016 (64-bit) | S59: 8 | T59: 200 | U59: 4 | V59: ALTO | W59: PRODUCCIÓN | X59: NA | Y59: NA | AB59: SI | AC59: Veritas | AD59: Veritas-FUllWed-Ret15_UIO_08
J60: VIRTUAL | K60: tvc-srv-nsofbd | L60: Nuevo servidor base de datos soft | M60: 192.168.21.211 | O60: - | P60: SI | Q60: Carlos Ayala/Christian Castillo | R60: Microsoft Windows Server 2019 (64-bit) | S60: 4 | T60: 300 | U60: 2 | V60: ALTO | W60: PRODUCCIÓN | X60: SQL SERVER | Y60: SQL Server 2019 | AB60: SI | AC60: Veritas | AD60: Veritas-FUllWed-Ret15_UIO_07
J61: VIRTUAL | K61: tvc-srv-ntpuio | L61: Servidor NTP Alepo | M61: 192.168.21.238 | O61: SI | P61: - | Q61: Pendiente de confirmacion Xavier Leon | R61: Red Hat Enterprise Linux 7.9 (64-bit) | S61: 32 | T61: =100+1000 -> 1100 | U61: 8 | V61: ALTO | W61: PRODUCCIÓN | X61: ORACLE | Y61: Oracle 11g R2
J62: VIRTUAL | K62: tvc-srv-nuevapiis | L62: Servidores de aplicaciones, donde se encuentra el servicio de Biometria que hace la conexión con https://adocolumbia.ado-tech.com/TVCable/api/Integration/TVCable/Validation/StartCompareFaces, para ello debe tener permiso el acceso al puerto 443 y asi mismo tiene otras conexiones hacia otros servicios que se identificaran en el transcurso del día. | M62: 192.168.21.155 | O62: SI | P62: - | Q62: Hector Miranda /Administrador de aplicaciones | R62: Microsoft Windows Server 2016 (64-bit) | S62: 24 | T62: 200 | U62: 8 | V62: ALTO | W62: PRODUCCIÓN | X62: NA | Y62: NA | AB62: SI | AC62: Veritas | AD62: Veritas-FUllWed-Ret15_UIO_07
J63: VIRTUAL | K63: tvc-srv-oracleasr | L63: Monitoreo de ODA | M63: 192.168.21.70 | O63: - | P63: - | Q63: Evelyn Puetate/Yurema Tobar | R63: Other (64-bit) | S63: 8 | T63: 70 | U63: 2 | V63: ALTO | W63: PRODUCCIÓN | X63: NA | Y63: NA | AB63: SI | AC63: Veritas | AD63: Veritas-FUllTue-Ret15_UIO_03
J64: VIRTUAL | K64: tvc-srv-pbxprov | L64: Central Telefónica Provincias | M64: 192.168.21.21 | O64: SI | P64: - | Q64: Luis Conteron/Guillermo Jurado | R64: Centos 7 | S64: 16 | T64: 100 | U64: 4 | V64: ALTO | W64: PRODUCCIÓN | X64: NA | Y64: NA | AB64: SI | AD64: Veritas-FUllTue-Ret15_UIO_03
J65: VIRTUAL | K65: tvc-srv-pbxuio | L65: Central Telefónica UIO | M65: 192.168.21.75 | O65: SI | P65: - | Q65: Luis Conteron /Guillermo Jurado | R65: CentOS 7 (64-bit) | S65: 16 | T65: 500 | U65: 4 | V65: ALTO | W65: PRODUCCIÓN | AB65: SI | AC65: Veritas | AD65: Veritas-FUllTue-Ret15_UIO_03
J66: VIRTUAL | K66: tvc-srv-preapi | L66: Servidor API FSM | M66: 192.168.21.188 | O66: SI | P66: - | Q66: Hector Miranda /Administrador de aplicaciones | R66: Red Hat Enterprise Linux 6 (64-bit) | S66: 48 | T66: =100+100 -> 200 | U66: 2 | V66: ALTO | W66: PREPRODUCCIÓN | X66: NA | Y66: NA | AB66: SI | AC66: Veritas | AD66: Veritas-FUllMon-Ret15_UIO_01
J67: VIRTUAL | K67: tvc-srv-predb | L67: Servidor pruebas base de datos FSM | M67: 192.168.21.182 | N67: 200.63.213.34 | O67: SI | P67: - | Q67: Carlos Ayala/Christian Castillo | R67: Red Hat Enterprise Linux 6 (64-bit) | S67: 16 | T67: 300 | U67: 2 | V67: BAJO | W67: PREPRODUCCIÓN | X67: ORACLE | Y67: Oracle 11g R2 | AB67: SI | AC67: Veritas | AD67: Veritas-FUllMon-Ret15_UIO_02
J68: VIRTUAL | K68: tvc-srv-proxyvrtuio | L68: Agente de Veritas, levanta la consola del NETbackup que permite generar y restaturar los respaldos | M68: 192.168.19.13 | O68: - | P68: SI | Q68: Evelyn Puetate/Yurema Tobar | R68: Red Hat Enterprise Linux 9.2 (64-bit) | S68: 8 | T68: 80 | U68: 8 | V68: ALTO | W68: PRODUCCIÓN | X68: NA | Y68: NA | AB68: SI | AC68: Veritas | AD68: Veritas-FUllTue-Ret15_UIO_05
J69: VIRTUAL | K69: tvc-srv-qaapi | L69: Servidor pruebas API FSM | M69: 192.168.21.187 | O69: SI | P69: - | Q69: Hector Miranda /Administrador de aplicaciones | R69: Red Hat Enterprise Linux 6 (64-bit) | S69: 48 | T69: 120 | U69: 2 | V69: BAJO | W69: PREPRODUCCIÓN | X69: NA | Y69: NA | AB69: SI | AC69: Veritas | AD69: Veritas-FUllMon-Ret15_UIO_01
J70: VIRTUAL | K70: tvc-srv-qtev-vir | L70: Qlik Sense - Analitica de datos que le permite hacer frente a los problemas analiticos más complejos. Servidor critico para la toma de decisiones de la compañia, porque es el resumen de las ventas que tiene la empresa. | M70: 192.168.21.100 | N70: 200.63.213.31 | O70: SI | P70: - | Q70: Veronica Molina | R70: Windows Server 2016 | S70: 196 | T70: =279.37+1000 -> 1279.37 | U70: 24 | V70: ALTO | W70: PRODUCCIÓN | X70: NA | Y70: NA | AB70: SI | AC70: Veritas | AD70: Veritas-FUllThu-Ret15_UIO_10
J71: VIRTUAL | K71: tvc-srv-repfin | L71: Repositorio de documentos para F.Eléctronica | M71: 192.168.21.176 | O71: SI | P71: - | Q71: Hector Miranda /Administrador de aplicaciones | R71: Red Hat Enterprise Linux 7 (64-bit) | S71: 12 | T71: =250+50 -> 300 | U71: 6 | V71: ALTO | W71: PRODUCCIÓN | X71: NA | Y71: NA | AB71: SI | AC71: Veritas | AD71: Veritas-FUllMon-Ret15_UIO_01
J72: VIRTUAL | K72: tvc-srv-robot | L72: Backup Robot | M72: 192.168.21.163 | O72: SI | P72: - | Q72: Hector Miranda /Administrador de aplicaciones | R72: Microsoft Windows Server 2016 (64-bit) | S72: 20 | T72: 250 | U72: 8 | V72: MEDIO | W72: PREPRODUCCIÓN | X72: NA | Y72: NA | AB72: SI | AC72: Veritas | AD72: Veritas-FUllThu-Ret15_UIO_09
J73: VIRTUAL | K73: tvc-srv-rpdr | L73: Servidor de RapidDR, para el manejo de tareas de failover del simplivity | M73: 192.168.21.110 | O73: SI | P73: - | Q73: Evelyn Puetate | R73: Microsoft Windows Server 2016 (64-bit) | S73: 8 | T73: 120 | U73: 4 | V73: ALTO | W73: PRODUCCIÓN | X73: NA | Y73: NA | AB73: si | AC73: Veritas | AD73: Veritas-FUllMon-Ret15_UIO_01
J74: VIRTUAL | K74: tvc-srv-satelitepam | L74: Servidor de Pandora FMS Enterprise | M74: 192.168.21.240 | O74: - | P74: SI | Q74: Evelyn Puetate/Yurema Tobar | R74: Red Hat Enterprise Linux 8 (64-bit) | S74: 4 | T74: 80 | U74: 4 | V74: MEDIO | W74: PRODUCCIÓN | AB74: SI | AC74: Veritas | AD74: Veritas-FUllTue-Ret15_UIO_03
J75: VIRTUAL | K75: tvc-srv-shpapp - ELIMINADO | L75: - | M75: 192.168.21.154 | N75: - | O75: - | P75: - | Q75: - | R75: - | S75: 8 | T75: 120 | U75: 2 | W75: ELIMINADO
J76: VIRTUAL | K76: tvc-srv-shpdb | L76: Base de datos Share Point | M76: 192.168.21.156 | O76: - | P76: SI | Q76: Carlos Ayala/Christian Castillo | R76: Microsoft Windows Server 2012 (64-bit) | S76: 24 | T76: =110+11230+300 -> 11640 | U76: 4 | V76: BAJO | W76: PRODUCCIÓN | X76: SQL SERVER | Y76: SQL Server 2012 Standard Edition | AB76: SI | AC76: Veritas | AD76: Veritas-FUllThu-Ret15_UIO_09
J77: VIRTUAL | K77: tvc-srv-shpdb1 | L77: Base de datos para SharePoint | M77: 192.168.21.127 | N77: 200.63.213.58 | O77: - | P77: SI | Q77: Carlos Ayala/Christian Castillo | R77: Microsoft Windows Server 2012 (64-bit) | S77: 32 | T77: =420+600 -> 1020 | U77: 4 | V77: BAJO | W77: ELIMINADO | X77: SQL SERVER | Y77: SQL Server 2012 SP4 | AB77: SI | AC77: veeam
J78: VIRTUAL | K78: tvc-srv-shpso1 | L78: SharePoint | M78: 192.168.21.137 | O78: - | P78: SI | Q78: Hector Miranda /Administrador de aplicaciones | R78: Microsoft Windows Server 2012 (64-bit) | S78: 20 | T78: 300 | U78: 6 | V78: BAJO | W78: PRODUCCIÓN | X78: NA | Y78: NA | AB78: SI | AC78: Veritas | AD78: Veritas-FUllThu-Ret15_UIO_10
J79: VIRTUAL | K79: tvc-srv-smsdth | L79: Pruebas sms DTH | M79: 192.168.21.44 | O79: - | P79: SI | Q79: APAGADO | R79: Microsoft Windows Server 2016 (64-bit) | S79: 8 | T79: 250 | U79: 4 | V79: BAJO | W79: ELIMINAR | X79: MYSQL | Y79: MySQL 5.1.36-community edition | AB79: SI | AC79: Veritas | AD79: Veritas-FUllThu-Ret15_UIO_10
J80: VIRTUAL | K80: tvc-srv-sofpro | L80: Servidor softswitch bancos | M80: 192.168.21.158 | O80: - | P80: SI | Q80: Hector Miranda /Administrador de aplicaciones | R80: Microsoft Windows Server 2016 (64-bit) | S80: 16 | T80: 200 | U80: 4 | V80: ALTO | W80: PRODUCCIÓN | X80: NA | Y80: NA | AB80: SI | AC80: Veritas
J81: VIRTUAL | K81: tvc-srv-softbd | L81: Base datos softswich de pagos - bancos | M81: 192.168.21.159 | N81: 200.63.213.30 | O81: - | P81: SI | Q81: Carlos Ayala/Christian Castillo | R81: Microsoft Windows Server 2012 (64-bit) | S81: 16 | T81: 200 | U81: 4 | V81: ALTO | W81: PRODUCCIÓN | X81: SQL SERVER | Y81: SQL Server 2012 Standard Edition | AB81: SI | AC81: Veritas | AD81: Veritas-FUllWed-Ret15_UIO_08
J82: VIRTUAL | K82: tvc-srv-softbd2 | L82: Base datos softswich de pagos - bancos-pruebas de bancos | M82: 192.168.21.212 | P82: SI | Q82: Carlos Ayala/Christian Castillo | R82: Microsoft Windows Server 2012 (64-bit) | S82: 16 | T82: 200 | U82: 4 | V82: ALTO | W82: PRUEBAS | X82: SQL SERVER | Y82: SQL Server 2012 Standard Edition | AB82: SI | AC82: Veritas | AD82: Veritas-FullFri-Ret15_UIO_13
J83: VIRTUAL | K83: tvc-srv-ssprodu | L83: Base datos de sofswitch y debitos automaticos producción | M83: 192.168.21.103 | O83: - | P83: SI | Q83: Carlos Ayala / Hector Miranda | R83: Microsoft Windows Server 2022 (64-bit) | S83: 32 | T83: 350 | U83: 4 | V83: ALTO | W83: PRODUCCIÓN | X83: SQL SERVER | Y83: SQL Server 2019 Standard Edition | AB83: SI | AC83: Veritas | AD83: Veritas-FUllThu-Ret15_UIO_09
J84: VIRTUAL | K84: tvc-srv-sonarqube | L84: Aplicativo SONARQUBE para analisis de codigo | M84: 192.168.21.39 | P84: SI | Q84: Mauricio Rodriguez | R84: Red Hat Enterprise Linux 9.2 (64-bit) | S84: 12 | T84: 150 | U84: 2 | V84: MEDIO | W84: PRODUCCIÓN | AB84: SI | AC84: veritas | AD84: Veritas-FullThu-Ret15_UIO_09
J85: VIRTUAL | K85: tvc-srv-sopcomarch | L85: Soporte de comarch | M85: 192.168.21.30 | P85: SI | Q85: Hector Miranda / Graciela Ortiz | R85: Microsoft Windows Server 2022 (64-bit) | S85: 8 | T85: 150 | U85: 4 | V85: MEDIO | W85: PRUEBAS | AB85: SI | AC85: veritas | AD85: Veritas-FullThu-Ret15_UIO_09
J86: VIRTUAL | K86: tvc-srv-techin | L86: Sistema de control de ingreso | M86: 192.168.21.3 | O86: SI | P86: - | Q86: Carlos Ayala / Administrador de aplicaciones / Angel Zambrano | R86: Microsoft Windows Server 2016 (64-bit) | S86: 20 | T86: 1300 | U86: 8 | V86: MEDIO | W86: PRODUCCIÓN | X86: SQL SERVER | Y86: SQL Server 2012 Standard Edition | AB86: SI | AC86: veritas | AD86: Veritas-FUllWed-Ret15_UIO_08
J87: VIRTUAL | K87: tvc-srv-wso2nod3 | L87: Servidor Dockers Net Core Apis | M87: 192.168.21.178 | N87: 200.63.213.33 | Q87: Hector Miranda / Graciela Ortiz | R87: Red Hat Enterprise Linux 7 (64-bit) | S87: 8 | T87: 250 | U87: 2 | V87: BAJO | W87: PRODUCCIÓN | X87: NA | Y87: NA | AB87: SI | AC87: veeam | AD87: Veritas-FullFri-Ret15_UIO_13
J88: VIRTUAL | K88: tvc-srv-testeb | L88: Desarrollo de Ebizness | M88: 192.168.21.223 | O88: - | P88: SI | Q88: Hector Miranda / Graciela Ortiz | R88: Microsoft Windows Server 2022 (64-bit) | S88: 12 | T88: 350 | U88: 6 | V88: BAJO | W88: PREPRODUCCIÓN | X88: NA | Y88: NA | AB88: SI | AC88: veritas | AD88: Veritas-FUllThu-Ret15_UIO_10
J89: VIRTUAL | K89: tvc-srv-tiflow | L89: Servidor flujos TI | M89: 192.168.21.221 | O89: SI | P89: - | Q89: Graciela Ortiz | R89: Microsoft Windows Server 2012 (64-bit) | S89: 10 | T89: 600 | U89: 4 | V89: MEDIO | W89: PRODUCCIÓN | X89: NA | Y89: NA | AB89: SI | AC89: Veritas | AD89: Veritas-FUllThu-Ret15_UIO_10
J90: VIRTUAL | K90: tvcsrvvcu | L90: Vcenter Quito | M90: 192.168.21.9 | O90: - | P90: - | Q90: Evelyn Puetate | R90: Other 3.x or later Linux (64-bit) | S90: 19 | T90: 700.35 | U90: 4 | V90: ALTO | W90: PRODUCCIÓN | X90: NA | Y90: NA | AB90: SI | AC90: veritas | AD90: Veritas-FUllTue-Ret15_UIO_05
J91: VIRTUAL | K91: tvc-srv-veritas (ELIMINADO) | L91: Servidor Respaldos Veritas NetBackup | M91: 192.168.21.125 | Q91: Evelyn Puetate | R91: Microsoft Windows Server 2016 (64-bit) | S91: 20 | T91: 250 | U91: 8 | V91: ALTO | W91: PRODUCCIÓN | X91: ORACLE | Y91: Oracle 11g R2 | AB91: SI
J92: VIRTUAL | K92: tvc-srv-veritasflexuio | L92: SERVIDOR QUE SERÁ LA COMUNICACIÓN DIRECTA AL FLEX VERITAS, PARA EJECUTAR EL JAVA. | M92: 192.168.21.244 | O92: - | P92: SI | Q92: Evelyn Puetate | R92: Red Hat Enterprise Linux 9.2 (64-bit) | S92: 4 | T92: 80 | U92: 2 | V92: ALTO | W92: PRODUCCIÓN
J93: VIRTUAL | K93: tvc-srv-webdth | L93: WEB DTH, Conciliador Prepago, Integrador Satelital, Cas Integrador | M93: 192.168.21.191 | N93: 200.63.213.17 | Q93: APAGADO | R93: Microsoft Windows Server 2016 (64-bit) | S93: 10 | T93: 250 | U93: 4 | V93: ALTO | W93: ELIMINAR | X93: SQL SERVER | Y93: SQL Server 2012 Standard Edition | AB93: SI | AC93: Veritas | AD93: Veritas-FUllThu-Ret15_UIO_10
J94: VIRTUAL | K94: tvc-srv-whatsupg (apagado) | L94: Monitoreo red | M94: 192.168.21.20 | Q94: Hector Miranda | R94: Microsoft Windows Server 2016 or later (64-bit) | S94: 12 | T94: 500 | U94: 4 | V94: BAJO | W94: A ELIMINAR | X94: NA | Y94: NA | AB94: NO equipo apagado
J95: VIRTUAL | K95: tvc-srv-medi2 | L95: Mediador windows prueba. Servidor donde esta el front operativo de servicios, para reiniciar los dps y los daemon. | M95: 192.168.21.205 | O95: - | P95: SI | Q95: Hector Miranda | R95: Microsoft Windows Server 2022 (64-bit) | S95: 14 | T95: 300 | U95: 6 | V95: BAJO | W95: PREPRODUCCIÓN | X95: NA | Y95: NA | AB95: SI | AC95: Veritas | AD95: Veritas-FUllWed-Ret15_UIO_08
J96: VIRTUAL | K96: tvc-srv-wmedia2 | L96: Servidor mediación 02. Servidor donde esta el front operativo de servicios, para reiniciar los dps y los daemon. | M96: 192.168.21.104 | N96: 200.63.213.14 | O96: SI | P96: - | Q96: Hector Miranda | R96: Microsoft Windows Server 2016 (64-bit) | S96: 10 | T96: 300 | U96: 6 | V96: ALTO | W96: PRODUCCIÓN | X96: NA | Y96: NA | AB96: SI | AC96: Veritas | AD96: Veritas-FUllWed-Ret15_UIO_08
J97: VIRTUAL | K97: tvc-srv-www | L97: Servidor www FSM | M97: 192.168.21.184 | N97: 200.63.213.62 | O97: SI | P97: - | Q97: Hector Miranda | R97: Red Hat Enterprise Linux 6 (64-bit) | S97: 38 | T97: 100 | U97: 10 | V97: ALTO | W97: PRODUCCIÓN | X97: NA | Y97: NA | AB97: SI | AC97: Veritas | AD97: Veritas-FUllMon-Ret15_UIO_01
J98: VIRTUAL | K98: tvc-srv-XtrimTest | L98: pagina de Xtrim - PRODUCCION | M98: 192.168.21.190 | N98: 200.63.213.90 | O98: SI | P98: - | Q98: Hector Miranda | R98: CentOS 7 (64-bit) | S98: 16 | T98: 250 | U98: 2 | V98: ALTO | W98: PRODUCCIÓN | X98: NA | Y98: NA | AB98: SI | AC98: Veritas | AD98: Veritas-FUllTue-Ret15_UIO_03
J99: VIRTUAL | K99: tvc-srv-xtvcable | L99: Boton de pago, el administrador de xtrim e ingreso de contrato. App Movil y Web service de los canales de Xtrim. Tiene Base de datos. https://mixtrim.com.ec/administrador/ | M99: 192.168.21.129 | N99: 200.63.213.26 | O99: SI | P99: - | Q99: Hector Miranda | R99: Red Hat Enterprise Linux 7 (64-bit) | S99: 18 | T99: 200 | U99: 10 | V99: ALTO | W99: PRODUCCIÓN | X99: MYSQL | Y99: MySQL 5.1.57-community edition | AB99: SI | AC99: veritas | AD99: Veritas-FUllMon-Ret15_UIO_01
J100: VIRTUAL | K100: tvc-srv-aduio1 | L100: Active Directory Principal | M100: 192.168.21.42 | O100: SI | P100: - | Q100: Evelyn Puetate /Yurema Tobar | R100: Microsoft Windows Server 2016 (64-bit) | S100: 20 | T100: 250 | U100: 8 | V100: ALTO | W100: PRODUCCIÓN | X100: NA | Y100: NA | AB100: SI | AC100: Veritas | AD100: Veritas-FUllWed-Ret15_UIO_06
J101: VIRTUAL | K101: tvc-srvmysql | L101: Servidor base de datos mediacion | M101: 192.168.21.206 | O101: SI | P101: - | Q101: Carlos Ayala/Christian Castillo | R101: Red Hat Enterprise Linux 5 (64-bit) | S101: 6 | T101: 200 | U101: 4 | V101: ALTO | W101: PRODUCCIÓN | X101: MYSQL | Y101: MySQL 5.1.57-community edition | AB101: SI | AC101: Veritas | AD101: Veritas-FUllMon-Ret15_UIO_02
J102: VIRTUAL | K102: tvc-srvmysql-test | L102: Base de datos mediador de test, de aprovisionamiento para enviar comando en los equipos de los clientes. | M102: 192.168.21.193 | O102: SI | P102: - | Q102: Carlos Ayala/Christian Castillo | R102: Red Hat Enterprise Linux 5 (64-bit) | S102: 6 | T102: 200 | U102: 4 | V102: BAJO | W102: PREPRODUCCIÓN | X102: MYSQL | Y102: MySQL 5.1.57-community edition | AB102: SI | AC102: veeam | AD102: Veritas-FullFri-Ret15_UIO_12
J103: VIRTUAL | K103: tvc-srvpamuio | L103: Servidor de Boveda de Claves (PAM) | M103: 192.168.21.107 | N103: 200.63.213.35 | O103: SI | P103: - | Q103: Evelyn Puetate /Yurema Tobar | R103: Microsoft Windows Server 2016 (64-bit) | S103: 16 | T103: 110 | U103: 4 | V103: ALTO | W103: PRODUCCIÓN | X103: NA | Y103: NA | AB103: SI | AC103: Veritas | AD103: Veritas-FUllThu-Ret15_UIO_09
J104: VIRTUAL | K104: tvc-srvtestlink | L104: Servidor para QA Testlink | O104: SI | P104: - | Q104: APAGADO | R104: Red Hat Enterprise Linux 5,5 (64-bit) | S104: 4 | T104: 40 | U104: 1 | V104: BAJO | W104: PREPRODUCCIÓN | X104: NA | Y104: NA | AB104: SI | AC104: veeam | AD104: Veritas-FullFri-Ret15_UIO_12
...

Sheet GYE 2025
E2: INVENTARIO DE SERVIDORES VIRTUALIZADOS Y FISICOS GYE 2025
A5: Fecha de actualización: 25/09/2025 | H5: Actualizado por: | I5: Mireya Iturralde
B6: ENCLOSURE | C6: SRV FISICOS | D6: SERIE | E6: IP del blade | F6: TOTAL SRV FISICOS | G6: CARACTERISTICAS | H6: SOPORTE | I6: # SRV VIRTUALES | J6: TIPO DE SERVIDOR | K6: SRV VIRTUALES | L6: APLICACIÓN | M6: IP INTERNA | N6: IP PUBLICA | O6: PROTECCIÓN DE TREND MCRO XDR - SRV | P6: CORTEX | Q6: Persona responsable del uso del SRV | R6: PANDORA | S6: SISTEMA OPERATIVO | T6: MEMORIA | U6: Espacio Disco | V6: Procesador | W6: SISTEMAS CRITICOS | X6: NIVEL DE BACKUP | Y6: SERVIDOR PRODUCCIÓN / PREPRODUCCIÓN | Z6: BASE DE DATOS | AA6: VERSIÓN DB | AB6: COSTO SOPORTE | AC6: EMPRESA QUE DA SOPORTE | AD6: BACKUP SE REALIZA | AE6: PLATAFORMA DE BACKUP | AF6: POLITICA DE BACKUP | AG6: COMENTARIO
A7: GYE - C7000 | B7: C7000 - VDI | C7: BL460C | D7: CZ3741XKMH | E7: 192.168.9.50 | F7: 2 | G7: 2X Gen9, Intel(R) Xeon(R) CPU E5-2620 v4 @ 2.10GHz, 2 slot de c/u 128GB en total 256 GB RAM | H7: TERMINA 2023 | I7: =COUNTIF(J7:J8,"=VIRTUAL") -> 0 | AG7: -
C8: BL460C | D8: CZ3741XKN1 | E8: 192.168.9.49 | G8: 2X Gen9, Intel(R) Xeon(R) CPU E5-2620 v4 @ 2.10GHz, 2 slot de c/u de 128 GB en total 256 GB RAM | H8: TERMINA 2023 | AG8: No se ejecuta porque, es un srv replicado del cloud1
C9: BL460C | D9: CZ3741XKMF | E9: 192.168.9.51 | G9: 2X Gen9, Intel(R) Xeon(R) CPU E5-2620 v4 @ 2.10GHz, 2 slot de c/u 128GB en total 256 GB RAM | H9: TERMINA 2023 | J9: VIRTUAL | K9: TVC-SRV-N8NDES | L9: Pruebas con un software de gestión documental | M9: 192.168.77.21 | O9: - | P9: SI | Q9: Mauricio Rodriguez | R9: SI | S9: Red Hat Enterprise Linux 9.5 (64-bit) | T9: 8 | U9: 70 | V9: 2 | X9: BAJO | Y9: PREPRODUCCIÓN | Z9: NA | AA9: NA | AD9: SI | AE9: veritas | AF9: Veritas-FullWed-Ret90_GYE_18
C10: BL460C | E10: 192.168.9.53 | F10: 2 | G10: 2X Gen9, Intel(R) Xeon(R) CPU E5-2620 v4 @ 2.10GHz, 2 slot de c/u 128GB en total 256 GB RAM | H10: TERMINA 2023 | J10: VIRTUAL | K10: TVC-SRV-GYELZBXDB01 | L10: Proyecto Zabbix | M10: 192.168.77.22 | O10: - | P10: SI | Q10: Jose Fernandez/ Alejandro Alvarez | R10: SI | S10: Red Hat Enterprise Linux 9.5 (64-bit) | T10: 8 | U10: 100 | V10: 4 | X10: BAJO | Y10: PREPRODUCCIÓN | Z10: NA | AA10: NA | AD10: SI | AE10: veritas | AF10: Veritas-FullWed-Ret90_GYE_18
J11: VIRTUAL | K11: TVC-SRV-GYELZBXSRV01 | L11: Proyecto Zabbix | M11: 192.168.77.23 | O11: - | P11: SI | Q11: Jose Fernandez/ Alejandro Alvarez | R11: si | S11: Red Hat Enterprise Linux 9.5 (64-bit) | T11: 8 | U11: 100 | X11: BAJO | Y11: PREPRODUCCIÓN | Z11: NA | AA11: NA | AD11: SI | AE11: veritas | AF11: Veritas-FullWed-Ret90_GYE_18
J12: VIRTUAL | K12: XTR-SRV-WORKERNODTES | L12: CLUSTER KUBERNETS WORKER NODE PARA EL NUEVO BSS AMBIENTE DE TEST | M12: 192.168.76.24 | O12: - | P12: SI | Q12: Harry Salvatierra | R12: SI | S12: Red Hat Enterprise Linux 9.5 (64-bit) | T12: 16 | U12: 100 | V12: 8 | X12: MEDIO | Y12: TEST | AD12: SI | AE12: veritas | AF12: Veritas-Full-TueRet90_GYE_19
J13: VIRTUAL | K13: XTR-SRV-MASTERNODTES | L13: CLUSTER KUBERNETS MASTER NODE PARA EL NUEVO BSS AMBIENTE DE TEST | M13: 192.168.76.25 | O13: - | P13: SI | Q13: Harry Salvatierra | R13: SI | S13: Red Hat Enterprise Linux 9.5 (64-bit) | T13: 8 | U13: 50 | V13: 4 | X13: MEDIO | Y13: TEST | AD13: SI | AE13: veritas | AF13: Veritas-Full-TueRet90_GYE_19
J14: VIRTUAL | K14: XTR-SRV-WORKERNODDES | L14: CLUSTER KUBERNETS WORKER NODE PARA EL NUEVO BSS AMBIENTE DESARROLLO | M14: 192.168.77.11 | S14: Red Hat Enterprise Linux 9.5 (64-bit) | T14: 16 | U14: 100 | V14: 8 | X14: MEDIO | Y14: PREPRODUCCIÓN | AE14: veritas | AF14: Veritas-Full-MonRet90_GYE_20
J15: VIRTUAL | K15: XTR-SRV-MASTERNODDES | L15: CLUSTER KUBERNETS MASTER NODE PARA EL NUEVO BSS AMBIENTE DESARROLLO | M15: 192.168.77.10 | S15: Red Hat Enterprise Linux 9.5 (64-bit) | T15: 8 | U15: 50 | V15: 4 | X15: MEDIO | Y15: PREPRODUCCIÓN | AE15: veritas | AF15: Veritas-Full-MonRet90_GYE_20
J16: VIRTUAL | K16: TVC-SRV-LANDINGPAGE | L16: Boton de pagos-SRV ligado a landingpagebak y pro | M16: 192.168.76.21 | O16: - | P16: SI | Q16: David Villamar | R16: SI | S16: Ubuntu 22.04 LTS | T16: 4 | U16: 100 | V16: 4 | X16: ALTO | Y16: PREPRODUCCIÓN | AD16: SI | AE16: veritas | AF16: Veritas-Full-TueRet90_GYE_19
J17: VIRTUAL | K17: TVC-SRV-MEDIADORDACCclon | M17: 192.168.77.27
J18: VIRTUAL | K18: tvc-srv-njbdps2clon | M18: 192.168.77.28
J19: VIRTUAL | K19: XTR-SRV-BACKEND-VT | L19: Es usado para la celula de ventas, que lo configura Daniel Solano. Conexión con bitbucket.TEST | M19: 192.168.76.29 | O19: - | P19: SI | R19: SI | S19: Red Hat Enterprise Linux 9.5 (64-bit) | T19: 16 | U19: 250 | V19: 4 | W19: ALTO | X19: ALTO | Y19: TEST | AD19: SI | AE19: veritas | AF19: Veritas-FullSun-Ret90_GYE_14
J20: VIRTUAL | K20: XTR-SRV-PLAYOPSTES | M20: 192.168.76.15 | R20: SI | S20: Ubuntu 22.04 LTS
J21: VIRTUAL | K21: XTR-SRV-BACKEND-VTA | L21: Es usado para la celula de ventas, que lo configura Daniel Solano. Conexión con bitbucket.DESA | M21: 192.168.77.31 | P21: SI | Q21: Harry Salvatierra | R21: SI | S21: Red Hat Enterprise Linux 9.5 (64-bit) | T21: 16 | U21: 250 | V21: 4 | X21: MEDIO | Y21: PREPRODUCCIÓN | AD21: SI | AE21: veritas | AF21: Veritas-Full-TueRet90_GYE_19
J22: VIRTUAL | K22: XTR-SRV-DBRRHH | L22: BASE DE DATOS para el CMS (Sistema de gestión de contenido) del proyecto Intranet Xtrim. | M22: 192.168.77.32 | O22: SI | P22: - | R22: SI | S22: Red Hat Enterprise Linux 9.5 (64-bit) | T22: 4 | U22: 80 | V22: 4 | X22: BAJO | Y22: PREPRODUCCIÓN | AD22: SI | AE22: veritas | AF22: Veritas-FullWed-Ret90_GYE_18
J23: VIRTUAL | K23: XTR-SRV-DBINTRAXTR | L23: SERVIDOR DE BASES DE DATOS PARA EL PROYECTO DE RRHH - INTRANET (AMBIENTE DE TEST) | M23: 192.168.76.50 | Q23: Miguel Briones / Carlos Ayala | R23: SI | S23: Red Hat Enterprise Linux 9.5 (64-bit) | T23: 16 | U23: 100 | V23: 8 | X23: ALTO | Y23: TEST | Z23: SI | AD23: SI | AE23: veritas | AF23: Veritas-FullThu-Ret90_GYE_17
J24: VIRTUAL | K24: XTR-SRV-xtrimdesa-ad | L24: SERVIDOR DE DNS PARA EL AMBIENTE DE DESARROLLO Y TEST | M24: 192.168.77.35 | N24: APAGADO | O24: SI | Q24: Mireya Iturralde | R24: SI | S24: WINdows Server 2016 | T24: 12 | U24: 200 | V24: 6 | W24: ALTO | X24: ALTO | Y24: PREPRODUCCIÓN
J25: VIRTUAL | K25: XTR-SRV-FRONTEND-VT | L25: celula de ventas | M25: 192.168.76.30 | O25: - | P25: SI | R25: SI | S25: Red Hat Enterprise Linux 9.5 (64-bit) | T25: 16 | U25: 250 | V25: 4 | W25: ALTO | X25: ALTO | Y25: TEST | AD25: SI | AE25: veritas | AF25: Veritas-FullSun-Ret90_GYE_14
J26: VIRTUAL | K26: XTR-SRV-FRONTEND-VT | L26: Es usado para la celula de ventas, que lo configura Daniel Solano. Conexión con bitbucket.TEST | M26: 192.168.76.30 | S26: Red Hat Enterprise Linux 9.5 (64-bit) | T26: 16 | U26: 250 | V26: 4 | X26: MEDIO | Y26: TEST | AD26: SI | AE26: veritas | AF26: Veritas-FullSun-Ret90_GYE_14
J27: VIRTUAL | K27: XTR-SRV-FRONTEND-VTA | L27: Es usado para la celula de ventas, que lo configura Daniel Solano. Conexión con bitbucket.DESA | M27: 192.168.77.30 | P27: SI | Q27: Harry Salvatierra | R27: SI | S27: Red Hat Enterprise Linux 9.5 (64-bit) | T27: 16 | U27: 250 | V27: 4 | X27: MEDIO | Y27: PREPRODUCCIÓN | AD27: SI | AE27: veritas | AF27: Veritas-Full-TueRet90_GYE_19
J28: VIRTUAL | K28: XTR-SRV-GYELDASH01 | L28: GRAFANA(herramienta de visualización de datos y monitoreo de código abierto) | M28: 192.168.77.24 | O28: - | P28: SI | Q28: Jose Fernandez/ Alejandro Alvarez | R28: SI | S28: Red Hat Enterprise Linux 9.5 (64-bit) | T28: 8 | U28: 100 | V28: 4 | X28: BAJO | Y28: PREPRODUCCIÓN | AD28: SI | AE28: veritas | AF28: Veritas-FullWed-Ret90_GYE_18
J29: VIRTUAL | K29: XTR-SRV-GYELIPAM01 | L29: IPAM(herramientas utilizadas para gestionar y organizar las direcciones IP) | M29: 192.168.77.25 | O29: - | P29: SI | Q29: Jose Fernandez/ Alejandro Alvarez | R29: SI | S29: Ubuntu 22.04 LTS | T29: 8 | U29: 100 | V29: 4 | X29: BAJO | Y29: PREPRODUCCIÓN | AD29: SI | AE29: veritas | AF29: Veritas-FullWed-Ret90_GYE_18
J30: VIRTUAL | K30: XTR-SRV-LANDZAPPING | L30: Boton de pagosZAPPING -SRV ligado a landzappingbak y pro | M30: 192.168.76.28 | P30: SI | Q30: David Villamar | R30: SI | S30: Ubuntu 22.04 LTS | T30: 4 | U30: 100 | V30: 4 | X30: ALTO | Y30: TEST | AD30: SI | AE30: veritas | AF30: Veritas-Full-TueRet90_GYE_19
J31: VIRTUAL | K31: XTR-SRV-MASTERNODDES | M31: 192.168.77.10 | Q31: Harry Salvatierra | R31: SI | S31: Red Hat Enterprise Linux 9.5 (64-bit) | T31: 16 | U31: 100 | V31: 8 | X31: MEDIO | Y31: DES | AE31: veritas | AF31: Veritas-Full-MonRet90_GYE_20
J32: VIRTUAL | K32: XTR-SRV-WORKERNODDES | M32: 192.168.77.11 | Q32: Harry Salvatierra | R32: SI | S32: Red Hat Enterprise Linux 9.5 (64-bit) | T32: 16 | U32: 50 | V32: 8 | X32: MEDIO | Y32: DES | AE32: veritas | AF32: Veritas-Full-MonRet90_GYE_20
J33: VIRTUAL | K33: XTR-SRV-N8NTEST | L33: para la aplicación de automatización N8N | M33: 192.168.76.31 | O33: SI | Q33: Mauricio Rodriguez | R33: SI | S33: Red Hat Enterprise Linux 9.5 (64-bit) | T33: 8 | U33: 70 | V33: 8 | X33: BAJO | Y33: TEST | AD33: SI | AE33: veritas | AF33: Veritas-FullThu-Ret90_GYE_17
J34: VIRTUAL | K34: xtr-srv-njdpstest | L34: Servidor replica del 21,189 como test | M34: 192.168.76.42 | O34: SI | Q34: Harry Salvatierra | R34: SI | S34: CENTOS 7 | T34: 8 | U34: 240 | V34: 4 | X34: BAJO | Y34: TEST | AD34: SI | AE34: veritas | AF34: Veritas-Full-TueRet90_GYE_19
J35: VIRTUAL | K35: XTR-SRV-PORTALOPE | L35: servidor para Portal de Operaciones | M35: 192.168.77.34 | O35: SI | R35: SI | S35: REd Hat Enterprise Linux 9.5 (64-bit) | T35: 8 | U35: 150 | V35: 2 | X35: BAJO | Y35: PREPRODUCCIÓN | AD35: SI | AE35: veritas | AF35: Veritas-FullThu-Ret90_GYE_17
J36: VIRTUAL | K36: XTR-SRV-SGSI01 | L36: Herramienta CISO Assistant para llevar el control del SGSI en Ciberseguridad. | M36: 192.168.77.36 | O36: SI | Q36: Jose Fernandez/ Alejandro Alvarez | R36: SI | S36: REd Hat Enterprise Linux 9.5 (64-bit) | T36: 16 | U36: 100 | V36: 4 | X36: BAJO | Y36: PREPRODUCCIÓN | AD36: SI | AE36: veritas | AF36: Veritas-FullThu-Ret90_GYE_17
J37: VIRTUAL | K37: TVCSRVVCG | L37: VCENTER DE GUAYAQUIL | M37: 192.168.59.130 | O37: NO | P37: NO | R37: SI | S37: VMWARE PHOTO OS | T37: 19 | U37: 720 | V37: 4 | X37: ALTO | Y37: PRODUCCIÓN | AD37: SI | AE37: veritas | AF37: Veritas-FullThu-Ret90_GYE_15
C38: NO MOVER | J38: VIRTUAL | K38: TVC-SRV-ARBITER | L38: Servidor Arbitrario para el simplivity, permite la comunicación con los nodos GYE. Se puede reiniciar el servidor pero siempre debe estar arriba, porque si existe un problema con los nodos del Simplivity, luego no habria quien gestione quien es el nodo master. | M38: 192.168.59.54 | O38: - | P38: SI | Q38: Mireya Iturralde | R38: SI | S38: Windows Server 2019 | T38: 4 | U38: 50 | V38: 2 | X38: ALTO | Y38: PRODUCCIÓN | Z38: NA | AA38: NA | AD38: SI | AE38: veritas | AF38: Veritas-FullThu-Ret90_GYE_17 | AG38: -
B39: C7000-TEC | C39: BL460C | D39: CZ3741XKMS | E39: 192.168.94.41 | F39: 1 | G39: 2X Gen9, Intel(R) Xeon(R) CPU E5-2620 v4 @ 2.10GHz, 2 slot de c/u de 128GB en total 256 GB RAM | H39: TERMINA 2023 | J39: FISICO
C40: BL460C | D40: CZ3741XKMY | E40: 192.168.94.42 | F40: 1 | G40: 2X Gen9, Intel(R) Xeon(R) CPU E5-2620 v4 @ 2.10GHz, 2 slot de c/u de 128GB en total 256 GB RAM | H40: TERMINA 2023 | J40: nmen
C41: BL460C | D41: CZ3741XKMD | E41: 192.168.94.43 | F41: 1 | G41: 2X Gen9, Intel(R) Xeon(R) CPU E5-2620 v4 @ 2.10GHz, 2 slot de c/u de 128GB en total 256 GB RAM | H41: TERMINA 2023 | J41: FISICO
B42: HP C7000 | C42: BL460C | E42: 192.168.9.49 | F42: 1 | G42: 2X Gen10, Intel(R) Xeon(R) Gold 5120 CPU @ 2.20GHz, 2 slot de memoria : de 128GB y 256GB, en total 384 GB RAM | H42: TERMINA 2023 | I42: - | J42: FISICO | M42: 192.168.9.49 | O42: SI | P42: - | T42: 384 | U42: 9728 | V42: 16 | X42: MEDIO | Y42: PRODUCCIÓN | Z42: ORACLE | AA42: Oracle 11g R2 | AD42: NO | AF42: Por tema de espacio no tenemos donde almacenar 9TB, y no hay espacio para instalar un plugin de veeam y respaldar el srv oracle. | AG42: Por tema de espacio no tenemos donde almacenar 9TB, y no hay espacio para instalar un plugin de veeam y respaldar el srv oracle.
B43: HP C7000 - DBFLASH | C43: BL460C | D43: 2M293800B9 | E43: 192.168.59.12 | F43: 1 | G43: 2X Gen10, Intel(R) Xeon(R) Gold 5120 CPU @ 2.20GHz, 2 slot de memoria : de 128GB y 256GB, en total 384 GB RAM | H43: TERMINA 2023 | I43: - | J43: FISICO | K43: TVC-SRV-DBFLASH | L43: BASE DE DATOS STAND BY DE FSM POR FLASH COPY | M43: 192.168.59.12 | O43: SI | P43: - | Q43: Carlos Ayala / Hector Miranda | R43: SI | S43: Oracle Linux 7.6 | T43: 384 | U43: 9728 | V43: 16 | X43: MEDIO | Y43: PRODUCCIÓN | Z43: ORACLE | AA43: Oracle 11g R2 | AD43: NO | AF43: Por tema de espacio no tenemos donde almacenar 9TB, y no hay espacio para instalar un plugin de veeam y respaldar el srv oracle. | AG43: Por tema de espacio no tenemos donde almacenar 9TB, y no hay espacio para instalar un plugin de veeam y respaldar el srv oracle.
A45: GYE - SIMPLIVITY | B45: tvc-nodo1gye | C45: ProLiant DL380 2 x Intel(R) Xeon(R) Gold 6238 CPU @ 2.10GHz x 22 Cores | D45: 2M232601ZM | E45: 192.168.9.28 | F45: 4 | G45: Gen 10, 1 TB RAM Y 25TB | H45: SI | I45: =COUNTIF(J45:J156,"=VIRTUAL") -> 112 | J45: VIRTUAL | K45: ise-xtrim-APcisco | L45: Servidor de Access Point de Cisco, e sun OVA. | M45: 192.168.59.30 | O45: NO | P45: NO | Q45: Sergio AScencio / Luis Conteron | R45: SI | S45: Red Hat Enterprise Linux 7 | T45: 16 | U45: 600 | V45: 8 | X45: ALTO | Y45: PRODUCCIÓN | Z45: NA | AA45: NA | AD45: SI | AE45: veritas | AF45: Veritas-FullMon-Ret90_GYE_13 | AG45: -
B46: tvc-nodo2gye | D46: 2M232601ZJ | E46: 192.168.9.30 | G46: Gen 10, 1 TB RAM Y 25TB | H46: SI | J46: VIRTUAL | K46: FORTIANALYZER-VM64 | L46: Servidor Forticlient | M46: 192.168.59.41 | O46: NO | P46: NO | Q46: Sergio AScencio / Luis Conteron | R46: SI | S46: FortiAnalyzer-VM64 - OTRO | T46: 16 | U46: 1024 | V46: 8 | X46: ALTO | Y46: PRODUCCIÓN | Z46: NA | AA46: NA | AD46: SI | AE46: veritas | AF46: Veritas-FullThu-Ret90_GYE_15 | AG46: -
B47: tvc-nodo3gye | D47: 2M232601ZK | E47: 192.168.9.32 | G47: Gen 10, 1 TB RAM Y 25TB | H47: SI | J47: VIRTUAL | K47: OmniStackVC-192-168-9-29 | L47: OMNISTACK DEL NODO 1 DEL SIMPLIVITY | M47: 192.168.9.29 | O47: NO | P47: NO | Q47: Mireya Iturralde | R47: SI | S47: Ubuntu Linux (64-bit) | T47: 92 | U47: 210 | V47: 8 | X47: ALTO | Y47: PRODUCCIÓN | Z47: NA | AA47: NA | AD47: SI | AF47: es propio del Simplivity | AG47: es propio del Simplivity
B48: tvc-nodo4gye | D48: 2M232601ZL | E48: 192.168.9.34 | G48: Gen 10, 1 TB RAM Y 25TB | H48: SI | J48: VIRTUAL | K48: OmniStackVC-192-168-9-31 | L48: OMNISTACK DEL NODO 2 DEL SIMPLIVITY | M48: 2 | O48: NO | P48: NO | Q48: Mireya Iturralde | R48: SI | S48: Ubuntu Linux (64-bit) | T48: 92 | U48: 210 | V48: 8 | X48: ALTO | Y48: PRODUCCIÓN | Z48: NA | AA48: NA | AD48: SI | AF48: es propio del Simplivity | AG48: es propio del Simplivity
J49: VIRTUAL | K49: OmniStackVC-192-168-9-33 | L49: OMNISTACK DEL NODO 3 DEL SIMPLIVITY | M49: 192.168.9.33 | O49: NO | P49: NO | Q49: Mireya Iturralde | R49: SI | S49: Ubuntu Linux (64-bit) | T49: 92 | U49: 210 | V49: 8 | X49: ALTO | Y49: PRODUCCIÓN | Z49: NA | AA49: NA | AD49: SI | AF49: es propio del Simplivity | AG49: es propio del Simplivity
J50: VIRTUAL | K50: OmniStackVC-192-168-9-35 | L50: OMNISTACK DEL NODO DEL SIMPLIVITY | M50: 192.168.9.35 | O50: NO | P50: NO | Q50: Mireya Iturralde | R50: SI | S50: Ubuntu Linux (64-bit) | T50: 92 | U50: 210 | V50: 8 | X50: ALTO | Y50: PRODUCCIÓN | Z50: NA | AA50: NA | AD50: SI | AF50: es propio del Simplivity | AG50: es propio del Simplivity
J51: VIRTUAL | K51: TVC-SRV-ADMCTX | L51: Servidor histórico para monitorear por 1 hora, 2 enlaces del balanceador que se considere más crítico o con mayor tráfico. Es parte del netscaler y permite el envió de notificaciones de las alertas de SSL. | M51: 192.168.9.225 | O51: NO | P51: NO | Q51: Mireya Iturralde | R51: SI | S51: FreeBSD 11 - OTR 64bits | T51: 32 | U51: =120+512 -> 632 | V51: 8 | W51: ALTO | X51: MEDIO | Y51: PRODUCCIÓN | Z51: NA | AA51: NA | AD51: SI | AF51: Veritas-Fulltue-Ret90_GYE_01 | AG51: -
J52: VIRTUAL | K52: TVC-SRV-ANUBIS | L52: Caja segura de claves NAC | M52: 192.168.59.118 | O52: - | P52: SI | Q52: Jose Fernandez | R52: SI | S52: Debian 12 - OTR 64bits | T52: 4 | U52: 100 | V52: 2 | W52: ALTO | X52: BAJO | Y52: PRODUCCIÓN | Z52: NA | AA52: NA | AD52: SI | AE52: veritas | AF52: Veritas-FullWed-Ret90_GYE_02 | AG52: -
J53: VIRTUAL | K53: TVC-SRV-APP | L53: Despliegue de multiples aplicaciones (Inventario, Ficha medica, Sistema de grabaciones, y otras herramientas, keycloack) | M53: 192.168.59.131 | N53: 190.154.47.131 | O53: SI | P53: - | Q53: Administrador de aplicaciones / Carlos Ayala / Hector Miranda | R53: SI | S53: Microsoft Windows Server 2016 | T53: 6 | U53: 200 | V53: 6 | W53: ALTO | X53: MEDIO | Y53: PRODUCCIÓN | Z53: NA | AA53: NA | AD53: SI | AE53: veritas | AF53: Veritas-FullWed-Ret90_GYE_02 | AG53: -
J54: VIRTUAL | K54: TVC-SRVAPPMOV | L54: servicio de notificaciones y App movil pruebas. (registro de nat. Confirmado por Hector Miranda) | M54: 192.168.59.117 | N54: 190.154.47.117 | O54: SI | P54: - | Q54: Hector Miranda | R54: SI | S54: Microsoft Windows Server 2016 | T54: 6 | U54: 200 | V54: 4 | W54: ALTO | X54: ALTO | Y54: PRODUCCIÓN | Z54: NA | AA54: NA | AD54: SI | AE54: veritas | AF54: Veritas-FullWed-Ret90_GYE_02 | AG54: -
J55: VIRTUAL | K55: TVC-SRV-ARCOTEL | L55: Servidor para las funcionalides de ARCOTEL | M55: 192.168.59.56 | O55: SI | P55: - | Q55: Jose Fernandez/ Alejandro Alvarez | R55: SI | S55: Windows 10 PRO | T55: 16 | U55: 500 | V55: 6 | W55: ALTO | X55: ALTO | Y55: PRODUCCIÓN | Z55: NA | AA55: NA | AD55: SI | AE55: veritas | AF55: Veritas-FullWed-Ret90_GYE_02
J56: VIRTUAL | K56: TVC-SRV-AXAP | L56: Servidor AXENTRIA | M56: 192.168.59.120 | O56: SI | P56: - | Q56: Graciela Ortiz | R56: SI | S56: Microsoft Windows Server 2016 | T56: 8 | U56: 200 300 1224 1024 | V56: 6 | W56: ALTO | X56: ALTO | Y56: PRODUCCIÓN | Z56: NA | AA56: NA | AD56: SI | AE56: veritas | AF56: Veritas-FullWed-Ret90_GYE_02 | AG56: -
J57: VIRTUAL | K57: TVC-SRV-AXSP | L57: Base de Datos del Servidor AXENTRIA | M57: 192.168.59.121 | O57: SI | P57: - | Q57: Graciela Ortiz | R57: SI | S57: Microsoft Windows Server 2016 | T57: 24 | U57: 200 500 | V57: 6 | W57: ALTO | X57: ALTO | Y57: PRODUCCIÓN | Z57: SQL SERVER | AA57: SQL Server 2019 Standard Edition SP1 | AD57: SI | AE57: veritas | AF57: Veritas-FullWed-Ret90_GYE_02 | AG57: -
J58: VIRTUAL | K58: TVC-SRV-AXWWW | L58: Servidor AXENTRIA - consultas WEB | M58: 192.168.59.122 | O58: SI | P58: - | Q58: Graciela Ortiz | R58: SI | S58: Microsoft Windows Server 2016 | T58: 8 | U58: 200 | V58: 4 | W58: ALTO | X58: ALTO | Y58: PRODUCCIÓN | Z58: NA | AA58: NA | AD58: SI | AE58: veritas | AF58: Veritas-FullWed-Ret90_GYE_02 | AG58: -
J59: VIRTUAL | K59: TVC-SRV-CCLOUD1 | L59: Servidor Cloud Clonnect de Citrix Principal | M59: 192.168.59.226 | O59: - | P59: SI | Q59: Mireya Iturralde | R59: SI | S59: Microsoft Windows Server 2022 | T59: 4 | U59: 100 | V59: 4 | X59: ALTO | Y59: PRODUCCIÓN | Z59: NA | AA59: NA | AD59: SI | AE59: veritas | AF59: Veritas-FullSun-Ret90_GYE_16 | AG59: -
J60: VIRTUAL | K60: TVC-SRV-CCLOUD2 | L60: Servidor Cloud Clonnect de Citrix Secundario | M60: 192.168.59.225 | O60: - | P60: SI | Q60: Mireya Iturralde | R60: SI | S60: Microsoft Windows Server 2022 | T60: 4 | U60: 100 | V60: 4 | X60: BAJO | Y60: PRODUCCIÓN | Z60: NA | AA60: NA | AD60: SI | AE60: veritas | AF60: Veritas-FullSun-Ret90_GYE_16 | AG60: No se ejecuta porque, es un srv replicado del cloud1
J61: VIRTUAL | K61: TVC-SRV-CENTELEF | L61: Central Telefonia Nueva | M61: 192.168.59.152 | N61: 190.154.47.152 | O61: NO | P61: NO | Q61: Luis Conteron | R61: SI | S61: Sangoma Linux release 7.8.2003 (Core) -OTR | T61: 4 | U61: 50 | V61: 2 | W61: ALTO | X61: MEDIO | Y61: PRODUCCIÓN | Z61: NA | AA61: NA | AD61: SI | AE61: veritas | AF61: Veritas-FullTue-Ret90_GYE_03 | AG61: -
J62: VIRTUAL | K62: TVC-SRV-CENTELEF2 | L62: Central Telefonia Nueva | O62: NO | P62: NO | Q62: Luis Conteron | R62: SI | S62: Sangoma Linux release 7.8.2003 (Core) -OTR | T62: 4 | U62: 50 | V62: 2 | W62: ALTO | X62: MEDIO | Y62: PRODUCCIÓN | Z62: NA | AA62: NA | AD62: SI | AE62: veritas | AF62: Veritas-FullTue-Ret90_GYE_03 | AG62: -
J63: VIRTUAL | K63: TVC-SRV-CLUSTER1 | L63: Servidor para cluster DB (escritura y lectura) A LA ESPERA DE CONFIRMACION DE CAYALA | M63: 192.168.59.43 | O63: - | P63: SI | Q63: James Pesantes /Carlos Ayala | R63: SI | S63: Red Hat Enterprise Linux 9.3 (64-bit) | T63: 8 | U63: =100+300 -> 400 | V63: 2 | X63: ALTO | Y63: PRODUCCIÓN | Z63: MYSQL | AA63: MySQL 8 community edition | AD63: SI | AE63: veritas | AF63: Veritas-FullTue-Ret90_GYE_03
J64: VIRTUAL | K64: TVC-SRV-CLUSTER2 | L64: Servidor para cluster DB (escritura y lectura) | M64: 192.168.59.45 | O64: - | P64: SI | Q64: James Pesantes /Carlos Ayala | R64: SI | S64: Red Hat Enterprise Linux 9.3 (64-bit) | T64: 4 | U64: =100+300 -> 400 | V64: 2 | X64: ALTO | Y64: PRODUCCIÓN | Z64: MYSQL | AA64: MySQL 8 community edition | AD64: SI | AE64: veritas | AF64: Veritas-FullTue-Ret90_GYE_03
J65: VIRTUAL | K65: TVC-SRV-COLSOC | L65: Colector de log del SOC | M65: 192.168.59.119 | O65: - | P65: SI | Q65: Jose Fernandez | R65: SI | S65: Red Hat Enterprise Linux 9.3 (64-bit) | T65: 8 | U65: 250 | V65: 4 | W65: ALTO | X65: MEDIO | Y65: PRODUCCIÓN | AD65: SI | AE65: veritas | AF65: Veritas-FullTue-Ret90_GYE_03
J66: VIRTUAL | K66: TVC-SRV-CONTV | L66: Servidor para la consola de tv que se asignaran a las islas | M66: 192.168.59.58 | N66: 190.154.47.58 | O66: - | P66: SI | Q66: Elsa Garcia | R66: SI | S66: Microsoft Windows Server 2022 | T66: 16 | U66: 350 | V66: 2 | W66: ALTO | X66: MEDIO | Y66: PRODUCCIÓN | Z66: NA | AA66: NA | AD66: SI | AE66: veritas | AF66: Veritas-FullFrid-Ret90_GYE_09 | AG66: APAGADO EL 22 DE ENERO DE 2025
J67: VIRTUAL | K67: TVC-SRV-CTXIM0 | L67: Imagen maestra para servidores web y win de citrix | M67: 192.168.59.221 | N67: APAGADO | O67: - | P67: SI | Q67: Mireya Iturralde | R67: SI | S67: Microsoft Windows Server 2022 | T67: 8 | U67: 230 | V67: 4 | X67: ALTO | Y67: PRODUCCIÓN | Z67: NA | AA67: NA | AD67: SI | AE67: veritas | AF67: Veritas-FullSun-Ret90_GYE_16 | AG67: -
J68: VIRTUAL | K68: TVC-SRV-CTXWB01 | L68: Servidor web para citrix cloud. | M68: 192.168.17.16 | O68: - | P68: SI | Q68: Mireya Iturralde | R68: SI | S68: Microsoft Windows Server 2022 | T68: 32 | U68: 230 | V68: 4 | X68: MEDIO | Y68: PRODUCCIÓN | Z68: NA | AA68: NA | AD68: NO | AF68: SERVIDOR ES UN CLON DE LA IMAGEN MAESTRA | AG68: SERVIDOR ES UN CLON DE LA IMAGEN MAESTRA
J69: VIRTUAL | K69: TVC-SRV-CTXWN01 | L69: Servidor de aplicaciones windows para citrix cloud. | M69: 192.168.17.12 | O69: - | P69: SI | Q69: Mireya Iturralde | R69: SI | S69: Microsoft Windows Server 2022 | T69: 32 | U69: 230 | V69: 4 | X69: MEDIO | Y69: PRODUCCIÓN | Z69: NA | AA69: NA | AD69: NO | AF69: SERVIDOR ES UN CLON DE LA IMAGEN MAESTRA | AG69: SERVIDOR ES UN CLON DE LA IMAGEN MAESTRA
J70: VIRTUAL | K70: TVC-SRV-CTXWN02 | L70: Servidor de aplicaciones windows para citrix cloud. | M70: 192.168.17.10 | O70: - | P70: SI | Q70: Mireya Iturralde | R70: SI | S70: Microsoft Windows Server 2022 | T70: 32 | U70: 230 | V70: 4 | X70: MEDIO | Y70: PRODUCCIÓN | Z70: NA | AA70: NA | AD70: NO | AF70: SERVIDOR ES UN CLON DE LA IMAGEN MAESTRA | AG70: SERVIDOR ES UN CLON DE LA IMAGEN MAESTRA
J71: VIRTUAL | K71: TVC-SRV-CTXWN03 | L71: Servidor de aplicaciones windows para citrix cloud. | M71: 192.168.17.13 | O71: - | P71: SI | Q71: Mireya Iturralde | R71: SI | S71: Microsoft Windows Server 2022 | T71: 32 | U71: 230 | V71: 4 | X71: MEDIO | Y71: PRODUCCIÓN | Z71: NA | AA71: NA | AD71: NO | AF71: SERVIDOR ES UN CLON DE LA IMAGEN MAESTRA | AG71: SERVIDOR ES UN CLON DE LA IMAGEN MAESTRA
J72: VIRTUAL | K72: TVC-SRV-CTXWN04 | L72: Servidor de aplicaciones windows para citrix cloud. | M72: 192.168.17.14 | O72: - | P72: SI | Q72: Mireya Iturralde | R72: SI | S72: Microsoft Windows Server 2022 | T72: 32 | U72: 230 | V72: 4 | X72: MEDIO | Y72: PRODUCCIÓN | Z72: NA | AA72: NA | AD72: NO | AF72: SERVIDOR ES UN CLON DE LA IMAGEN MAESTRA | AG72: SERVIDOR ES UN CLON DE LA IMAGEN MAESTRA
J73: VIRTUAL | K73: TVC-SRV-CTXWN05 | L73: Servidor de aplicaciones windows para citrix cloud. | M73: 192.168.17.15 | O73: - | P73: SI | Q73: Mireya Iturralde | R73: SI | S73: Microsoft Windows Server 2022 | T73: 32 | U73: 230 | V73: 4 | X73: MEDIO | Y73: PRODUCCIÓN | Z73: NA | AA73: NA | AD73: NO | AF73: SERVIDOR ES UN CLON DE LA IMAGEN MAESTRA | AG73: SERVIDOR ES UN CLON DE LA IMAGEN MAESTRA
J74: VIRTUAL | K74: TVC-SRV-DBALL | L74: Servidor de base de datos para el balanceador. Mysql. de pruebas (confirmado ccastillo) | M74: 192.168.59.204 /IP VIRTUAL 59.52 | O74: - | P74: SI | Q74: James Pesantes /Carlos Ayala | R74: SI | S74: Red Hat Enterprise Linux 9.3 (64-bit) | T74: 8 | U74: 150 300 | V74: 4 | W74: BAJO | X74: ALTO | Y74: PREPRODUCCIÓN | Z74: MYSQL | AA74: MySQL 8 community edition | AD74: SI | AE74: veritas | AF74: Veritas-FullSun-Ret90_GYE_06 | AG74: -
J75: VIRTUAL | K75: TVC-SRV-DBALL1 | L75: Servidor de base de datos para el balanceador. Mysql | M75: 192.168.59.206 | O75: - | P75: SI | Q75: James Pesantes /Carlos Ayala | R75: SI | S75: Red Hat Enterprise Linux 9.3 (64-bit) | T75: 12 | U75: 150 300 | V75: 16 | W75: ALTO | X75: ALTO | Y75: PRODUCCIÓN | Z75: MYSQL | AA75: MySQL 8 community edition | AD75: SI | AE75: veritas | AF75: Veritas-FullSun-Ret90_GYE_06 | AG75: -
J76: VIRTUAL | K76: TVC-SRV-DBALL2 | L76: Servidor de base de datos para el balanceador. Mysql | M76: 192.168.59.207 | O76: - | P76: SI | Q76: James Pesantes /Carlos Ayala | R76: SI | S76: Red Hat Enterprise Linux 9.3 (64-bit) | T76: 8 | U76: 150 300 | V76: 4 | W76: ALTO | X76: ALTO | Y76: PRODUCCIÓN | Z76: MYSQL | AA76: MySQL 8 community edition | AD76: SI | AE76: veritas | AF76: Veritas-FullSun-Ret90_GYE_06 | AG76: -
J77: VIRTUAL | K77: TVC-SRV-DBAPP | L77: Servidor de Base de datos de multiples aplicaciones (Inventario, Ficha medica, Sistema de grabaciones, y otras herramientas) | M77: 192.168.59.137 | N77: 190.154.47.209 | O77: SI | P77: - | Q77: James Pesantes /Carlos Ayala / Hector Miranda | R77: SI | S77: Microsoft Windows Server 2016 | T77: 12 | U77: 200 500 | V77: 4 | W77: ALTO | X77: ALTO | Y77: PRODUCCIÓN | Z77: SQL SERVER | AA77: SQL Server 2019 Standard Edition SP1 | AD77: SI | AE77: veritas | AF77: Veritas-FullMon-Ret90_GYE_13 | AG77: -
J78: VIRTUAL | K78: TVC-SRVDBCRM | L78: Servidor DB CRM | M78: 192.168.59.202 | O78: SI | P78: - | Q78: James Pesantes /Carlos Ayala / Hector Miranda | R78: SI | S78: Microsoft Windows Server 2016 | T78: 10 | U78: 200 500 | V78: 4 | W78: ALTO | X78: ALTO | Y78: PRODUCCIÓN | Z78: SQL SERVER | AA78: SQL Server 2016 Standard Edition | AD78: SI | AE78: veritas | AF78: Veritas-FullThu-Ret90_GYE_04 | AG78: -
J79: VIRTUAL | K79: TVC-SRV-DBING | L79: Servidor de ingreso de contrato con su respectiva base de datos. | M79: 192.168.59.55 | N79: 190.154.47.55 | O79: - | P79: SI | Q79: James Pesantes /Carlos Ayala / Hector Miranda | R79: SI | S79: Red Hat Enterprise Linux 9.2 (64-bit) | T79: 8 | U79: 250 | V79: 4 | W79: ALTO | X79: ALTO | Y79: PRODUCCIÓN | Z79: NA | AA79: NA | AD79: SI | AE79: veritas | AF79: Veritas-FullThu-Ret90_GYE_04 | AG79: -
J80: VIRTUAL | K80: TVC-SRV-DBPANDORA | L80: Servidor de base de Datos de Pandora FMS Enterprise | M80: 192.168.59.113 | O80: - | P80: SI | Q80: Carlos Ayala /James Pesantes / Yurema Tobar | R80: SI | S80: Red Hat Enterprise Linux 8 (64-bit) | T80: 16 | U80: 500 | V80: 8 | W80: ALTO | X80: ALTO | Y80: PRODUCCIÓN | AD80: SI | AE80: veritas | AF80: Veritas-FullTue-Ret90_GYE_03 | AG80: -
J81: VIRTUAL | K81: TVC-SRV-DBSQL | L81: Servidor de base de datos para el balanceador. SQL SERVER | M81: 192.168.59.205 | O81: - | P81: SI | Q81: Carlos Ayala / Mauricio Rodriguez | R81: SI | S81: Microsoft Windows Server 2022 | T81: 12 | U81: =100+150+200 -> 450 | V81: 4 | W81: DAR DE BAJA | X81: DAR DE BAJA | Y81: - | AD81: SI | AE81: veritas | AF81: Veritas-FullThu-Ret90_GYE_15 | AG81: -
J82: VIRTUAL | K82: TVC-SRV-DHCPGYE | L82: Servidor deDHCP para GYE. A la espera para cambiar el DHCP a este servidor. | M82: 192.168.59.84 | O82: - | P82: SI | Q82: Yurema Tobar / Mireya Iturralde | R82: SI | S82: Microsoft Windows Server 2022 | T82: 16 | U82: 100 | V82: 4 | W82: ALTO | X82: ALTO | Y82: PRODUCCIÓN | Z82: NA | AA82: NA | AD82: SI | AE82: veritas | AF82: Veritas-FullTue-Ret90_GYE_03
J83: VIRTUAL | K83: TVC-SRV-DISTRECOMMERCE | L83: Servidor para ECOMMERCE de ventas de terceros, para la autenticación de distribuidores de ventas. Para que la información de E-commerce de distribuidor no se mezcle con la información de E-commerce de servicio que está en producción. | M83: 192.168.59.127 | N83: 190.154.47.127 | O83: - | P83: SI | Q83: Administrador de aplicaciones / Hector Miranda | R83: SI | S83: Red Hat Enterprise Linux 9.2 (64-bit) | T83: 4 | U83: 120 | V83: 8 | W83: ALTO | X83: MEDIO | Y83: PRODUCCIÓN | AD83: SI | AE83: veritas | AF83: Veritas-FullTue-Ret90_GYE_03 | AG83: -
J84: VIRTUAL | K84: TVC-SRV-DNACENTER | L84: Servidor pde DNA center, para administración global de todos los SW Cisco de GYE y UIO. | M84: 192.168.59.229 | O84: NO | P84: NO | Q84: Mireya Iturralde | R84: SI | S84: Ubuntu - OVA | T84: 256 | U84: =100+550+2295 -> 2945 | V84: 32 | W84: ALTO | X84: BAJO | Y84: PRODUCCIÓN | Z84: NA | AA84: NA | AD84: SI | AE84: veritas | AF84: Veritas-Fulltue-Ret90_GYE_01 | AG84: -
J85: VIRTUAL | K85: TVC-SRV-ELASTICSEARCH | L85: Servicio de syslog y experiencia de usuario de pandora | M85: 192.168.59.25 | O85: - | P85: SI | Q85: Mireya Iturralde | R85: SI | S85: Rocky 8.7- OTR | T85: 6 | U85: 70 | V85: 2 | W85: ALTO | X85: BAJO | Y85: PRODUCCIÓN | Z85: NA | AA85: NA | AD85: SI | AE85: veritas | AF85: Veritas-FullFrid-Ret90_GYE_09 | AG85: -
J86: VIRTUAL | K86: TVC-SRV-FLUENTD | L86: Servidor para centralizar todos los logs que se generan desde los microservicios y otros aplicativos. Se va a trabajar con el aplicativo “Fluentd” como “data collector” para lo cual es necesario alojarlo en un servidor. | M86: 192.168.59.86 | O86: - | P86: SI | Q86: Hector Miranda | R86: SI | S86: RedHat Enterprise Linux 9,4 | T86: 8 | U86: 100 | V86: 4 | W86: ALTO | X86: ALTO | Y86: PRODUCCIÓN | Z86: NA | AA86: NA | AD86: SI | AE86: veritas | AF86: Veritas-FullThu-Ret90_GYE_04
J87: VIRTUAL | K87: TVC-SRV-FORTIMAGANERGYE | L87: Servidor de FortiManager | M87: 192.168.59.21 | O87: NO | P87: NO | Q87: Luis Conteron / Guillermo Jurado | R87: SI | S87: FortiManager-VM64 v7.4.3-build2487 240514 (GA) - OTR | T87: 16 | U87: 500 | V87: 4 | W87: ALTO | X87: ALTO | Y87: PRODUCCIÓN | AD87: SI | AE87: veritas | AF87: Veritas-FullThu-Ret90_GYE_04 | AG87: -
J88: VIRTUAL | K88: TVC-SRV-FRONTCERT | L88: Para el nuevo portal de Ingreso de Contratos mismo que va a ser desarrollado por el proveedor NextGen (Ambiente PRODUCCION) | M88: 192.168.59.26 | N88: 190.154.47.26 | O88: - | P88: SI REV | Q88: Hector Miranda/Administrador de aplicaciones | R88: SI | S88: Ubuntu 22.04 LTS | T88: 2 | U88: 50 | V88: 2 | W88: ALTO | X88: MEDIO | Y88: PRODUCCIÓN | Z88: NA | AA88: NA | AD88: SI | AE88: veritas | AF88: Veritas-FullMon-Ret90_GYE_13 | AG88: -
J89: VIRTUAL | K89: TVC-SRV-FRONTCERTPROD | L89: Para el nuevo portal de Ingreso de Contratos para producción, desarrollado por Ricardo Rivera. | M89: 192.168.59.80 | P89: SI | R89: SI | S89: Ubuntu 22.04 LTS | T89: 2 | U89: 30 | V89: 2 | W89: ALTO | X89: ALTO | Y89: PRODUCCIÓN | AF89: Veritas-FullThu-Ret90_GYE_15
J90: VIRTUAL | K90: TVC-SRV-FRONTEND | L90: Servidor frontend para el nuevo desarrollo del módulo de promociones que se integrara con Tytan. | M90: 192.168.59.87 | N90: 59.12 | O90: - | P90: SI | Q90: Mauricio Rodriguez/ | R90: SI | S90: Red Hat Enterprise Linux 9,4 | T90: 16 | U90: 200 | V90: 4 | W90: Bajo | X90: BAJO | Y90: PREPRODUCCIÓN | Z90: NA | AA90: NA | AD90: SI | AE90: Veeam Backup | AF90: Veritas-FullThu-Ret90_GYE_04 | AG90: -
J91: VIRTUAL | K91: TVC-SRV-FRONTTEST | L91: Para desarrollo de los sistemas de contratos web, portal unificado y otros aplicativos internos. | M91: 192.168.59.27 | O91: - | P91: SI | Q91: Mauricio Rodriguez/Administardor de aplicaciones | R91: SI | S91: Ubuntu 22.04 LTS | T91: 2 | U91: 30 | V91: 2 | X91: MEDIO | Y91: PREPRODUCCIÓN | AE91: veritas | AF91: Veritas-FullThu-Ret90_GYE_04
J92: VIRTUAL | K92: TVC-SRV-HAPROXY | L92: HA PROXY PRODUCCION de Middleware | M92: 192.168.59.200 | O92: - | P92: SI | Q92: Administrador de aplicaciones/Mauricio Rodriguez | R92: SI | S92: Ubuntu 22.04 LTS | T92: 16 | U92: 100 | V92: 8 | W92: ALTO | X92: ALTO | Y92: PRODUCCIÓN | Z92: NA | AA92: NA | AD92: SI | AE92: veritas | AF92: Veritas-FullThu-Ret90_GYE_15 | AG92: -
J93: VIRTUAL | K93: TVC-SRV-KIOSKOBACK | L93: SERVIDOR PARA KIOSKOS VIRTUALES - BACK | M93: 192.168.59.194 | N93: 190.154.47.194 | O93: - | P93: SI | Q93: Administrador de aplicaciones/Mauricio Rodriguez | R93: SI | S93: Ubuntu 22.04 LTS | T93: 4 | U93: 150 | V93: 2 | W93: ALTO | X93: ALTO | Y93: PRODUCCIÓN | Z93: NA | AA93: NA | AD93: SI | AE93: veritas | AF93: Veritas-FullThu-Ret90_GYE_15 | AG93: -
J94: VIRTUAL | K94: TVC-SRV-KIOSKOFRONT | L94: SERVIDOR PARA KIOSKOS VIRTUALES - FRONT | M94: 192.168.59.195 | N94: 190.154.47.195 | O94: - | P94: SI | Q94: Administrador de aplicaciones/Mauricio Rodriguez | R94: SI | S94: Ubuntu 22.04 LTS | T94: 4 | U94: 150 | V94: 2 | W94: ALTO | X94: ALTO | Y94: PRODUCCIÓN | Z94: NA | AA94: NA | AD94: SI | AE94: veritas | AF94: Veritas-FullFrid-Ret90_GYE_05 | AG94: -
J95: VIRTUAL | K95: TVC-SRV-KMS1 | L95: 59 | M95: 192.168.59.230 | O95: - | P95: SI | Q95: Mireya Iturralde | R95: SI | S95: Microsoft Windows Server 2022 | T95: 8 | U95: 100 | V95: 4 | X95: ALTO | Y95: PRODUCCIÓN | Z95: NA | AA95: NA | AD95: SI | AE95: veritas | AF95: Veritas-FullSun-Ret90_GYE_16 | AG95: -
J96: VIRTUAL | K96: TVC-SRV-LANDINGPAGEbak | L96: Directorio: backend /backend.xtrim.com.ec en DNS interno | M96: 192.168.59.90 | O96: - | P96: SI | Q96: Administrador de aplicaciones/Mauricio Rodriguez-David Villamar | R96: SI | S96: Ubuntu 22.04 LTS | T96: 4 | U96: 100 | V96: 4 | W96: ALTO | X96: ALTO | Y96: PRODUCCIÓN | AD96: SI | AE96: veritas | AF96: Veritas-Full-TueRet90_GYE_19
J97: VIRTUAL | K97: TVC-SRV-LANDINGPAGEpro | L97: dominio: pagos.xtrim.com.ec con seguridades mediante WAF /Directorio: pagos | M97: 192.168.59.89 | N97: 200.63.213.91 | O97: - | P97: SI | Q97: Administrador de aplicaciones/Mauricio Rodriguez-David Villamar | R97: SI | S97: Ubuntu 22.04 LTS | T97: 4 | U97: 100 | V97: 4 | W97: ALTO | X97: ALTO | Y97: PRODUCCIÓN | AD97: SI | AE97: veritas | AF97: Veritas-Full-TueRet90_GYE_19
J98: VIRTUAL | K98: TVC-SRV-MALWAREGYE | L98: Srv Malware que analizará los backup de Veritas. | M98: 192.168.59.20 | O98: - | P98: SI | Q98: Mireya Iturralde | R98: SI | S98: Red Hat Enterprise Linux 9.2 (64-bit) | T98: 32 | U98: 20-100 | V98: 8 | W98: ALTO | X98: MEDIO | Y98: PRODUCCIÓN | AE98: veritas | AF98: Veritas-FullFrid-Ret90_GYE_05
J99: VIRTUAL | K99: TVC-SRV-MEDIADORDACC | L99: Contiene el gestor de colas de Tv HFC, Ejecuta el envio de comandos de aprovisionamiento del servicio de Tv HFC con el DAC | M99: 192.168.59.116 | O99: - | P99: SI | Q99: Administrador de aplicaciones /Hector Miranda | R99: SI | S99: RedHat Enterprise Linux 8,6 | T99: 16 | U99: 120 | V99: 4 | W99: ALTO | X99: ALTO | Y99: PRODUCCIÓN | Z99: NA | AA99: NA | AD99: SI | AE99: veritas | AF99: Veritas-FullThu-Ret90_GYE_15 | AG99: -
J100: VIRTUAL | K100: TVC-SRV-MONPROD | L100: Servidor Monitoreo Produccion. 1. Base Datos Arcotel, contiene los registros de las acciones generadas por los incidentes reportados por Arcotel. 2. Aplicaciones de QlikView, 3. Power Automate y robot para regularizar ingreso de contratos | M100: 192.168.59.134 | O100: SI | P100: - | Q100: Graciela Ortiz / Carlos Ayala / Christian Castillo/Jose Fernandez | R100: SI | S100: Microsoft Windows Server 2016 | T100: 16 | U100: 500 | V100: 6 | W100: ALTO | X100: MEDIO | Y100: PRODUCCIÓN | Z100: SQL SERVER | AA100: SQL Server 2012 Standard Edition | AD100: SI | AE100: veritas | AF100: Veritas-FullFrid-Ret90_GYE_05 | AG100: 189
J101: VIRTUAL | K101: TVC-SRV-MOODLE | L101: Aulas Virtuales de Moodle, ofrece funciones como videoconferencias, pizarras, uso compartido de documentos y cuestionarios interactivos para mejorar la experiencia de aprendizaje de los alumnos. | M101: 192.168.59.3 | O101: - | P101: SI | R101: SI | S101: Ubuntu Ubuntu 22.04 LTS (64-bit) | T101: 4 | U101: 200 | V101: 2 | X101: MEDIO | Y101: PRODUCCIÓN | Z101: NA | AA101: NA | AD101: SI | AE101: veritas | AF101: Veritas-FullFrid-Ret90_GYE_07
J102: VIRTUAL | K102: TVC-SRV-NESSUS | L102: Escanea vulnerabilidades de servidores, servicios y aplicaciones. | M102: 192.168.59.59 | O102: - | P102: SI | Q102: Jose Fernandez | R102: SI | S102: Debian 12 - OTR | T102: 8 | U102: 150 | V102: 4 | W102: ALTO | X102: ALTO | Y102: PRODUCCIÓN | Z102: NA | AA102: NA | AE102: veritas | AF102: Veritas-FullFrid-Ret90_GYE_07
J103: VIRTUAL | K103: tvc-srv-njbdps2 | L103: Pruebas página de Xtrim En el servidor 21.189 se encuentran las siguientes aplicaciones 1. JBoss y CM de Desarrollo 2. Dps de desarrollo 3. JBoss y CM de AQTEST 4. Dps de desarrollo (QAtest) Adicionalmente funciona como repositorio ftp para transacciones de pruebas, como por ejemplo 1. SoftSwitch 2. Débitos automáticos 3. Cdr 4. Facturación electronica de prueba. | M103: 192.168.59.173 | O103: SI | P103: - | Q103: Hector Miranda /Administrador aplicaciones | R103: SI | S103: CentOS Linux release 7.9.2009 (Core) | T103: 8 | U103: =240+120 -> 360 | V103: 4 | X103: BAJO | Y103: PREPRODUCCIÓN | Z103: NA | AA103: NA | AD103: SI | AF103: Veritas-FullMon-Ret90_GYE_13
J104: VIRTUAL | K104: TVC-SRV-OOKLADAT | L104: Servidor de Ookla para analizar datos | M104: 192.168.59.39 | O104: SI | P104: - | Q104: Jorge Mendoza | R104: SI | S104: Microsoft Windows Server 2016 | T104: 16 | U104: 500 | V104: 4 | X104: MEDIO | Y104: PRODUCCIÓN | Z104: NA | AA104: NA | AD104: SI | AE104: veritas | AF104: Veritas-FullMon-Ret90_GYE_13 | AG104: -
...

Sheet GYE
A2: INVENTARIO DE SERVIDORES VIRTUALIZADOS Y FISICOS GYE 2024
A5: Fecha de actualización: 25Julio2024 | H5: Actualizado por: | I5: Mireya Iturralde
B6: ENCLOSURE | C6: SRV FISICOS | D6: SERIE | E6: IP del blade | F6: TOTAL SRV FISICOS | G6: CARACTERISTICAS | H6: SOPORTE | I6: # SRV VIRTUALES | J6: TIPO DE SERVIDOR | K6: SRV VIRTUALES | L6: APLICACIÓN | M6: IP INTERNA | N6: IP PUBLICA | O6: PROTECCIÓN DE TREND MCRO XDR - SRV | P6: CORTEX | Q6: Persona responsable del uso del SRV | R6: SISTEMA OPERATIVO | S6: MEMORIA | T6: Espacio Disco | U6: Procesador | V6: SISTEMAS CRITICOS | W6: NIVEL DE BACKUP | X6: SERVIDOR PRODUCCIÓN / PREPRODUCCIÓN | Y6: BASE DE DATOS | Z6: VERSIÓN DB | AA6: COSTO SOPORTE | AB6: EMPRESA QUE DA SOPORTE | AC6: BACKUP SE REALIZA | AD6: PLATAFORMA DE BACKUP | AE6: POLITICA DE BACKUP | AF6: COMENTARIO
A7: GYE | B7: HP C3000 | C7: BL460C | D7: - | E7: 192.168.0.121 | F7: 3 | G7: 2 X Gen7 64 GB RAM | H7: NO | X7: - | Y7: N/A | Z7: N/A
C8: BL460C | D8: - | E8: 192.168.0.122 | G8: 2 X Gen7 64 GB RAM | H8: NO
C9: BL460C | D9: - | E9: 192.168.0.123 | G9: 2 X Gen7 64 GB RAM | H9: NO
A10: GYE | B10: C7000-VDI | C10: BL460C | D10: CZ3741XKMH | E10: 140.27.120.50 | F10: 2 | G10: 2X Gen9, Intel(R) Xeon(R) CPU E5-2620 v4 @ 2.10GHz, 2 slot de c/u 128GB en total 256 GB RAM | H10: TERMINA 2023 | I10: =COUNTIF(J10:J23,"=VIRTUAL") -> 14 | J10: VIRTUAL | K10: TVC-SRV-CCLOUD1 | L10: Servidor Cloud Clonnect de Citrix Principal | M10: 192.168.59.226 | O10: - | P10: SI | Q10: Yurema Tobar / Mireya Iturralde | R10: Microsoft Windows Server 2022 | S10: 4 | T10: 100 | U10: 4 | W10: ALTO | X10: PRODUCCIÓN | Y10: NA | Z10: NA | AC10: SI | AD10: veritas | AE10: Veritas-FullSun-Ret90_GYE_16 | AF10: -
C11: BL460C | D11: CZ3741XKN1 | E11: 140.27.120.49 | G11: 2X Gen9, Intel(R) Xeon(R) CPU E5-2620 v4 @ 2.10GHz, 2 slot de c/u de 128 GB en total 256 GB RAM | H11: TERMINA 2023 | J11: VIRTUAL | K11: TVC-SRV-CCLOUD2 | L11: Servidor Cloud Clonnect de Citrix Secundario | M11: 192.168.59.225 | O11: - | P11: SI | Q11: Yurema Tobar / Mireya Iturralde | R11: Microsoft Windows Server 2022 | S11: 4 | T11: 100 | U11: 4 | W11: BAJO | X11: PRODUCCIÓN | Y11: NA | Z11: NA | AC11: SI | AD11: veritas | AE11: Veritas-FullSun-Ret90_GYE_16 | AF11: No se ejecuta porque, es un srv replicado del cloud1
J12: VIRTUAL | K12: TVC-SRV-CTXIM0 | L12: Imagen maestra para servidores web y win de citrix | M12: 192.168.59.221 | O12: - | P12: SI | Q12: Yurema Tobar / Mireya Iturralde | R12: Microsoft Windows Server 2022 | S12: 8 | T12: 230 | U12: 4 | W12: ALTO | X12: PRODUCCIÓN | Y12: NA | Z12: NA | AC12: SI | AD12: veritas | AE12: Veritas-FullSun-Ret90_GYE_16 | AF12: -
J13: VIRTUAL | K13: TVC-SRV-CTXWB01 | L13: Servidor web para citrix cloud. | M13: 192.168.17.11 | O13: - | P13: SI | Q13: Yurema Tobar / Mireya Iturralde | R13: Microsoft Windows Server 2022 | S13: 32 | T13: 230 | U13: 4 | W13: MEDIO | X13: PRODUCCIÓN | Y13: NA | Z13: NA | AC13: NO | AF13: SERVIDOR ES UN CLON DE LA IMAGEN MAESTRA
J14: VIRTUAL | K14: TVC-SRV-CTXWN01 | L14: Servidor de aplicaciones windows para citrix cloud. | M14: 192.168.17.16 | O14: - | P14: SI | Q14: Yurema Tobar / Mireya Iturralde | R14: Microsoft Windows Server 2022 | S14: 32 | T14: 230 | U14: 4 | W14: MEDIO | X14: PRODUCCIÓN | Y14: NA | Z14: NA | AC14: NO | AF14: SERVIDOR ES UN CLON DE LA IMAGEN MAESTRA
J15: VIRTUAL | K15: TVC-SRV-CTXWN02 | L15: Servidor de aplicaciones windows para citrix cloud. | M15: 192.168.17.12 | O15: - | P15: SI | Q15: Yurema Tobar / Mireya Iturralde | R15: Microsoft Windows Server 2022 | S15: 32 | T15: 230 | U15: 4 | W15: MEDIO | X15: PRODUCCIÓN | Y15: NA | Z15: NA | AC15: NO | AF15: SERVIDOR ES UN CLON DE LA IMAGEN MAESTRA
J16: VIRTUAL | K16: TVC-SRV-CTXWN03 | L16: Servidor de aplicaciones windows para citrix cloud. | M16: 192.168.17.13 | O16: - | P16: SI | Q16: Yurema Tobar / Mireya Iturralde | R16: Microsoft Windows Server 2022 | S16: 32 | T16: 230 | U16: 4 | W16: MEDIO | X16: PRODUCCIÓN | Y16: NA | Z16: NA | AC16: NO | AF16: SERVIDOR ES UN CLON DE LA IMAGEN MAESTRA
J17: VIRTUAL | K17: TVC-SRV-CTXWN04 | L17: Servidor de aplicaciones windows para citrix cloud. | M17: 192.168.17.14 | O17: - | P17: SI | Q17: Yurema Tobar / Mireya Iturralde | R17: Microsoft Windows Server 2022 | S17: 32 | T17: 230 | U17: 4 | W17: MEDIO | X17: PRODUCCIÓN | Y17: NA | Z17: NA | AC17: NO | AF17: SERVIDOR ES UN CLON DE LA IMAGEN MAESTRA
J18: VIRTUAL | K18: TVC-SRV-CTXWN06 | L18: Servidor de aplicaciones windows para citrix cloud. | M18: 192.168.17.10 | O18: - | P18: SI | Q18: Yurema Tobar / Mireya Iturralde | R18: Microsoft Windows Server 2022 | S18: 32 | T18: 230 | U18: 4 | W18: MEDIO | X18: PRODUCCIÓN | Y18: NA | Z18: NA | AC18: NO | AF18: SERVIDOR ES UN CLON DE LA IMAGEN MAESTRA
J19: VIRTUAL | K19: TVC-SRV-KMS1 | L19: Servidor de licencias RDS para Citrix. | M19: 192.168.59.230 | O19: - | P19: SI | Q19: Yurema Tobar / Mireya Iturralde | R19: Microsoft Windows Server 2022 | S19: 8 | T19: 100 | U19: 4 | W19: ALTO | X19: PRODUCCIÓN | Y19: NA | Z19: NA | AC19: SI | AD19: veritas | AE19: Veritas-FullSun-Ret90_GYE_16 | AF19: -
J20: VIRTUAL | K20: TVC-SRV-PROFILE | L20: Servidor de Perfiles Ambiente Citrix Cloud | M20: 192.168.17.5 | O20: - | P20: SI | Q20: Yurema Tobar / Mireya Iturralde | R20: Microsoft Windows Server 2022 | S20: 16 | T20: 600 | U20: 4 | W20: ALTO | X20: PRODUCCIÓN | Y20: NA | Z20: NA | AC20: SI | AD20: veritas | AE20: Veritas-FullSun-Ret90_GYE_16 | AF20: -
J21: VIRTUAL | K21: TVC-SRV-SFRONT1 | L21: Servidor de StoreFront Citrix Primary | M21: 192.168.59.227 | O21: - | P21: SI | Q21: Yurema Tobar / Mireya Iturralde | R21: Microsoft Windows Server 2022 | S21: 8 | T21: 100 | U21: 4 | W21: ALTO | X21: PRODUCCIÓN | Y21: NA | Z21: NA | AC21: SI | AD21: veritas | AE21: Veritas-FullSun-Ret90_GYE_16 | AF21: -
J22: VIRTUAL | K22: TVC-SRV-SFRONT2 | L22: Servidor de StoreFront Citrix Secundario | M22: 192.168.59.228 | O22: - | P22: SI | Q22: Yurema Tobar / Mireya Iturralde | R22: Microsoft Windows Server 2022 | S22: 8 | T22: 100 | U22: 4 | W22: BAJO | X22: PRODUCCIÓN | Y22: NA | Z22: NA | AC22: NO | AF22: No se ejecuta porque, es un srv replicado del storefront2
J23: VIRTUAL | K23: TVC-SRVG-CTXFS2 | L23: Servidor data usuarios | M23: 192.168.59.233 | O23: SI | P23: - | Q23: Yurema Tobar | R23: 90 | S23: 8 | T23: 1024 | U23: 6 | W23: ALTO | X23: PRODUCCIÓN | Y23: NA | Z23: NA | AC23: SI | AD23: veritas | AE23: Veritas-FullSun-Ret90_GYE_16
A24: GYE | B24: C7000-TI | C24: BL460C | D24: CZ3741XKMM | E24: 140.27.120.51 | F24: 1 | G24: 2X Gen9, Intel(R) Xeon(R) CPU E5-2620 v4 @ 2.10GHz, 2 slot de c/u 128GB en total 256 GB RAM | H24: TERMINA 2023 | I24: =COUNTIF(J24:J39,"=VIRTUAL") -> 16 | J24: VIRTUAL | K24: vREALIZE LCM APPLIANCE | L24: Se creo por default una vez instalado el vmware. | M24: 140.27.120.210 | O24: - | P24: - | Q24: Yurema Tobar / Guillermo Jurado | R24: Linux OTRO | S24: 6 | T24: 78 | U24: 4 | W24: DAR DE BAJA | X24: PRODUCCIÓN | Y24: NA | Z24: NA | AC24: SI | AD24: veritas | AF24: -
C25: BL460C | D25: CZ3741XKMF | E25: 140.27.120.52 | F25: 1 | G25: 2X Gen9, Intel(R) Xeon(R) CPU E5-2620 v4 @ 2.10GHz, 2 slot de c/u 128GB en total 256 GB RAM | H25: TERMINA 2023 | J25: VIRTUAL | K25: PC-REMOTE | L25: Equipo para escritorio remoto para Xavier León | M25: 192.168.17.6 | O25: - | P25: SI | Q25: Xavier León | R25: Windows 11 PRO | S25: 8 | T25: 200 | U25: 2 | W25: BAJO | X25: PREPRODUCCIÓN | AC25: no
C26: BL460C | D26: CZ3741XKN5 | E26: 140.27.120.53 | F26: 1 | G26: 2X Gen9, Intel(R) Xeon(R) CPU E5-2620 v4 @ 2.10GHz, 2 slot de c/u 128GB en total 256 GB RAM | H26: TERMINA 2023 | J26: VIRTUAL | K26: TVC-SRV-DOCKQA | L26: SERVIDOR DE DOCKERS DE DESARROLLO, PARA EL AMBIENTE DE CONTROL DE CALIDAD. clonado del 59.189 | M26: 192.168.59.140 | O26: - | P26: SI | Q26: Mauricio Rodriguez | R26: Ubuntu 20.04 LTS | S26: 32 | T26: 220 | U26: 4 | W26: BAJO | X26: PREPRODUCCIÓN | Y26: NA | Z26: NA | AD26: veeam
J27: VIRTUAL | K27: TVC-SRV-DWTEST | L27: Prueba de DatawareHouse | M27: 192.168.59.125 | O27: - | P27: SI | Q27: Carlos Ayala / Hector Miranda | R27: Ubuntu 22.04 | S27: 4 | T27: 120 | U27: 2 | W27: MEDIO | X27: PREPRODUCCIÓN | Y27: NA | Z27: NA | AC27: SI | AF27: -
J28: VIRTUAL | K28: TVC-SRV-FRONQA | L28: SERVIDOR FRONT END, PARA EL AMBIENTE DE CONTROL DE CALIDAD. | M28: 192.168.59.142 | O28: - | P28: SI | Q28: Mauricio Rodriguez | R28: Ubuntu 22.04 LTS | S28: 2 | T28: 30 | U28: 2 | W28: BAJO | X28: PREPRODUCCIÓN | Y28: NA | Z28: NA | AC28: SI | AD28: veeam | AF28: -
J29: VIRTUAL | K29: TVC-SRV-HAPROXYQA | L29: SERVIDOR DE HAPROXY, PARA EL AMBIENTE DE CONTROL DE CALIDAD. clonado 59.200 | M29: 192.168.59.141 | O29: - | P29: SI | Q29: Mauricio Rodriguez | R29: Ubuntu 22.04 LTS | S29: 8 | T29: 80 | U29: 4 | W29: BAJO | X29: PREPRODUCCIÓN | AC29: SI | AD29: veeam | AF29: -
J30: VIRTUAL | K30: TVC-SRV-HKTEST | L30: Servidor HIperK pruebas | M30: 140.27.120.109 | O30: SI | P30: - | Q30: Carlos Ayala | R30: Red Hat Enterprise Linux 6,9 | S30: 20 | T30: 350 | U30: 4 | W30: BAJO | X30: PREPRODUCCIÓN | Y30: NA | Z30: NA | AC30: SI | AF30: -
J31: VIRTUAL | K31: TVC-SRV-PREDBAPI | L31: Base de datos del Middleware Mysql Preproducción API. (Se confirma con Mauricio) | M31: 192.168.59.199 | O31: - | P31: SI | Q31: Carlos Ayala / Christian Castillo | R31: Ubuntu 22.04 LTS | S31: 8 | T31: 100 | U31: 4 | V31: BAJO | W31: MEDIO | X31: PREPRODUCCIÓN | Y31: MYSQL | Z31: MySQL 8 community edition | AC31: SI | AD31: veritas | AE31: Veritas-Fulltue-Ret90_GYE_01 | AF31: -
J32: VIRTUAL | K32: TVC-SRV-PREHAPROXY | L32: HA PROXY Y BASE DE DATOS. AMBIENTE DE PRE-PRODUCCION de Middleware (Se confirma con Mauricio) | M32: 192.168.59.201 | O32: - | P32: SI | Q32: Administrador de aplicaciones / Mauricio Rodriguez / Carlos Ayala / Christian Castillo | R32: Ubuntu 22.04 LTS | S32: 8 | T32: 80 | U32: 4 | V32: BAJO | W32: MEDIO | X32: PREPRODUCCIÓN | Y32: MYSQL | Z32: MySQL 8 community edition | AC32: SI | AD32: veritas | AE32: Veritas-Fulltue-Ret90_GYE_01 | AF32: -
J33: VIRTUAL | K33: TVC-SRV-PREWSO2API1 | L33: Servidor WSO2 Api Manager para el Middleware (Se confirma con Mauricio) | M33: 192.168.59.186 | O33: - | P33: SI | Q33: Administrador de aplicaciones / Mauricio Rodriguez | R33: Ubuntu 20.04 LTS | S33: 16 | T33: 75 | U33: 4 | V33: BAJO | W33: ALTO | X33: PREPRODUCCIÓN | Y33: NA | Z33: NA | AC33: SI | AD33: veritas | AE33: Veritas-Fulltue-Ret90_GYE_01 | AF33: -
J34: VIRTUAL | K34: TVC-SRV-PREWSO2IDEN | L34: Servidor WSO2 Identity para el Middleware (Se confirma con Mauricio) | M34: 192.168.59.187 | O34: - | P34: SI | Q34: Administrador de aplicaciones / Mauricio Rodriguez | R34: Ubuntu 20.04 LTS | S34: 16 | T34: 75 | U34: 4 | V34: BAJO | W34: ALTO | X34: PREPRODUCCIÓN | Y34: NA | Z34: NA | AC34: SI | AD34: veritas | AE34: Veritas-Fulltue-Ret90_GYE_01 | AF34: -
J35: VIRTUAL | K35: TVC-SRV-PREWSO2DB | L35: BD REDIS y para el Middleware (Se confirma con Mauricio) | M35: 192.168.59.188 | O35: - | P35: SI | Q35: Carlos Ayala / Christian Castillo | R35: Ubuntu 20.04 LTS | S35: 16 | T35: 90 | U35: 4 | V35: BAJO | W35: ALTO | X35: PREPRODUCCIÓN | Y35: NA | Z35: NA | AC35: SI | AD35: veritas | AE35: Veritas-Fulltue-Ret90_GYE_01 | AF35: -
J36: VIRTUAL | K36: TVC-SRV-PREWSO2NOD1 | L36: Servidor WSO2 Nodos microservicios para el Middleware - Preproducción (Se confirma con Mauricio) | M36: 192.168.59.189 | N36: 190.154.47.189 | O36: - | P36: SI | Q36: Administrador de aplicaciones / Mauricio Rodriguez | R36: Ubuntu 20.04 LTS | S36: 32 | T36: 220 | U36: 4 | V36: BAJO | W36: ALTO | X36: PREPRODUCCIÓN | Y36: NA | Z36: NA | AC36: SI | AD36: veritas | AE36: Veritas-FullThu-Ret90_GYE_15 | AF36: -
J37: VIRTUAL | K37: TVC-SRV-SSTEST | L37: Servidor SoftSwitch preproducción, y pruebas de conexiones a las entidades bancarias. | M37: 192.168.59.231 | N37: 190.154.47.232 | O37: - | P37: SI | Q37: Administrador de aplicaciones / Hector Miranda | R37: Microsoft Windows Server 2022 | S37: 16 | T37: 120 | U37: 4 | V37: BAJO | W37: BAJO | X37: PREPRODUCCIÓN | Y37: NA | Z37: NA | AC37: SI | AE37: Veritas-FullMon-SSTEST | AF37: -
J38: VIRTUAL | K38: TVC-SRV-WSO2DBQA | L38: BD REDIS para el Middleware y MongoDB Zapping, PARA AMBIENTE DE CONTROL DE CALIDAD. | M38: 192.168.59.143 | O38: - | P38: SI | Q38: Mauricio Rodriguez | R38: Ubuntu 20.04 LTS | S38: 32 | T38: 180 | U38: 8 | W38: BAJO | X38: PRODUCCIÓN | Y38: NA | Z38: NA | AC38: SI | AD38: veritas | AF38: -
C39: NO MOVER | J39: VIRTUAL | K39: TVC-SRV-ARBITER | L39: Servidor Arbitrario para el simplivity, permite la comunicación con los nodos GYE. Se puede reiniciar el servidor pero siempre debe estar arriba, porque si existe un problema con los nodos del Simplivity, luego no habria quien gestione quien es el nodo master. | M39: 192.168.59.54 | O39: - | P39: SI | Q39: Yurema Tobar/Mireya Iturralde | R39: Windows Server 2019 | S39: 4 | T39: 50 | U39: 2 | W39: ALTO | X39: PRODUCCIÓN | Y39: NA | Z39: NA | AC39: SI | AD39: veritas | AE39: Veritas-FullThu-Ret90_GYE_17 | AF39: -
B41: C7000-TEC | C41: BL460C | D41: CZ3741XKMS | E41: 192.168.94.41 | F41: 1 | G41: 2X Gen9, Intel(R) Xeon(R) CPU E5-2620 v4 @ 2.10GHz, 2 slot de c/u de 128GB en total 256 GB RAM | H41: TERMINA 2023 | I41: =COUNTIF(J41:J50,"=VIRTUAL") -> 10 | J41: VIRTUAL | K41: CoreViewGYE | L41: Funcionalidad: Gestion de plataforma ARRIS | M41: 192.168.87.60 | O41: - | P41: SI | Q41: Jose Lopez / William Chenche | R41: Microsoft Windows Server 2022 | S41: 16 | T41: 120 | U41: 4 | W41: ALTO | X41: PRODUCCIÓN | AD41: veeam
C42: BL460C | D42: CZ3741XKMY | E42: 192.168.94.42 | F42: 1 | G42: 2X Gen9, Intel(R) Xeon(R) CPU E5-2620 v4 @ 2.10GHz, 2 slot de c/u de 128GB en total 256 GB RAM | H42: TERMINA 2023 | J42: VIRTUAL | K42: DhcpGponGYE | L42: Funcionalidad: Servidor DHCP, para la plataforma GPON en R2 & R3. | M42: 192.168.1.200 | O42: - | P42: SI | Q42: Christian Francis | R42: Ubuntu 22.04 LTS | S42: 16 | T42: 170 | U42: 4 | W42: ALTO | X42: PRODUCCIÓN | AD42: veeam
C43: BL460C | D43: CZ3741XKMD | E43: 192.168.94.43 | F43: 1 | G43: 2X Gen9, Intel(R) Xeon(R) CPU E5-2620 v4 @ 2.10GHz, 2 slot de c/u de 128GB en total 256 GB RAM | H43: TERMINA 2023 | J43: VIRTUAL | K43: dnscorp2.satnet.net | L43: Funcionalidad: Servidor DNS decundario, clientes corporativos | M43: 192.168.1.72 | O43: - | P43: SI | Q43: Christian Francis | R43: Ubuntu 22.04 LTS | S43: 24 | T43: 120 | U43: 24 | W43: ALTO | X43: PRODUCCIÓN | Y43: NA | Z43: NA | AD43: veeam
J44: VIRTUAL | K44: dnsgpon2 | L44: Funcionalidad: Servidor DNS recursivo, clientes residenciales HFC, GPON | M44: 192.168.1.70 | O44: - | P44: SI | Q44: Christian Francis | R44: Ubuntu 22.04 LTS | S44: 24 | T44: 120 | U44: 24 | W44: ALTO | X44: PRODUCCIÓN | Y44: NA | Z44: NA | AD44: veeam
J45: VIRTUAL | K45: dnsgpon4 | L45: Funcionalidad: Servidor DNS recursivo, clientes residenciales HFC, GPON | M45: 192.168.1.74 | O45: - | P45: SI | Q45: Christian Francis | R45: Ubuntu 22.04 LTS | S45: 24 | T45: 120 | U45: 24 | W45: ALTO | X45: PRODUCCIÓN | Y45: NA | Z45: NA | AD45: veeam
J46: VIRTUAL | K46: dnssipgye.satnet.net | L46: Servidor de prueba para tecnología | M46: 192.168.1.75 | O46: - | P46: SI | Q46: Christian Francis | R46: Ubuntu 22.04 LTS | S46: 8 | T46: 150 | U46: 4 | W46: ALTO | X46: PRODUCCIÓN | Y46: NA | Z46: NA | AD46: veeam
J47: VIRTUAL | K47: ISPmonitorGYE | L47: Funcionalidad:Servidor de monitoreo de la red clientes. | M47: 192.168.1.34 | O47: - | P47: SI | Q47: Cesar Moreno | R47: Microsoft Windows Server 2022 | S47: 24 | T47: 500 | U47: 8 | W47: ALTO | X47: PRODUCCIÓN | AD47: veeam
J48: VIRTUAL | K48: ORION2 | L48: Funcionalidad: Gestor de monitoreo Descripción: Realiza el monitoreo de equipos de la red de XTRIM mediante snmp e icmp. | M48: 192.168.87.6 | O48: - | P48: SI | Q48: Mireya Anaguano / Cesar Moreno | R48: Microsoft Windows Server 2019 (64-bit) | S48: 32 | T48: 120 | U48: 12 | W48: ALTO | X48: PRODUCCIÓN | AC48: NO | AD48: veeam | AF48: -
J49: VIRTUAL | K49: SocGYE | L49: Servidor del soc para colectar los logs de TEC | M49: 192.168.1.20 | O49: - | P49: SI | Q49: Christian Francis | R49: Ubuntu 22.04 LTS | S49: 12 | T49: 250 | U49: 8 | W49: MEDIO | X49: PRODUCCIÓN
J50: VIRTUAL | K50: TVC-VCENTERCLOUD | L50: vcenter para el nuevo tipo de licenciamiento por suscripción de VMWare. | M50: 192.168.59.17 | O50: - | P50: - | Q50: Yurema Tobar / Mireya Iturralde | R50: VMware Photon OS - OTR | S50: 21 | T50: 49 | U50: 4 | W50: ALTO | X50: PRODUCCIÓN | Y50: NA | Z50: NA | AC50: SI | AD50: veritas | AE50: Veritas-FullThu-Ret90_GYE_17 | AF50: -
B52: HP C7000 | C52: BL460C | D52: 2M293800B9 | E52: 192.168.59.12 | F52: 1 | G52: 2X Gen10, Intel(R) Xeon(R) Gold 5120 CPU @ 2.20GHz, 2 slot de memoria : de 128GB y 256GB, en total 384 GB RAM | H52: TERMINA 2023 | I52: - | J52: FISICO | K52: TVC-SRV-DBFLASH | L52: BASE DE DATOS STAND BY DE FSM POR FLASH COPY | M52: 192.168.59.12 | O52: SI | P52: - | Q52: Carlos Ayala / Hector Miranda | R52: Oracle Linux 7.6 | S52: 384 | T52: 9728 | U52: 16 | W52: MEDIO | X52: PRODUCCIÓN | Y52: ORACLE | Z52: Oracle 11g R2 | AC52: NO | AF52: Por tema de espacio no tenemos donde almacenar 9TB, y no hay espacio para instalar un plugin de veeam y respaldar el srv oracle.
F53: - | I53: - | J53: FISICO | K53: .200 | L53: BASE DE DATOS DEL FSM | M53: 192.168.59.10 | O53: SI | P53: - | Q53: Carlos Ayala / Hector Miranda | R53: RedHat Enterprise Linux 6.8 | S53: 264 | T53: 2560 | U53: 16 | W53: MEDIO | X53: PRODUCCIÓN | Y53: ORACLE | Z53: Oracle 11g R2 | AC53: NO | AF53: Por tema de espacio
A55: GYE | B55: tvc-nodo1gye | C55: ProLiant DL380 2 x Intel(R) Xeon(R) Gold 6238 CPU @ 2.10GHz x 22 Cores | D55: 2M232601ZM | E55: 192.168.9.28 | F55: 4 | G55: Gen 10, 1 TB RAM Y 25TB | H55: SI | J55: VIRTUAL | K55: ise-xtrim-APcisco | L55: Servidor de Access Point de Cisco, e sun OVA. | M55: 192.168.59.30 | O55: - | P55: - | Q55: Diana Loor | R55: Red Hat Enterprise Linux 7 | S55: 16 | T55: 600 | U55: 8 | W55: ALTO | X55: PRODUCCIÓN | Y55: NA | Z55: NA | AC55: SI | AD55: veritas | AE55: Veritas-FullMon-Ret90_GYE_13 | AF55: -
A56: GYE | B56: tvc-nodo2gye | D56: 2M232601ZJ | E56: 192.168.9.30 | G56: Gen 10, 1 TB RAM Y 25TB | H56: SI | I56: =COUNTIF(J56:J153,"=VIRTUAL") -> 96 | J56: VIRTUAL | K56: FORTIANALYZER-VM64 | L56: Servidor Forticlient | M56: 192.168.59.41 | O56: - | P56: - | Q56: Diana Loor | R56: FortiAnalyzer-VM64 - OTRO | S56: 16 | T56: 1024 | U56: 8 | W56: ALTO | X56: PRODUCCIÓN | Y56: NA | Z56: NA | AC56: SI | AD56: veritas | AE56: Veritas-FullThu-Ret90_GYE_15 | AF56: -
A57: GYE | B57: tvc-nodo3gye | D57: 2M232601ZK | E57: 192.168.9.32 | G57: Gen 10, 1 TB RAM Y 25TB | H57: SI | J57: VIRTUAL | K57: OmniStackVC-192-168-9-29 | L57: OMNISTACK DEL NODO 1 DEL SIMPLIVITY | M57: 192.168.9.29 | O57: - | P57: - | Q57: Yurema Tobar / Mireya Iturralde | R57: Ubuntu Linux (64-bit) | S57: 92 | T57: 210 | U57: 8 | W57: ALTO | X57: PRODUCCIÓN | Y57: NA | Z57: NA | AC57: SI | AF57: es propio del Simplivity
A58: GYE | B58: tvc-nodo4gye | D58: 2M232601ZL | E58: 192.168.9.34 | G58: Gen 10, 1 TB RAM Y 25TB | H58: SI | J58: VIRTUAL | K58: OmniStackVC-192-168-9-31 | L58: OMNISTACK DEL NODO 2 DEL SIMPLIVITY | M58: 192.168.9.31 | O58: - | P58: - | Q58: Yurema Tobar / Mireya Iturralde | R58: Ubuntu Linux (64-bit) | S58: 92 | T58: 210 | U58: 8 | W58: ALTO | X58: PRODUCCIÓN | Y58: NA | Z58: NA | AC58: SI | AF58: es propio del Simplivity
J59: VIRTUAL | K59: OmniStackVC-192-168-9-33 | L59: OMNISTACK DEL NODO 3 DEL SIMPLIVITY | M59: 192.168.9.33 | O59: - | P59: - | Q59: Yurema Tobar / Mireya Iturralde | R59: Ubuntu Linux (64-bit) | S59: 92 | T59: 210 | U59: 8 | W59: ALTO | X59: PRODUCCIÓN | Y59: NA | Z59: NA | AC59: SI | AF59: es propio del Simplivity
J60: VIRTUAL | K60: OmniStackVC-192-168-9-35 | L60: OMNISTACK DEL NODO DEL SIMPLIVITY | M60: 192.168.9.35 | O60: - | P60: - | Q60: Yurema Tobar / Mireya Iturralde | R60: Ubuntu Linux (64-bit) | S60: 92 | T60: 210 | U60: 8 | W60: ALTO | X60: PRODUCCIÓN | Y60: NA | Z60: NA | AC60: SI | AF60: es propio del Simplivity
J61: VIRTUAL | K61: tvc-bss-cm-01 | L61: Alepo - Collection Manager, API GW/ con IP flotante 192.168.59.75 wso2.xtrim-app.com | M61: 192.168.59.63 | O61: - | P61: SI | Q61: ALEPO | R61: Oracle Linux 8 (64-bit) | S61: 28 | T61: 500 | U61: 16 | W61: ALTO | X61: APAGADO | Y61: NA | Z61: NA | AB61: SI | AC61: SI | AD61: veritas | AE61: Veritas-FullMon-Ret90_GYE_10 | AF61: -
J62: VIRTUAL | K62: tvc-bss-cm-02 | L62: Alepo - Collection Manager, API GW | M62: 192.168.59.81 | O62: - | P62: SI | Q62: ALEPO | R62: Oracle Linux 8 (64-bit) | S62: 28 | T62: 500 | U62: 16 | W62: ALTO | X62: APAGADO | Y62: NA | Z62: NA | AB62: SI | AC62: SI | AD62: veritas | AE62: Veritas-FullMon-Ret90_GYE_10 | AF62: -
J63: VIRTUAL | K63: tvc-bss-crm-01 | L63: Alepo- CRM + Billing + Product catalogue + Inventory + Trouble Ticketing + Affiliate Management + Off line rating /Con IP flotante 192.168.59.72 tiene alojada la pag reportes.xtrim-app.com | M63: 192.168.59.60 | O63: - | P63: SI | Q63: ALEPO | R63: Oracle Linux 8 (64-bit) | S63: 48 | T63: 800 | U63: 48 | W63: ALTO | X63: APAGADO | Y63: NA | Z63: NA | AB63: SI | AC63: SI | AD63: veritas | AE63: Veritas-FullMon-Ret90_GYE_10 | AF63: -
J64: VIRTUAL | K64: tvc-bss-db-01 | L64: Alepo - BSS Database - ambiente de producción | M64: 192.168.59.67 | O64: - | P64: SI | Q64: Alepo | R64: Oracle Linux 8 (64-bit) | S64: 48 | T64: 3000 | U64: 32 | W64: ALTO | X64: APAGADO | Y64: MARIADB | Z64: 10.7.4 | AB64: SI | AC64: SI | AD64: veritas | AE64: Veritas-FullMon-Ret90_GYE_10 | AF64: -
J65: VIRTUAL | K65: tvc-bss-db-02_recovery | L65: Alepo - BSS Database - ambiente de producción | M65: 192.168.59.80 | O65: - | P65: SI | Q65: ALEPO | R65: Oracle Linux 8 (64-bit) | S65: 48 | T65: 3000 | U65: 32 | W65: ALTO | X65: APAGADO | Y65: MARIADB | Z65: 10.7.4 | AD65: veritas | AE65: Veritas-FullMon-Ret90_GYE_10
J66: VIRTUAL | K66: tvc-bss-ffm-01 | L66: Alepo - FFM/ Con IP flotante 192.168.59.73 se tiene alojada la pag keycloak.xtrim-app.com | M66: 192.168.59.61 | O66: - | P66: SI | Q66: Alepo | R66: Oracle Linux 8 (64-bit) | S66: 32 | T66: 500 | U66: 8 | W66: ALTO | X66: APAGADO | Y66: NA | Z66: NA | AB66: SI | AC66: SI | AD66: veritas | AE66: Veritas-FullMon-Ret90_GYE_10 | AF66: -
J67: VIRTUAL | K67: tvc-bss-inter-01 | L67: Alepo - Interconnect | M67: 192.168.59.65 | O67: - | P67: SI | Q67: ALEPO | R67: Oracle Linux 8 (64-bit) | S67: 48 | T67: 3510 | U67: 32 | W67: ALTO | X67: APAGADO | Y67: NA | Z67: NA | AB67: SI | AC67: SI | AD67: veritas | AE67: Veritas-FullMon-Ret90_GYE_10 | AF67: -
J68: VIRTUAL | K68: tvc-bss-mediation-01 | L68: Alepo - Mediation | M68: 192.168.59.64 | O68: - | P68: SI | Q68: Alepo | R68: Oracle Linux 8 (64-bit) | S68: 32 | T68: 600 | U68: 16 | W68: ALTO | X68: APAGADO | Y68: NA | Z68: NA | AB68: SI | AC68: SI | AD68: veritas | AE68: Veritas-FullWed-Ret90_GYE_11 | AF68: -
J69: VIRTUAL | K69: tvc-bss-mon | L69: Alepo - Monitoring Tool | M69: 192.168.59.68 | O69: - | P69: SI | Q69: ALEPO | R69: Oracle Linux 8 (64-bit) | S69: 16 | T69: 400 | U69: 8 | W69: ALTO | X69: APAGADO | Y69: NA | Z69: NA | AB69: SI | AC69: SI | AD69: veritas | AE69: Veritas-FullWed-Ret90_GYE_11 | AF69: -
J70: VIRTUAL | K70: tvc-bss-olap-serv | L70: Alepo - Reporting Tool (OLAP) Se tiene alojada la pagina reportes.xtrim-app.com | M70: 192.168.59.70 | O70: - | P70: SI | Q70: ALEPO | R70: Microsoft Windows Server 2019 (64-bit) | S70: 64 | T70: 600 | U70: 20 | W70: ALTO | X70: APAGADO | Y70: NA | Z70: NA | AB70: SI | AC70: SI | AD70: veritas | AE70: Veritas-FullWed-Ret90_GYE_11 | AF70: -
J71: VIRTUAL | K71: tvc-bss-oms-01 | L71: Alepo - Order Management /Con IP flotante 192.168.59.78 se tiene alojada la pag oms.xtrim-app.com | M71: 192.168.59.66 | O71: - | P71: SI | Q71: ALEPO | R71: Oracle Linux 8 (64-bit) | S71: 32 | T71: 300 | U71: 16 | W71: ALTO | X71: APAGADO | Y71: NA | Z71: NA | AB71: SI | AC71: SI | AD71: veritas | AE71: Veritas-FullWed-Ret90_GYE_11 | AF71: -
J72: VIRTUAL | K72: tvc-bss-reporter-db | L72: Alepo - BSS Databases - ambiente de producción - y reporteria. Reporting DB (OLTP) + (Customer Data for 6 Years) excluding CDR Storage | M72: 192.168.59.71 | O72: - | P72: SI | Q72: Alepo | R72: Oracle Linux 8 (64-bit) | S72: 48 | T72: 5000 | U72: 16 | W72: ALTO | X72: APAGADO | Y72: MARIADB | Z72: 10.7.4 | AB72: SI | AC72: SI | AD72: veritas | AE72: Veritas-FullWed-Ret90_GYE_11 | AF72: -
J73: VIRTUAL | K73: tvc-bss-stg | L73: Alepo - Staging – preproducción (Este está dedicado a un entorno de prueba) | M73: 192.168.59.69 | N73: 190.154.47.69 | O73: - | P73: SI | Q73: Alepo | R73: Oracle Linux 8 (64-bit) | S73: 16 | T73: 550 | U73: 8 | W73: ALTO | X73: APAGADO | Y73: MARIADB | Z73: 10.7.4 | AB73: SI | AC73: SI | AD73: veritas | AE73: Veritas-FullWed-Ret90_GYE_11 | AF73: -
J74: VIRTUAL | K74: tvc-bss-wsrc-01 | L74: Alepo - Web Self Care + Chatbot + Whatsapp | M74: 192.168.59.62 | O74: - | P74: SI | Q74: Alepo | R74: Oracle Linux 8 (64-bit) | S74: 28 | T74: 500 | U74: 16 | W74: ALTO | X74: APAGADO | Y74: NA | Z74: NA | AB74: SI | AC74: SI | AD74: veritas | AE74: Veritas-FullWed-Ret90_GYE_11 | AF74: -
J75: VIRTUAL | K75: TVC-SRV-ADIRGYE | L75: Servidor Active Directory Principal | M75: 192.168.59.235 | O75: SI | P75: - | Q75: Yurema Tobar / Mireya Iturralde | R75: Microsoft Windows Server 2016 | S75: 12 | T75: 200 | U75: 6 | V75: ALTO | W75: ALTO | X75: PRODUCCIÓN | Y75: NA | Z75: NA | AC75: SI | AD75: veritas | AE75: Veritas-FullFrid-Ret90_GYE_09 | AF75: -
J76: VIRTUAL | K76: TVC-SRV-ADIRGYE2 | L76: Servidor Active Directory Secundario | M76: 192.168.59.234 | O76: SI | P76: - | Q76: Yurema Tobar / Mireya Iturralde | R76: Microsoft Windows Server 2016 | S76: 8 | T76: 200 | U76: 4 | V76: ALTO | W76: BAJO | X76: PRODUCCIÓN | Y76: NA | Z76: NA | AC76: SI | AD76: veritas | AE76: Veritas-FullFrid-Ret90_GYE_09 | AF76: -
J77: VIRTUAL | K77: TVC-SRV-ADMCTX | L77: Servidor histórico para monitorear por 1 hora, 2 enlaces del balanceador que se considere más crítico o con mayor tráfico. Es parte del netscaler y permite el envió de notificaciones de las alertas de SSL. | M77: 192.168.9.225 | O77: - | P77: - | Q77: Yurema Tobar / Mireya Iturralde | R77: FreeBSD 11 - OTR 64bits | S77: 32 | T77: =120+512 -> 632 | U77: 8 | V77: ALTO | W77: MEDIO | X77: PRODUCCIÓN | Y77: NA | Z77: NA | AC77: SI | AE77: Veritas-Fulltue-Ret90_GYE_01 | AF77: -
J78: VIRTUAL | K78: TVC-SRV-ANUBIS | L78: Caja segura de claves NAC | M78: 192.168.59.118 | O78: - | P78: SI | Q78: Jose Fernandez | R78: Debian 12 - OTR 64bits | S78: 4 | T78: 100 | U78: 2 | V78: ALTO | W78: BAJO | X78: PRODUCCIÓN | Y78: NA | Z78: NA | AC78: SI | AD78: veritas | AE78: Veritas-FullWed-Ret90_GYE_02 | AF78: -
J79: VIRTUAL | K79: TVC-SRV-APP | L79: Despliegue de multiples aplicaciones (Inventario, Ficha medica, Sistema de grabaciones, y otras herramientas, keycloack) | M79: 192.168.59.131 | N79: 190.154.47.131 | O79: SI | P79: - | Q79: Administrador de aplicaciones / Carlos Ayala / Hector Miranda | R79: Microsoft Windows Server 2016 | S79: 6 | T79: 200 | U79: 6 | V79: ALTO | W79: MEDIO | X79: PRODUCCIÓN | Y79: NA | Z79: NA | AC79: SI | AD79: veritas | AE79: Veritas-FullWed-Ret90_GYE_02 | AF79: -
J80: VIRTUAL | K80: TVC-SRVAPPMOV | L80: servicio de notificaciones y App movil pruebas. (registro de nat. Confirmado por Hector Miranda) | M80: 192.168.59.117 | N80: 190.154.47.117 | O80: SI | P80: - | Q80: Hector Miranda | R80: Microsoft Windows Server 2016 | S80: 6 | T80: 200 | U80: 4 | V80: ALTO | W80: ALTO | X80: PRODUCCIÓN | Y80: NA | Z80: NA | AC80: SI | AD80: veritas | AE80: Veritas-FullWed-Ret90_GYE_02 | AF80: -
J81: VIRTUAL | K81: TVC-SRV-ARCOTEL | L81: Servidor para las funcionalides de ARCOTEL | M81: 192.168.59.56 | O81: SI | P81: - | Q81: Jose Fernandez/ Alejandro Alvarez | R81: Windows 10 PRO | S81: 16 | T81: 500 | U81: 6 | V81: ALTO | W81: ALTO | X81: PRODUCCIÓN | Y81: NA | Z81: NA | AC81: SI | AD81: veritas | AE81: Veritas-FullWed-Ret90_GYE_02
J82: VIRTUAL | K82: TVC-SRV-AXAP | L82: Servidor AXENTRIA | M82: 192.168.59.120 | O82: SI | P82: - | Q82: Graciela Ortiz | R82: Microsoft Windows Server 2016 | S82: 8 | T82: 200 300 1224 1024 | U82: 6 | V82: ALTO | W82: ALTO | X82: PRODUCCIÓN | Y82: NA | Z82: NA | AC82: SI | AD82: veritas | AE82: Veritas-FullWed-Ret90_GYE_02 | AF82: -
J83: VIRTUAL | K83: TVC-SRV-AXSP | L83: Base de Datos del Servidor AXENTRIA | M83: 192.168.59.121 | O83: SI | P83: - | Q83: Graciela Ortiz | R83: Microsoft Windows Server 2016 | S83: 24 | T83: 200 500 | U83: 6 | V83: ALTO | W83: ALTO | X83: PRODUCCIÓN | Y83: SQL SERVER | Z83: SQL Server 2019 Standard Edition SP1 | AC83: SI | AD83: veritas | AE83: Veritas-FullWed-Ret90_GYE_02 | AF83: -
J84: VIRTUAL | K84: TVC-SRV-AXWWW | L84: Servidor AXENTRIA - consultas WEB | M84: 192.168.59.122 | O84: SI | P84: - | Q84: Graciela Ortiz | R84: Microsoft Windows Server 2016 | S84: 8 | T84: 200 | U84: 4 | V84: ALTO | W84: ALTO | X84: PRODUCCIÓN | Y84: NA | Z84: NA | AC84: SI | AD84: veritas | AE84: Veritas-FullWed-Ret90_GYE_02 | AF84: -
J85: VIRTUAL | K85: TVC-SRV-CENTELEF | L85: Central Telefonia Nueva | M85: 192.168.59.152 | N85: 190.154.47.152 | O85: - | P85: - | Q85: Luis Conteron | R85: Sangoma Linux release 7.8.2003 (Core) -OTR | S85: 4 | T85: 50 | U85: 2 | V85: ALTO | W85: MEDIO | X85: PRODUCCIÓN | Y85: NA | Z85: NA | AC85: SI | AD85: veritas | AE85: Veritas-FullTue-Ret90_GYE_03 | AF85: -
J86: VIRTUAL | K86: TVC-SRV-CLUSTER1 | L86: Servidor para cluster DB (escritura y lectura) A LA ESPERA DE CONFIRMACION DE CAYALA | M86: 192.168.59.43 | O86: - | P86: SI | Q86: Christian Castillo / Carlos Ayala | R86: Red Hat Enterprise Linux 9.3 (64-bit) | S86: 8 | T86: =100+300 -> 400 | U86: 2 | W86: ALTO | X86: PRODUCCIÓN | Y86: MYSQL | Z86: MySQL 8 community edition | AD86: veritas | AE86: Veritas-FullTue-Ret90_GYE_03
J87: VIRTUAL | K87: TVC-SRV-CLUSTER2 | L87: Servidor para cluster DB (escritura y lectura) | M87: 192.168.59.38 | O87: - | P87: SI | Q87: Christian Castillo / Carlos Ayala | R87: Red Hat Enterprise Linux 9.3 (64-bit) | S87: 4 | T87: =100+300 -> 400 | U87: 2 | W87: ALTO | X87: PRODUCCIÓN | Y87: MYSQL | Z87: MySQL 8 community edition | AD87: veritas | AE87: Veritas-FullTue-Ret90_GYE_03
J88: VIRTUAL | K88: TVC-SRV-COLSOC | L88: Colector de log del SOC | M88: 192.168.59.119 | O88: - | P88: SI | Q88: Jose Fernandez | R88: Red Hat Enterprise Linux 9.3 (64-bit) | S88: 8 | T88: 250 | U88: 4 | V88: ALTO | W88: MEDIO | X88: PRODUCCIÓN | AD88: veritas | AE88: Veritas-FullTue-Ret90_GYE_03
J89: VIRTUAL | K89: TVC-SRV-CONTV | L89: Servidor para la consola de tv que se asignaran a las islas | M89: 192.168.59.58 | N89: 190.154.47.58 | O89: - | P89: SI | Q89: Elsa Garcia | R89: Microsoft Windows Server 2022 | S89: 16 | T89: 350 | U89: 2 | V89: ALTO | W89: MEDIO | X89: PRODUCCIÓN | Y89: NA | Z89: NA | AC89: SI | AD89: veritas | AE89: Veritas-FullFrid-Ret90_GYE_09 | AF89: APAHGAR
J90: VIRTUAL | K90: TVC-SRV-DBALL | L90: Servidor de base de datos para el balanceador. Mysql. de pruebas (confirmado ccastillo) | M90: 192.168.59.204 /IP VIRTUAL 59.52 | O90: - | P90: SI | Q90: Christian Castillo / Carlos Ayala | R90: Red Hat Enterprise Linux 9.3 (64-bit) | S90: 8 | T90: 150 300 | U90: 4 | V90: BAJO | W90: ALTO | X90: PREPRODUCCIÓN | Y90: MYSQL | Z90: MySQL 8 community edition | AC90: SI | AD90: veritas | AE90: Veritas-FullSun-Ret90_GYE_06 | AF90: -
J91: VIRTUAL | K91: TVC-SRV-DBALL1 | L91: Servidor de base de datos para el balanceador. Mysql | M91: 192.168.59.206 | O91: - | P91: SI | Q91: Christian Castillo / Carlos Ayala | R91: Red Hat Enterprise Linux 9.3 (64-bit) | S91: 12 | T91: 150 300 | U91: 16 | V91: ALTO | W91: ALTO | X91: PRODUCCIÓN | Y91: MYSQL | Z91: MySQL 8 community edition | AC91: SI | AD91: veritas | AE91: Veritas-FullSun-Ret90_GYE_06 | AF91: -
J92: VIRTUAL | K92: TVC-SRV-DBALL2 | L92: Servidor de base de datos para el balanceador. Mysql | M92: 192.168.59.207 | O92: - | P92: SI | Q92: Christian Castillo / Carlos Ayala | R92: Red Hat Enterprise Linux 9.3 (64-bit) | S92: 8 | T92: 150 300 | U92: 4 | V92: ALTO | W92: ALTO | X92: PRODUCCIÓN | Y92: MYSQL | Z92: MySQL 8 community edition | AC92: SI | AD92: veritas | AE92: Veritas-FullSun-Ret90_GYE_06 | AF92: -
J93: VIRTUAL | K93: TVC-SRV-DBAPP | L93: Servidor de Base de datos de multiples aplicaciones (Inventario, Ficha medica, Sistema de grabaciones, y otras herramientas) | M93: 192.168.59.137 | N93: 190.154.47.209 | O93: SI | P93: - | Q93: Carlos Ayala / Christian Castillo / Hector Miranda | R93: Microsoft Windows Server 2016 | S93: 12 | T93: 200 500 | U93: 4 | V93: ALTO | W93: ALTO | X93: PRODUCCIÓN | Y93: SQL SERVER | Z93: SQL Server 2019 Standard Edition SP1 | AC93: SI | AD93: veritas | AE93: Veritas-FullMon-Ret90_GYE_13 | AF93: -
J94: VIRTUAL | K94: TVC-SRVDBCRM | L94: Servidor DB CRM | M94: 192.168.59.202 | O94: SI | P94: - | Q94: Carlos Ayala / Christian Castillo / Hector Miranda | R94: Microsoft Windows Server 2016 | S94: 10 | T94: 200 500 | U94: 4 | V94: ALTO | W94: ALTO | X94: PRODUCCIÓN | Y94: SQL SERVER | Z94: SQL Server 2016 Standard Edition | AC94: SI | AD94: veritas | AE94: Veritas-FullThu-Ret90_GYE_04 | AF94: -
J95: VIRTUAL | K95: TVC-SRV-DBING | L95: Servidor de ingreso de contrato con su respectiva base de datos. | M95: 192.168.59.55 | N95: 190.154.47.55 | O95: - | P95: SI | Q95: Carlos Ayala / Christian Castillo / Hector Miranda | R95: Red Hat Enterprise Linux 9.2 (64-bit) | S95: 8 | T95: 250 | U95: 4 | V95: ALTO | W95: ALTO | X95: PRODUCCIÓN | Y95: NA | Z95: NA | AC95: SI | AD95: veritas | AE95: Veritas-FullThu-Ret90_GYE_04 | AF95: -
J96: VIRTUAL | K96: TVC-SRV-DBPANDORA | L96: Servidor de base de Datos de Pandora FMS Enterprise | M96: 192.168.59.113 | O96: - | P96: SI | Q96: Carlos Ayala / Christian Castillo / Yurema Tobar | R96: Red Hat Enterprise Linux 8 (64-bit) | S96: 16 | T96: 500 | U96: 8 | V96: ALTO | W96: ALTO | X96: PRODUCCIÓN | AC96: SI | AD96: veritas | AE96: Veritas-FullTue-Ret90_GYE_03 | AF96: -
J97: VIRTUAL | K97: TVC-SRV-DBSQL | L97: Servidor de base de datos para el balanceador. SQL SERVER | M97: 192.168.59.205 | O97: - | P97: SI | Q97: Carlos Ayala / Mauricio Rodriguez | R97: Microsoft Windows Server 2022 | S97: 12 | T97: =100+150+200 -> 450 | U97: 4 | V97: DAR DE BAJA | W97: DAR DE BAJA | X97: - | AC97: SI | AD97: veritas | AE97: Veritas-FullThu-Ret90_GYE_15 | AF97: -
J98: VIRTUAL | K98: TVC-SRV-DHCPGYE | L98: Servidor deDHCP para GYE. A la espera para cambiar el DHCP a este servidor. | M98: 192.168.59.84 | O98: - | P98: SI | Q98: Yurema Tobar / Mireya Iturralde | R98: Microsoft Windows Server 2022 | S98: 16 | T98: 100 | U98: 4 | V98: ALTO | W98: ALTO | X98: PRODUCCIÓN | Y98: NA | Z98: NA | AC98: NO | AD98: veritas | AE98: Veritas-FullTue-Ret90_GYE_03 | AF98: TODAVIA EL SERVIDOR NO PASA A PRODUCCIÓN
J99: VIRTUAL | K99: TVC-SRV-DISTRECOMMERCE | L99: Servidor para ECOMMERCE de ventas de terceros, para la autenticación de distribuidores de ventas. Para que la información de E-commerce de distribuidor no se mezcle con la información de E-commerce de servicio que está en producción. | M99: 192.168.59.127 | N99: 190.154.47.127 | O99: - | P99: SI | Q99: Administrador de aplicaciones / Hector Miranda | R99: Red Hat Enterprise Linux 9.2 (64-bit) | S99: 4 | T99: 120 | U99: 8 | V99: ALTO | W99: MEDIO | X99: PRODUCCIÓN | AC99: SI | AD99: veritas | AE99: Veritas-FullTue-Ret90_GYE_03 | AF99: -
J100: VIRTUAL | K100: TVC-SRV-DNACENTER | L100: Servidor pde DNA center, para administración global de todos los SW Cisco de GYE y UIO. | M100: 192.168.59.229 | O100: - | P100: - | Q100: Yurema Tobar / Mireya Iturralde | R100: Ubuntu - OVA | S100: 256 | T100: =100+550+2295 -> 2945 | U100: 32 | V100: ALTO | W100: BAJO | X100: PRODUCCIÓN | Y100: NA | Z100: NA | AC100: NO | AE100: Veritas-Fulltue-Ret90_GYE_01
J101: VIRTUAL | K101: TVC-SRV-ELASTICSEARCH | L101: Servicio de syslog y experiencia de usuario de pandora | M101: 192.168.59.25 | O101: - | P101: - | Q101: Yurema Tobar / Mireya Iturralde | R101: Rocky 8.7- OTR | S101: 6 | T101: 70 | U101: 2 | V101: ALTO | W101: BAJO | X101: PRODUCCIÓN | Y101: NA | Z101: NA | AC101: SI | AD101: veritas | AE101: Veritas-FullFrid-Ret90_GYE_09 | AF101: -
J102: VIRTUAL | K102: TVC-SRV-FLUENTD | L102: Servidor para centralizar todos los logs que se generan desde los microservicios y otros aplicativos. Se va a trabajar con el aplicativo “Fluentd” como “data collector” para lo cual es necesario alojarlo en un servidor. | M102: 192.168.59.86 | O102: - | P102: SI | Q102: Hector Miranda | R102: RedHat Enterprise Linux 9,4 | S102: 8 | T102: 100 | U102: 4 | V102: ALTO | W102: ALTO | X102: PRODUCCIÓN | Y102: NA | Z102: NA | AC102: SI | AD102: veritas | AE102: Veritas-FullThu-Ret90_GYE_04
J103: VIRTUAL | K103: TVC-SRV-FORTIMAGANERGYE | L103: Servidor de FortiManager | M103: 192.168.59.21 | O103: - | P103: - | Q103: Luis Conteron / Guillermo Jurado | R103: FortiManager-VM64 v7.4.3-build2487 240514 (GA) - OTR | S103: 16 | T103: 500 | U103: 4 | V103: ALTO | W103: ALTO | X103: PRODUCCIÓN | AC103: SI | AD103: veritas | AE103: Veritas-FullThu-Ret90_GYE_04 | AF103: -
J104: VIRTUAL | K104: TVC-SRV-FRONTCERT | L104: Para el nuevo portal de Ingreso de Contratos mismo que va a ser desarrollado por el proveedor NextGen (Ambiente PRODUCCION) | M104: 192.168.59.26 | N104: 190.154.47.26 | O104: - | P104: SI | Q104: Hector Miranda/Administrador de aplicaciones | R104: Ubuntu 22.04 LTS | S104: 2 | T104: 30 | U104: 2 | V104: ALTO | W104: MEDIO | X104: PRODUCCIÓN | Y104: NA | Z104: NA | AC104: SI | AD104: veritas | AE104: Veritas-FullMon-Ret90_GYE_13 | AF104: -
J105: VIRTUAL | K105: TVC-SRV-FRONTEND | L105: Servidor frontend para el nuevo desarrollo del módulo de promociones que se integrara con Tytan. | M105: 192.168.59.87 | O105: - | P105: SI | Q105: Mauricio Rodriguez/ | R105: Red Hat Enterprise Linux 9,4 | S105: 16 | T105: 200 | U105: 4 | V105: Bajo | W105: BAJO | X105: PREPRODUCCIÓN | Y105: NA | Z105: NA | AC105: SI | AD105: Veeam Backup | AE105: Veritas-FullThu-Ret90_GYE_04 | AF105: -
J106: VIRTUAL | K106: TVC-SRV-FRONTTEST | L106: Para desarrollo de los sistemas de contratos web, portal unificado y otros aplicativos internos. | M106: 192.168.59.27 | O106: - | P106: SI | Q106: Mauricio Rodriguez/Administardor de aplicaciones | R106: Ubuntu 22.04 LTS | S106: 2 | T106: 30 | U106: 2 | W106: MEDIO | X106: PREPRODUCCIÓN | AD106: veritas | AE106: Veritas-FullThu-Ret90_GYE_04
...

Sheet Licencia Red Hat
B3: DESCRIPCIÓN | E3: TIPO DE LICENCIA | F3: CANTIDAD | G3: CONTRATO | H3: CADUCA | L3: DESCRIPCIÓN | O3: TIPO DE LICENCIA | P3: CANTIDAD | Q3: CONTRATO | R3: CADUCA | S3: OBSERVACION
B4: LICENCIA PARA LOS 4 HOST DEL C7000 GYE | E4: DATACENTER | F4: 4 | L4: LICENCIA PARA LOS 3 HOST DEL C7000 GYE - TEC | O4: DATACENTER PREIMUN | P4: 3 | Q4: 17020451 | R4: 45744 | S4: NO RENOVAR, SE COMPRO EN MARZO 2024
B5: ProLiant DL380 Gen10 | C5: 192.168.9.28 | D5: NODO DEL SIMPLIVITY GYE | E5: UTIL PORQUE TENEMOS SRV VIRTUALES CON RED HAT | G5: 11025116 | H5: 45481 | L5: BL460C | M5: 192.168.94.37 | N5: BLADE DEL C7000
B6: ProLiant DL380 Gen10 | C6: 192..168.9.30 | D6: NODO DEL SIMPLIVITY GYE | G6: 11025116 | H6: 45481 | L6: BL460C | M6: 192.168.94.38 | N6: BLADE DEL C7000
B7: ProLiant DL380 Gen10 | C7: 192.168.9.32 | D7: NODO DEL SIMPLIVITY GYE | G7: 16832113 | H7: 45500 | L7: BL460C | M7: 192.168.94.39 | N7: BLADE DEL C7000
B8: ProLiant DL380 Gen10 | C8: 192.168.9.34 | D8: NODO DEL SIMPLIVITY GYE | G8: 16832113 | H8: 45500 | L8: LICENCIAS PARA HOSTS DEL C7000 - UIO TEC | O8: HOST AND VIRTUAL STANDARD | P8: 2 | Q8: 16810868 | R8: 45489 | S8: ACTUALIZAR LA FECHA POR PARTE DE CONECTA
B9: LICENCIA PARA LOS 2 NODOS DEL SIMPLIVITY UIO | E9: DATACENTER | F9: 4 | L9: BL460C | M9: tec-iway-db | N9: BLADE DEL C7000
B10: ProLiant DL380 | C10: 192.168.34.160 | D10: NODO DEL SIMPLIVITY UIO | E10: UTIL PORQUE TENEMOS SRV VIRTUALES CON RED HAT | G10: 16832113 | H10: 45500 | L10: BL460C | M10: tec-iway-db-backup | N10: BLADE DEL C7000
B11: ProLiant DL380 | C11: 192.168.34.162 | D11: NODO DEL SIMPLIVITY UIO | G11: 16832113 | H11: 45516
B12: ProLiant DL380 | C12: 192.168.34.164 | D12: NODO DEL SIMPLIVITY UIO | G12: 17020451 | H12: 45744 | T12: DATACENTER - 9 | V12: OBSERVACIÓN
B13: ProLiant DL380 | C13: 192.168.34.166 | D13: NODO DEL SIMPLIVITY UIO | G13: 17020451 | H13: 45744 | T13: SIMPLIVITY GYE | U13: 4
B14: STAND ALONE GYE | E14: HOST AND VIRTUAL | F14: 2 | L14: TOTAL DE LICENCIAS DATACENTER PREMIUM | P14: =P4 -> 3 | T14: SIMPLIVITY UIO | U14: 2 | V14: + 2 Renovadas en Marzo
B15: BL460C | C15: 192.168.59.10 | D15: BASE DE DATOS DEL FSM | E15: NO ES NECESARIO | G15: - | H15: - | T15: C7000 GYE - VMWARE | U15: 1
B16: SUN FIRE X4275 | C16: 140.27.120.165 | D16: TVC-INSIGHT1 | E16: APAGADO | G16: - | H16: - | L16: TOTAL DE LICENCIAS HOST AND VIRTUAL PREMIUM | P16: =P8 -> 2
B17: SUN FIRE X4275 | C17: 140.27.120.164 | D17: TVC-INSIGHT2 | E17: AUN UTILIZADA | F17: USADAS - consume 2 | G17: 14254849 | H17: 45498
B18: ODA X8-2HA UIO | E18: HOST AND VIRTUAL | F18: 8 | T18: VIRTUAL NODES - 7 | V18: OBSERVACIÓN
B19: ODA X8-2HA | C19: 192.168.21.120 | D19: DPS - 192.168.21.147 | E19: NO PERMITE SUSCRIBIRLA | T19: TVC-INSIGHT1 - GYE | U19: 1 | V19: APAGADO
B20: ODA X8-2HA | C20: 192.168.21.122 | D20: INSIGHT - 192.168.31.200 | N20: DATACENTER | O20: 9 | T20: TVC-INSIGHT2 - GYE | U20: 1
D21: JBOSS - 192.168.21.175 | N21: VIRTUAL NODES | O21: 7 | T21: C7000 GYE - DB FLASH COPY | U21: 1
D22: INSIGHT - 192.168.31.190 | T22: tvc-srv-dbfsm - Base Datos FSM | U22: 1
B23: LICENCIAS PARA HOSTS DEL C7000 - UIO | E23: DATACENTER | F23: 3 | T23: tvc-srv-dbfin - Base de datops Iperk | U23: 1
B24: BL460 - C7000 | C24: 192.168.21.146 | D24: tvc-srv-nver - Comarch Revitalizacion | E24: NO PERMITE SUSCRIBIRLA | G24: - | H24: - | T24: Dataware House Aplicación | U24: 1 | V24: APAGADO
B25: ProLiant BL460c Gen8 | C25: srv-esx-ti1 | D25: BLADE DEL C7000 - TI | E25: NO ES NECESARIO | G25: 16832113 | H25: 45517 | T25: ODA NODO 1 | U25: 1
B26: ProLiant BL460c Gen8 | C26: srv-esx-ti2 | D26: BLADE DEL C7000 - TI | G26: 16832113 | H26: 45517 | T26: ODA NODO 2 | U26: 1
B27: ProLiant BL460c Gen8 | C27: srv-esx-ti3 | D27: BLADE DEL C7000 - TI | G27: 16832113 | H27: 45517 | T27: tvc-srv-nver - Comarch Revitalizacion 21.146 | U27: 1
B28: BL460 - C7000 | C28: 192.168.34.118 | D28: Servidor base de datos para Data WareHouse Nuevo - 192.168.21.238 - tvc-srv-bddw | E28: APAGADO | G28: - | H28: -
B29: STAND ALONE UIO | E29: HOST AND VIRTUAL | F29: 4
B30: BL460 - C7000 | C30: 192.168.21.124 | D30: tvc-srv-dbfsm - Base Datos FSM | F30: USADAS - consume 2 | G30: 14254849 | H30: 45498
B31: DL380 | C31: 192.168.21.144 | D31: tvc-srv-dbfin - Base de datops Iperk | F31: USADAS - consume 2 | G31: 14254849 | H31: 45498
B32: SUNFIRE X4275 | C32: 192.168.21.142 | D32: tvc-srv-dtwhapp - Dataware House Aplicación | F32: NO USADA - APAGADA
B33: TOTAL DE LICENCIAS DATACENTER STANDARD | F33: =F4+F9+F23 -> 11
B35: TOTAL DE LICENCIAS HOST AND VIRTUAL STANDARD (7), SI SE USA EN VIRTUAL SERIA 14 SOCKET DISPONIBLE | F35: =F14+F18+F29 -> 14
A40: CANTIDAD | B40: Contract Number | C40: Subscription Number | D40: Product | E40: INICIA | F40: CADUCA
A41: 2 | B41: 17105221 | C41: 15169612 | D41: Red Hat Enterprise Linux for Virtual Datacenters, Standard | E41: 45482 | F41: 45846
A42: 7 | B42: 17105223 | C42: 15169619 | D42: Red Hat Enterprise Linux Server, Standard (Physical or Virtual Nodes) | E42: 45499 | F42: 45863
A43: 3 | B43: 17105221 | C43: 15169621 | D43: Red Hat Enterprise Linux for Virtual Datacenters, Standard | E43: 45500 | F43: 45864
A44: 4 | B44: 17105221 | C44: 15169620 | D44: Red Hat Enterprise Linux for Virtual Datacenters, Standard | E44: 45517 | F44: 45881
A45: 2 | B45: 17282215 | C45: 16522476 | D45: Red Hat Enterprise Linux for Virtual Datacenters, Standard | E45: 45744 | F45: 45835
A46: 1 | B46: 17240106 | C46: 15975544 | D46: Red Hat Ansible Automation Platform, Standard (100 Managed Nodes) | E46: 45705 | F46: 46069

Sheet Hoja1
C4: DESCRIPCIÓN | F4: TIPO DE LICENCIA | G4: CANTIDAD | H4: CONTRATO | I4: CADUCA
C5: LICENCIA PARA LOS 4 HOST DEL C7000 GYE | F5: DATACENTER | G5: 4
C6: ProLiant DL380 Gen10 | D6: 192.168.9.28 | E6: NODO DEL SIMPLIVITY GYE | F6: UTIL PORQUE TENEMOS SRV VIRTUALES CON RED HAT | H6: 11025116 | I6: 45481
C7: ProLiant DL380 Gen10 | D7: 192..168.9.30 | E7: NODO DEL SIMPLIVITY GYE | H7: 11025116 | I7: 45481
C8: ProLiant DL380 Gen10 | D8: 192.168.9.32 | E8: NODO DEL SIMPLIVITY GYE | H8: 16832113 | I8: 45500
C9: ProLiant DL380 Gen10 | D9: 192.168.9.34 | E9: NODO DEL SIMPLIVITY GYE | H9: 16832113 | I9: 45500
C10: LICENCIA PARA LOS 2 NODOS DEL SIMPLIVITY UIO | F10: DATACENTER | G10: 4
C11: ProLiant DL380 | D11: 192.168.34.160 | E11: NODO DEL SIMPLIVITY UIO | F11: UTIL PORQUE TENEMOS SRV VIRTUALES CON RED HAT | H11: 16832113 | I11: 45500
C12: ProLiant DL380 | D12: 192.168.34.162 | E12: NODO DEL SIMPLIVITY UIO | H12: 16832113 | I12: 45517
C13: ProLiant DL380 | D13: 192.168.34.164 | E13: NODO DEL SIMPLIVITY UIO | H13: 16832113 | I13: 45517
C14: ProLiant DL380 | D14: 192.168.34.166 | E14: NODO DEL SIMPLIVITY UIO | H14: 17020451 | I14: 45744
C15: STAND ALONE GYE | F15: HOST AND VIRTUAL | G15: 3
C16: BL460C | D16: 192.168.59.10 | E16: BASE DE DATOS DEL FSM | F16: AUN UTILIZADA | H16: 14254849 | I16: 45498
C17: SUN FIRE X4275 | D17: 140.27.120.165 | E17: TVC-INSIGHT1 | F17: APAGADO
C18: SUN FIRE X4275 | D18: 140.27.120.164 | E18: TVC-INSIGHT2 | F18: AUN UTILIZADA | H18: 14254849 | I18: 45498

Sheet Licencia Vmware
A2: COVERED ITEM | B2: CLAVE DE LICENCIA | C2: HOST ASIGNADOS | D2: AIGNADO A | E2: NOMBRE DE LA LICENCIA EN VCENTER | F2: CANTIDAD | G2: End Date | H2: FECHA DEL CONTRATO
A3: VMware vSphere 7 Standard for 1 processor | B3: N4010-8MJ96-K8CGX-0638H-1N90M | C3: tvc-nodo1gye.grupotvcable.com tvc-nodo3gye.grupotvcable.com tvc-nodo4gye.grupotvcable.com 140.27.120.49 140.27.120.50 140.27.120.51 140.27.120.52 140.27.120.53 | D3: SIMPLIVITY GYE Y C7000 - GYE | E3: License 1 (493309718) | F3: 14 | G3: 45532 | H3: 46626
A4: VMware vSphere 6 Standard | B4: 1J6C1-FW386-U8P8A-0930M-1NN0N | C4: 192.168.34.126 | D4: C7000 - UIO TI | E4: License 6 (4100161721) | F4: 1 | G4: 45317 | H4: 45535 | I4: REVISARLAS CON GUILLE
A5: VMware vCenter Server 7 Standard for vSphere 7 (Per Instance) | B5: 1501J-69087-58JG2-010AP-C8MQH | C5: vCenter Server 7 Standard - UIO 192.168.21.9 | D5: VCENTER UIO | E5: License 7 VCENTERUIO(42551574) | F5: 1 | G5: 45532 | H5: 46626
A6: VMware vSphere 6 Standard | B6: 1J2AL-FW3D6-U8Q82-0ACAH-185KJ | C6: 192.168.34.120 | D6: C7000 - UIO TI | E6: License 5 (4100161721) | F6: 1 | G6: 45317 | H6: 45535 | I6: REVISARLAS CON GUILLE
A7: VSPHERE 6 STANDARD FOR 1 PROCESSOR | B7: MN01K-8ML46-683GN-0UCAM-10CKM | C7: tvc-srv-esx3.grupotvcable.com tvc-srv-esx4.grupotvcable.com tvc-nodo2gye.grupotvcable.com | D7: SIMPLIVITY - UIO | E7: License 8 (4102347659) | F7: 6 | G7: 45532 | H7: 46626
A8: vSphere 7 Standard | B8: MH20J-6MJDH-J8KGJ-0T826-1TP4H | C8: tvc-srv-esx1.grupotvcable.com tvc-srv-esx2.grupotvcable.com | D8: SIMPLIVITY - UIO Y GYE | E8: License 2 (4126837669) | F8: 4 | G8: 45532 | H8: 46626
A9: VMware vSphere 7 Standard for 1 processor | B9: 5M6A3-AWJ4M-U8Q83-0UCRK-8W50J | C9: 19216834118 | D9: C7000 - UIO TI | E9: License 9 (472912554) | F9: 1 | G9: 45535 | H9: 45535 | I9: REVISARLAS CON GUILLE
A10: VMware vSphere 6 Standard | B10: 55420-FWK16-F8D8X-0UA20-1802J | C10: 192.168.34.11 192.168.34.12 192.168.34.13 | D10: C7000 - UIO TEC | E10: License 3 (4137718595) | F10: 6 | G10: 44974 | H10: 45535 | I10: REVISARLAS CON GUILLE
A11: vCenter Server 7 Standard | B11: 14490-A914P-28VG2-0V8KP-3M635 | C11: vCenter Server 7 Standard - GYE 192.168.59.130 | D11: VCENTER GYE | E11: License 4 VCENTERGYE(472912554) | F11: 1 | G11: 45532 | H11: 46626
A12: vCenter vsphere 8 Standard- Suscripción | B12: WJ49M-8CKD2-588N9-015A4-3RK70 | C12: TVC-SRV-VCENTERCLOUD - GYE 192.168.59.17 | D12: VCENTER GYE | E12: License 10 vcenter (26179750) | F12: 1 | G12: 45330 | H12: 45696 | I12: EXPIRADA
A13: vCenter Server 8 Standard- Suscripción | B13: W468M-2009K-J89P8-0JE04-3D0L0 | C13: srv-esx-tec1 - 192.168.94.41 srv-esx-tec2 - 192.168.94.42 srv-esx-tec3 - 192.168.94.43 | D13: BLADE C7000 - TEC | E13: License 11 (26179750) | F13: 96 | G13: 45330 | H13: 45696 | I13: EXPIRADA
A16: PLATAFORMA | B16: HOST ASIGNADOS | C16: LICENCIA POR CONTRATO | D16: HOST | E16: SOCKET | F16: NUCLEO DE PROCESADOR DE DOCKET | G16: CORE VIRTUAL (SOCKET X NUCLEO) | H16: LOGICO PROCESADOR | I16: CORE FISICO | J16: PROCESADOR CONTRATADO
A17: SIMPLIVITY GYE | B17: tvc-nodo1gye.grupotvcable.com | C17: License 1 (493309718) | D17: 4 | E17: 2 | F17: 22 | G17: 44 | H17: 88 | I17: 176 | J17: 352
B18: tvc-nodo2gye.grupotvcable.com | E18: 2 | F18: 22 | G18: 44 | H18: 88
B19: tvc-nodo3gye.grupotvcable.com | E19: 2 | F19: 22 | G19: 44 | H19: 88
B20: tvc-nodo4gye.grupotvcable.com | C20: License 8 (4102347659) | E20: 2 | F20: 22 | G20: 44 | H20: 88
A21: SIMPLIVITY UIO | B21: tvc-srv-esx1.grupotvcable.com | C21: License 2 (4126837669) | D21: 2 | E21: 2 | F21: 20 | G21: 40 | H21: 80 | I21: 168 | J21: 336
B22: tvc-srv-esx2.grupotvcable.com | E22: 2 | F22: 20 | G22: 40 | H22: 80
B23: tvc-srv-esx3.grupotvcable.com | C23: License 8 (4102347659) | D23: 2 | E23: 2 | F23: 22 | G23: 44 | H23: 88
B24: tvc-srv-esx4.grupotvcable.com | C24: License 8 (4102347659) | E24: 2 | F24: 22 | G24: 44 | H24: 88
A25: C7000 - TI GYE | B25: SRV-ESX-TI1 | C25: License 1 (493309718) | D25: 2 | E25: 2 | F25: 8 | G25: 16 | H25: 32 | I25: =SUM(G25:G26) -> 32 | J25: =SUM(H25:H26) -> 64
B26: SRV-ESX-TI2 | E26: 2 | F26: 8 | G26: 16 | H26: 32
A27: VCENTER | B27: VCENTER GYE | C27: License 4 VCENTERGYE(472912554) | D27: -
B28: VCENTERUIO | C28: License 7 VCENTERUIO (42551574) | D28: - | E28: TOTAL | I28: =SUM(I17:I26) -> 376 | J28: =SUM(J17:J26) -> 752

Sheet Resumen
B4: QUITO
B5: Total SRV Fisicos | C5: =UIO!F173 -> 26
B6: Total SRV Virtuales | C6: =UIO!I173 -> 144
B7: Total Servidores | C7: =SUM(C5:C6) -> 170
B10: GUAYAQUIL | E10: NAC
B11: Total SRV Fisicos | C11: =GYE!F168 -> 25 | E11: FISICO NAC | F11: =C5+C11 -> 51
B12: Total SRV Virtuales | C12: =GYE!I168 -> 140 | E12: VIRTUAL NAC | F12: =C12+C6 -> 284
B13: Total Servidores | C13: =SUM(C11:C12) -> 165 | E13: TOTAL SRV NAC | F13: =C7+C13 -> 335
B16: SISTEMAS CRITICOS NIVEL ALTO A NIVEL NACIONAL | D16: SRV VIRTUAL | E16: CAPACIDAD - SRV VIRTUAL | F16: SRV FISICO | G16: CAPACIDAD - SRV FISICO
B17: GUAYAQUIL | C17: =COUNTIF(GYE!W7:W163,"ALT*") -> 90 | D17: =COUNTIFS(GYE!W7:W163,"ALT*",GYE!J7:J163,"VIRTU*") -> 87 | E17: =SUMIFS(GYE!T7:T163,GYE!W7:W163,"ALT*",GYE!J7:J163,"VIRT*") -> 34373.19 | F17: =COUNTIFS(GYE!W7:W163,"ALT*",GYE!J7:J163,"FISI*") -> 3 | G17: =SUMIFS(GYE!T7:T163,GYE!W7:W163,"ALT*",GYE!J7:J163,"FISI*") -> 35680
B18: QUITO | C18: =COUNTIF(UIO!V8:V154,"ALT*") -> 104 | D18: =COUNTIFS(UIO!V8:V169,"ALT*",UIO!J8:J169,"VIRTU*") -> 105 | E18: =SUMIFS(UIO!T8:T169,UIO!V8:V169,"ALT*",UIO!J8:J169,"VIRTU*") -> 64964.5 | F18: =COUNTIFS(UIO!V8:V169,"ALT*",UIO!J8:J169,"FISI*") -> 10 | G18: =SUMIFS(UIO!T8:T169,UIO!V8:V169,"ALT*",UIO!J8:J169,"FIS*") -> 8200
B19: TOTAL | C19: =SUM(C17:C18) -> 194
B21: SISTEMAS CRITICOS NIVEL MEDIO A NIVEL NACIONAL | D21: SRV VIRTUAL | E21: CAPACIDAD - SRV VIRTUAL | F21: SRV FISICO | G21: CAPACIDAD - SRV FISICO
B22: GUAYAQUIL | C22: =COUNTIF(GYE!W7:W163,"MEDI*") -> 33 | D22: =COUNTIFS(GYE!W7:W163,"MED*",GYE!J7:J163,"VIRTU*") -> 30 | E22: =SUMIFS(GYE!T7:T163,GYE!W7:W163,"MED*",GYE!J7:J163,"VIRT*") -> 6862 | F22: =COUNTIFS(GYE!W7:W163,"MED*",GYE!J7:J163,"FISI*") -> 3 | G22: =SUMIFS(GYE!T7:T163,GYE!W7:W163,"MED*",GYE!J7:J163,"FIS*") -> 13488
B23: QUITO | C23: =COUNTIF(UIO!V8:V154,"MEDI*") -> 16 | D23: =COUNTIFS(UIO!V8:V169,"MED*",UIO!J8:J169,"VIRTU*") -> 16 | E23: =SUMIFS(UIO!T8:T169,UIO!V8:V169,"MED*",UIO!J8:J169,"VIRTU*") -> 5537.27 | F23: =COUNTIFS(UIO!V8:V168,"MED*",UIO!J8:J168,"FIS*") -> 1 | G23: =SUMIFS(UIO!T8:T168,UIO!V8:V168,"MED*",UIO!J8:J168,"FIS*") -> 7800
B24: TOTAL | C24: =SUM(C22:C23) -> 49
B26: SISTEMAS CRITICOS NIVEL BAJO A NIVEL NACIONAL | D26: SRV VIRTUAL | E26: CAPACIDAD - SRV VIRTUAL | F26: SRV FISICO | G26: CAPACIDAD - SRV FISICO
B27: GUAYAQUIL | C27: =COUNTIF(GYE!W7:W163,"BAJ*") -> 23 | D27: =COUNTIFS(GYE!W7:W163,"BAJO*",GYE!J7:J163,"VIRTU*") -> 22 | E27: =SUMIFS(GYE!T7:T163,GYE!W7:W163,"BAJ*",GYE!J7:J163,"VIRT*") -> 5905 | F27: =COUNTIFS(GYE!W7:W163,"BAJ*",GYE!J7:J163,"FISI*") -> 1 | G27: =SUMIFS(GYE!T7:T163,GYE!W7:W163,"BAJ*",GYE!J7:J163,"FIS*") -> 1200
B28: QUITO | C28: =COUNTIF(UIO!V8:V154,"BAJ*") -> 25 | D28: =COUNTIFS(UIO!V8:V168,"BAJ*",UIO!J8:J168,"VIRTU*") -> 25 | E28: =SUMIFS(UIO!T8:T168,UIO!V8:V168,"BAJ*",UIO!J8:J168,"VIRTU*") -> 20510.856 | F28: =COUNTIFS(UIO!V8:V168,"BAJ*",UIO!J8:J168,"FIS*") -> 1 | G28: =SUMIFS(UIO!T8:T168,UIO!V8:V168,"BAJ*",UIO!J8:J168,"FIS*") -> 600
B29: TOTAL | C29: =SUM(C27:C28) -> 48
B31: SISTEMAS CRITICOS NIVEL DAR DE BAJA A NIVEL NACIONAL | D31: SRV VIRTUAL | E31: CAPACIDAD - SRV VIRTUAL | F31: SRV FISICO | G31: CAPACIDAD - SRV FISICO
B32: GUAYAQUIL | C32: =COUNTIF(GYE!W7:W163,"DAR*") -> 3 | D32: =COUNTIFS(GYE!W7:W163,"DAR*",GYE!J7:J163,"VIRTU*") -> 2 | E32: =SUMIFS(GYE!T7:T163,GYE!W7:W163,"DAR*",GYE!J7:J163,"VIRT*") -> 528 | F32: =COUNTIFS(GYE!W7:W163,"DAR*",GYE!J7:J163,"FISI*") -> 1 | G32: =SUMIFS(GYE!T7:T163,GYE!W7:W163,"DAR*",GYE!J7:J163,"FIS*") -> 1200
B33: QUITO | C33: =COUNTIF(UIO!V8:V168,"DAR*") -> 0 | D33: =COUNTIFS(UIO!V8:V168,"DAR*",UIO!J8:J168,"VIRTU*") -> 0 | E33: =SUMIFS(UIO!T8:T168,UIO!V8:V168,"DAR*",UIO!J8:J168,"VIRTU*") -> 0 | F33: =COUNTIFS(UIO!V8:V168,"DAR*",UIO!J8:J168,"FIS*") -> 0 | G33: =SUMIFS(UIO!T8:T168,UIO!V8:V168,"DAR*",UIO!J8:J168,"FIS*") -> 0
B34: TOTAL | C34: =SUM(C32:C33) -> 3
B36: SERVIDORES A NIVEL NACIONAL
B37: Total SRV Fisicos | C37: =SUM(C5,C11) -> 51
B38: Total SRV Virtuales | C38: =SUM(C6,C12) -> 284
B39: Total Servidores | C39: =SUM(C37:C38) -> 335
B42: SOPORTE TERCEROS | C42: tecnoav,comware,asic
B43: costo soporte terceros | C43: =SUM(GYE!AA168+UIO!Z160) -> 5690 | D43: USD
B45: SRV MICROSOFT | E45: SRV RED HAT- SIMPLIVTY | H45: SRV DE DISTRIBUCION LINUX - SIMPLIVITY | K45: SR DEL SIMPLVITY
B46: GUAYAQUIL | C46: =COUNTIFS(GYE!R7:R163,"*WIND*") -> 47 | E46: GUAYAQUIL | F46: =COUNTIFS('GYE 2025'!S45:S156,"*RED*") -> 23 | H46: GUAYAQUIL | I46: =COUNTIFS('GYE 2025'!S45:S156,"*RED*")+COUNTIFS('GYE 2025'!S45:S156,"*OTR*")+COUNTIFS('GYE 2025'!S45:S156,"*UBU*")+COUNTIFS('GYE 2025'!S45:S156,"*DEBI*")+COUNTIFS('GYE 2025'!S45:S156,"*CEN*") -> 71 | K46: GUAYAQUIL | L46: ='GYE 2025'!I45 -> 112
B47: QUITO | C47: =COUNTIFS(UIO!R8:R154,"*WIND*") -> 58 | E47: QUITO | F47: =COUNTIFS('UIO 2025'!S8:S97,"*RED*") -> 31 | H47: QUITO | I47: =COUNTIFS('UIO 2025'!S8:S97,"*RED*")+COUNTIFS('UIO 2025'!S8:S97,"*OTR*")+COUNTIFS('UIO 2025'!S8:S97,"*UBU*")+COUNTIFS('UIO 2025'!S8:S97,"*DEBI*")+COUNTIFS('UIO 2025'!S8:S97,"*CENT*") -> 42 | K47: QUITO | L47: ='UIO 2025'!I8 -> 89
B48: TOTAL DE SRV MICROSOFT | C48: =SUM(C46:C47) -> 105 | E48: TOTAL DE SRV RED HAT | F48: =SUM(F46:F47) -> 54 | H48: TOTAL | I48: =SUM(I46:I47) -> 113 | K48: TOTAL | L48: =SUM(L46:L47) -> 201
B51: SERVIDOR DEL SIMPLIVITY NAC
B52: GUAYAQUIL | C52: =GYE!I56 -> 96
B53: QUITO | C53: =UIO!I8 -> 99
B54: TOTAL DE SRV | C54: =C52+C53 -> 195
